Workbook

Sheet All Board Credits & Important U
A1: Credits | D1: Stadiums of all boards
A2: Boards | B2: Available Credits | D2: Australia | E2: Bangladesh | F2: England | G2: India | H2: Italy | I2: Netherlands | J2: Newzealand | K2: Pakistan | L2: Qatar | M2: Scotland | N2: South Africa | O2: Srilanka | P2: UAE | Q2: West Indies | R2: Zimbabwe | S2: Canada
A3: Scotland | B3: =Scotland!A4 -> 17724615 | D3: {=Australia!B7:B19} -> Level 3 Stadiums | E3: {=Bangladesh!B8:B20} -> Level 3 Stadiums | F3: {=England!B10:B28} -> Level 3 Stadiums | G3: {=India!B7:B16} -> Level 3 Stadiums | H3: {=Italy!B7:B15} -> Level 3 Stadiums | I3: {=Netherlands!B7:B17} -> Level 3 Stadiums | J3: {=Newzealand!B8:B19} -> Level 3 Stadiums | K3: {=Pakistan!B7:B19} -> Level 3 Stadiums | L3: {=Qatar!B8:B19} -> Level 3 Stadiums | M3: {=Scotland!C7:C18} -> Level 3 Stadiums | N3: {=SA!B9:B20} -> Level 3 Stadiums | O3: {=Srilanka!B7:B18} -> Level 3 Stadiums | P3: {=UAE!B7:B18} -> Level 3 Stadiums | Q3: {=WestIndies!B8:B21} -> Level 3 Stadiums | R3: {=Zimbabwe!C7:C19} -> Level 3 Stadiums | S3: {=Canada!B7:B18} -> Level 3 Stadiums
A4: Australia | B4: =Australia!A4 -> 6851560 | D4: Melbourne Cricket Ground | E4: Padma - Meghna Cricket Arena | F4: Lords International Stadium | G4: Eternal Coliseum | H4: Vivian Richards Cricket Ground | I4: Maya Stadium Amsterdam | J4: Eden Park | K4: Pindi International Stadium | L4: West End Park | M4: Grange Cricket Stadium | N4: Newlands Cricket Stadium | O4: Colombo International Stadium | P4: Dubai International Stadium | Q4: ABD Georgetown Cricket Arena | R4: Mosi-oa-Tunya ICS | S4: CAA Centre
A5: Newzealand | B5: =Newzealand!A5 -> 4298385 | D5: Sydney Cricket Ground | E5: Hilsha Heritage Stadium | Franchise League L1 | Upgraded | F5: WGG International Stadium | G5: Sree Padmanaba Cricket Park | H5: Ovale di Carteria | I5: Dutch Cricket Arena Hague | J5: Sky International Stadium | K5: Karachi International Stadium | L5: Lusail International Stadium | M5: Seven Oaks Stadium | N5: Wanderers International Stadium | O5: Kandy International Stadium | P5: Level 2 Stadiums | Q5: Malayalipuram International Stadium | R5: Lachit Borphukan Cricket Stadium | S5: Level 2 Stadiums
A6: Bangladesh | B6: =Bangladesh!A5 -> 5510745 | D6: Optus Stadium | Free T20 WC | E6: Karnaphuli Cricket Park | F6: The Rose Bowl | G6: Jannat Wadi | Franchise League L1 | Upgraded | H6: Level 2 Stadiums | I6: Zubeen Garg Heritage Stadium | J6: Sovereign Crown Arena | K6: Gaddafi Stadium Lahore | Franchise League L1 | Upgraded | L6: Doha International Stadium | M6: Scotba Cricket Stadium | L1 FL | UP | N6: Level 2 Stadiums | O6: Level 2 Stadiums | P6: None | Q6: Bridgetown Royal Cricket Arena | Franchise League L1 | Upgraded | R6: Level 2 Stadiums | S6: None
A7: India | B7: =India!A4 -> 3852710 | D7: Adelaide Oval | E7: Mango Fortress Stadium | F7: Trent Bridge | Franchise League L1 | Upgraded | G7: Level 2 Stadiums | H7: None | I7: Pragjyotish Ground | J7: Thunder Dome | K7: Multan International Stadium | L7: Level 2 Stadiums | M7: K.M Cricket Arena | N7: None | O7: None | P7: Level 1 Stadiums | Q7: Basseterre Patriots Cricket Ground | R7: None | S7: Level 1 Stadiums
A8: Pakistan | B8: =Pakistan!A4 -> 6798500 | D8: Sydney Show Ground | Franchise League L1 | Upgraded | E8: Sylhet Jewel Stadium | F8: The Oval | G8: None | H8: Level 1 Stadiums | I8: Nilachal Khel Pathar | J8: Inferno Bay Arena | K8: Hyder Cricket Stadium | L8: None | M8: Level 2 Stadiums | N8: Level 1 Stadiums | O8: Level 1 Stadiums | P8: None | Q8: Kingstown Volcano Cricket Stdaium | R8: Level 1 Stadiums | S8: None
A9: England | B9: =England!A7 -> 3834985 | D9: Marvel Cricket Stadium | E9: Sundarbans Cricket Fortress | F9: Old Trafford | G9: Level 1 Stadiums | H9: None | I9: Level 2 Stadiums | J9: Ironhold Park | K9: Quetta Cricket Arena | L9: Level 1 Stadiums | M9: None | N9: None | O9: None | Q9: Port of Spain Knights Arena | R9: None
A10: Srilanka | B10: =Srilanka!A4 -> 1654300 | D10: The Gabba | E10: Sonar Bangla Cricket Arena | F10: Yorkshire Headingley | G10: Prince's Arena | I10: None | J10: Alpine Crown Arena | K10: Karakoram Stadium Skardu | L10: None | M10: Level 1 Stadiums | Q10: Kingston Kings Cricket Stadium
A11: Qatar | B11: =Qatar!A5 -> 5621460 | D11: Ninja Stadium Hobart | E11: Sands cox's Bazar | F11: Somerset County Ground | G11: Lion's Citadel | I11: Level 1 Stadiums | J11: Titan Bay Coliseum | Franchise League L1 | Ugraded | K11: Khyber Stadium Peshawar | M11: None | Q11: St. John's Falcon Cricket Arena
A12: West Indies | B12: =WestIndies!A5 -> 6625225 | D12: Level 2 Stadiums | E12: Level 2 Stadiums | F12: Level 2 Stadiums | G12: Master's Arena | I12: None | J12: Level 2 Stadiums | K12: Level 2 Stadiums | Q12: Hayley Matthews IS
A13: Italy | B13: =Italy!A4 -> 1781475 | D13: None | E13: None | F13: Middlesex Lords County Cricket Ground | J13: None | K13: None | Q13: Level 2 Stadiums
A14: Netherlands | B14: =Netherlands!A4 -> 1087315 | D14: Level 1 Stadiums | E14: Level 1 Stadiums | F14: Durahm Riverside Ground | J14: Level 1 Stadiums | K14: Level 1 Stadiums | N14: Sponsors | Q14: None
A15: South Africa | B15: =SA!A6 -> 5181100 | D15: None | E15: None | F15: Level 1 Stadiums | K15: None | Q15: Level 1 Stadiums
A16: UAE | B16: =UAE!A4 -> 468725 | F16: None | Q16: None
A17: Canada | B17: =Zimbabwe!A4 -> 139000
A18: Zimbabwe | B18: =Canada!A4 -> 251500
A19: Ireland | B19: =Ireland!A5 -> 718775
A20: Uganda | B20: =Uganda!A4 -> 174825
A21: USA | B21: =USA!A4 -> 944725
A22: Argentina | B22: ='Dismantled Argentina'!A4 -> 33500
A23: Kenya | B23: =Kenya!A4 -> 127000 | F23: Franchise League Updates
A24: Nepal | B24: =Nepal!A5 -> 164000 | F24: League Name | G24: Award Name | H24: Award Winner | I24: Franchise Team | J24: National Board
A25: Papua New Guinea | B25: =PNG!A4 -> 253225 | F25: THE HUNDRED 2026 | G25: Emerging Player | H25: Vishnu CV | I25: Southern Brave | J25: England
A26: Portugal | B26: =Portugal!A4 -> 72000 | G26: Economical Bowler | H26: Waleed Khan | I26: Southern Brave | J26: Afghanistan
G27: Most Sixes | H27: Hasan Musabir | I27: MI London | J27: Newzealand
A28: International Tournament Updates | G28: Best Bowler | H28: Safeer Babu | I28: Sunrisers Leeds | J28: England
A29: Tournament Name | B29: Awards | C29: Award Winners | D29: Official Board | G29: Best Batsman | H29: Nirmal Baishya | I29: Sunrisers Leeds | J29: Netherlands
A30: T20 World CUP 2026 | B30: Most Dot Balls | C30: Toby Joseph | D30: England | G30: Player of the Tournament | H30: Shivaji Prakash | I30: Welsh Fire | J30: India
B31: Most Maidens | C31: Anurag Raj | D31: Australia | G31: Runners Up | H31: Sunrisers Leeds
B32: Best Economy | C32: Virendra | D32: Srilanka | G32: Champions | H32: MI London
B33: Best Bat Average | C33: Bhavin Kumar | D33: Pakistan | F33: PAKISTAN SUPER LEAGUE 2026 | G33: Emerging Player | H33: Wajdan | I33: Lahore Qalandars | J33: Pakistan
B34: Fastest Century | C34: Rejith Mohan | D34: England | G34: Most Sixes | H34: Muhammad Usman | I34: Lahore Qalandars | J34: Pakistan
B35: Fastest Fifty | C35: Diljith Das | D35: England | G35: Best Bowler | H35: Adithya Mahajan | I35: Lahore Qalandars | J35: Afghanistan
B36: Most Fours | C36: Rejith Mohan | D36: England | G36: Best Batsman | H36: Al Ameen | I36: Quetta Gladiators | J36: West Indies
B37: Most Sixes | C37: Hashir | D37: Scotland | G37: Player of the Tournament | H37: Adithya Mahajan | I37: Lahore Qalandars | J37: Afghanistan
B38: Best Bowl Figure | C38: Anshad | D38: Scotland | G38: Fair Play Award | H38: Quetta Gladiators
B39: Highest Individual Score | C39: Sai Naveen | D39: Australia | G39: Runners up | H39: Hyderabad Kings
B40: Fastest Umpire | C40: Nasrullah Kapri | D40: Pakistan | G40: Champions | H40: Lahore Qalandars
B41: World Cup Operaions Excellence | C41: Yasin Iqbal | D41: Australia | F41: BIG BASH LEAGUE 2026 | G41: Best Young Player | H41: Anand Ajikumar | I41: Sydney Sixers | J41: Australia
B42: Best Captain | C42: Midhun Manilal | D42: West Indies | G42: Most Sixes | H42: Arnab Sarkar & Nasrullah Kapri | I42: Sydney Sixers | J42: Australia & Pakistan
B43: Best Bowler | C43: Chappy | D43: Scotland | G43: Best Bowler ( Golden Arm ) | H43: Zarnish Saira | I43: Melbourne Stars | J43: Pakistan
B44: Best Batsman | C44: Rejith Mohan | D44: England | G44: Best Batsman ( Golden Bat ) | H44: Arnab Sarkar | I44: Sydney Sixers | J44: Australia
B45: Man of the Tournament | C45: Chappy | D45: Scotland | G45: Player of the Tournament | H45: Arnab Sarkar | I45: Sydney Sixers | J45: Australia
B46: Runners Up | D46: England | G46: Fair Play Award | H46: Brisbane Heat
B47: Champions | D47: Scotland | G47: Runners up | H47: Melbourne Stars
A48: EMERGING TALENTS LEAGUE 2026 | B48: Best Captain | C48: Amjith | D48: Scotland | G48: Champions | H48: Sydney Sixers
B49: Best Bowler | C49: Mowglee | D49: West Indies | F49: KIWI CROWN LEAGUE 2026 | G49: Rise of the crown (Emerging Player) | H49: Karthik Devadiga | I49: Wellington Warriors | J49: Newzealand
B50: Best Batsman | C50: Shajahan | D50: England | G50: The Thunder Striker (Most Sixes) | H50: Vishnu Vijay | I50: Northern Knights | J50: Italy
B51: Player of the Tournament | C51: Shajahan | D51: England | G51: The Shadow scepter (Best Bowler) | H51: Waqas Mughal | I51: Tauranga Titans | J51: Australia
B52: Match of the Tournament | C52: England & West Indies | G52: The Golden Crown (Best Batsman) | H52: Vishnu Vijay | I52: Northern Knights | J52: Italy
B53: Best Talent Discovery Board | C53: All four Boards | G53: Crowned Warrior (Player of the Tournament) | H53: Adithya Mahajan | I53: Northern Knights | J53: Afghanistan
B54: Fair Play | C54: England & Scotland | G54: Spirit of Crown (Fair Play Award) | H54: Canterbury Kings
B55: Runners Up | C55: England | G55: Runners up | H55: Tauranga Titans
B56: Champions | C56: Scotland | G56: Champions | H56: Northern Knights
A57: LONE WARRIOR 2026 | B57: Semifinalists | C57: Abhi & Anshad | D57: Scotland & India | F57: INDIAN PREMIER LEAGUE 2026 | G57: Emerging Player | H57: Asru KSD | I57: Kolkata Knight Riders | J57: India
B58: Runner Up | C58: Shamroz | D58: Pakistan | G58: Most Sixes | H58: Hasan Musabir | I58: Punjab Kings | J58: Newzealand
B59: Champion | C59: Diljith Das | D59: England | G59: Purple Cap | H59: Shamroz | I59: Kolkata Knight Riders | J59: Pakistan
A60: ASIA CUP 2026 | B60: Fair play | C60: UAE | G60: Orange Cap | H60: Shukoor | I60: Kolkata Knight Riders | J60: Scotland
B61: Captain of the tournament | C61: Ans Sheikh | D61: Qatar | G61: Player of the Tournament | H61: Rahul Seenu | I61: Delhi Capitals | J61: India
B62: Emerging Player | C62: Sebin | D62: UAE | G62: Fair Play Award | H62: Chennai Super Kings
B63: Golden Ball | C63: Ahmed Mughal | D63: Qatar | G63: Runners up | H63: Kolkata Knight Riders
B64: Golden Bat | C64: Syed Raza | D64: Qatar | G64: Champions | H64: Rajasthan Royals
B65: Player of the tournament | C65: Syed Raza | D65: Qatar | F65: CARIBBEAN PREMIER LEAGUE 2026 | G65: Emerging Player | H65: Abhishek Vava | I65: Barbados Royals | J65: West Indies
B66: Runners Up | D66: Bangladesh | G66: Most Sixes | H66: Shivaji Prakash | I66: Guyana Amazon Warriors | J66: India
B67: Champions | D67: Qatar | G67: Best Bowler | H67: Anish Babu | I67: Jamaica Kingsmen | J67: West Indies
A68: EURO CUP 2026 | B68: Fair play | C68: Scotland | G68: Best Batsman | H68: Rahul Suresh | I68: Trinbago Knight Riders | J68: West Indies
B69: Captain of the tournament | C69: Diljith Das | D69: England | G69: Player of the Tournament | H69: Waqas Mughal | I69: St Vincent Volcanoes | J69: Australia
B70: Emerging Player | C70: Jihan | D70: Netherlands | G70: Fair Play Award | H70: Guyana Amazon Warriors
B71: Golden Ball | C71: Safeer Babu | D71: England | G71: Runners up | H71: Trinbago Knight Riders
B72: Golden Bat | C72: Sunaif | D72: England | G72: Champions | H72: Jamaica Kingsmen
B73: Player of the tournament | C73: Subaida | D73: Italy | F73: SCOTTISH PREMIER LEAGUE 2026 | G73: Emerging Player | H73: Ajoy Babu | I73: Perth Panthers | J73: Scotland
B74: Runners Up | D74: Italy | G74: Most Sixes | H74: Mahesh Margol | I74: Glasgow Giants | J74: Newzealand
B75: Champions | D75: England | G75: Best Bowler | H75: Aaiz Khan | I75: Highland Hawks | J75: Pakistan
A76: OCEANIA CUP 2026 | B76: Fair play | C76: Newzealand | G76: Best Batsman | H76: Mahesh Margol | I76: Glasgow Giants | J76: Newzealand
B77: Captain of the tournament | C77: Toby Joseph | D77: Newzealand | G77: Player of the Tournament | H77: Arjun Raj R | I77: Glasgow Giants | J77: West Indies
B78: Emerging Player | C78: Kaushik & Ajay | D78: South Africa & West Indies | G78: Fair Play Award | H78: Highland Hawks
B79: Golden Ball | C79: Arnab Sarkar | D79: Australia | G79: Runners up | H79: Tartan Strikers
B80: Golden Bat | C80: Harsh Dubey | D80: Australia | G80: Champions | H80: Glasgow Giants
B81: Player of the tournament | C81: Arnab Sarkar | D81: Australia
B82: Runners Up | D82: Newzealand
B83: Champions | D83: Australia
A84: WOMEN'S GLOBAL LEAGUE 2026 | B84: Best Women Talent Discovery Board | C84: All five Boards
B85: Fair Play | C85: Fair Play
B86: Best Captain | C86: Ishita Sharma | D86: Bangladesh
B87: Best Bowler | C87: Tasnim | D87: Bangladesh
B88: Best Batsman | C88: Sneha Jyothish | D88: England
B89: Player of the Tournament | C89: Tasnim | D89: Bangladesh
B90: Runners Up | C90: Italy
B91: Champions | C91: Bangladesh
A92: ASSOCIATE NATIONS CUP 2026 | B92: Player of the tournament | C92: Naveen Gupta | D92: Canada
B93: Best Batsman | C93: Rehan | D93: Canada
B94: Best Bowler | C94: Dhurbo Rajbongshi | D94: Zimbabwe
B95: Highest Individual Score | C95: Noufal | D95: Ireland
B96: Best Bowling figure in a match | C96: Mohsin Lathif & Dhurbo | D96: USA & Zimbabwe
B97: Best Batting Average | C97: Naveen Gupta | D97: Canada
B98: Hosting Nation | C98: USA
B99: Runners Up | C99: Canada
B100: Champions | C100: Ireland
...

Sheet IOCF 2.0
A1: Council of Champions | B1: Council of Established | C1: Council of Challengers | D1: Council of Origins
A2: 1. Scotland
A3: 2. England
A4: 3. Qatar
A5: 4. Australia

Sheet All Time Records
A1: CLUB Format
A2: Field | B2: Player Name | C2: Country | D2: Stats
A3: Highest Score By a Player in a Match | B3: Ameen | C3: West Indies | D3: 125
A4: Best Bowling Figure by a Player in a Match | B4: Rahul Suresh | C4: West Indies | D4: 46116
A5: Highest Score By a Team in a Match
A6: Lowest Score by a Team in a Match | B6: Bangladesh | D6: 192
A7: Highest Score chased by a team
A8: Lowest score defened by a team
A10: T10 Format
A11: Field | B11: Player Name | C11: Country | D11: Stats
A12: Highest Score By a Player in a Match | B12: Abhinav Sham | C12: Nepal | D12: 122
A13: Best Bowling Figure by a Player in a Match
A14: Highest Score By a Team in a Match | B14: West Indies | D14: 216
A15: Lowest Score by a Team in a Match
A16: Highest Score chased by a team
A17: Lowest score defened by a team
A19: T20 Format
A20: Field | B20: Player Name | C20: Country | D20: Stats
A21: Highest Score By a Player in a Match | B21: Hrushikesh HD | C21: Newzealand | D21: 217
A22: Best Bowling Figure by a Player in a Match
A23: Highest Score By a Team in a Match | B23: England | D23: 386
A24: Lowest Score by a Team in a Match
A25: Highest Score chased by a team
A26: Lowest score defened by a team
A28: ODI Format
A29: Field | B29: Player Name | C29: Country | D29: Stats
A30: Highest Score By a Player in a Match | B30: Aaiz Khan | C30: Pakistan | D30: 201
A31: Best Bowling Figure by a Player in a Match
A32: Highest Score By a Team in a Match | B32: Qatar | D32: 472
A33: Lowest Score by a Team in a Match
A34: Highest Score chased by a team
A35: Lowest score defened by a team
A37: Test Format
A38: Field | B38: Player Name | C38: Country | D38: Stats
A39: Highest Score By a Player in a Match | B39: Hirak Jyoti | C39: Netherlands | D39: 176
A40: Best Bowling Figure by a Player in a Match
A41: Highest Score By a Team in a Match | B41: South Africa | D41: 351
A42: Lowest Score by a Team in a Match
A43: Highest Score chased by a team
A44: Lowest score defened by a team

Sheet Afghanistan
A1: Board: Afghanistan
A2: Chairman: Waleed Khan | CEO: Umar Khan
A3: Credits left:
A4: =100000+B6+A21+D6+E6+E14+C6 -> 83000
A5: Players | B5: Player trade | C5: Stadium: | D5: International Series: | E5: Whitewash Win: | F5: Trophy Cabinet ( International series)
A6: 1. Maharoof | B6: -20000 | C6: -30000 | D6: 7000 | E6: 1000 | F6: 1. The Golden Cup
A7: 2. Shobha Joseph | B7: 1. Umar (IOCF): 20K | C7: Level 3 Stadiums | D7: 1. Away(West Indies): 7000 (Won) | E7: 1. vs West Indies: 1
A8: 3. Irfan Sohail | C8: Afghan National Sports Complex
A9: 4. Glinson Babu
A10: 5. Saleem Rana
A11: 6. Muhammad Raheel
A12: 7. Nadeem Ahmed
A13: 8. Adnan Abbas | E13: Whitewash lose:
A14: 9. Abdullah Usmani | E14: 0
A15: 10. Farhan Mallick
A16: 11. Nabahan
A17: 12. Talha Arain
A18: 13. Anoop
A19: 14. Saif Ali
A20: All Franchise League Credits Updates :
A21: =A23 -> 25000
A22: Qatar Elite Crown League :
A23: =A26 -> 25000
A24: 2026
A25: All Team Profit:
A26: =A29+B29+C29+D29+E29+F29+G29+H29 -> 25000
A27: AL KHOR PREDATORS | B27: AL RAYYAN RAIDERS | C27: AL WAKRAH DUKES | D27: DOHA STALLIONS | E27: LUSAIL KNIGHTS | F27: MESAEID BLAZE | G27: QATAR VENOMS | H27: UMM SALAL SPARTANS
A28: Team Profit: | B28: Team Profit: | C28: Team Profit: | D28: Team Profit: | E28: Team Profit: | F28: Team Profit: | G28: Team Profit: | H28: Team Profit:
A29: 0 | B29: 0 | C29: 0 | D29: 0 | E29: 0 | F29: 25000 | G29: 0 | H29: 0
F30: 1. Waleed Khan
F31: No Salary(Traded)
F32: Man of the match: 2 (10000)
F33: Best Bowler: 1 (5000)

Sheet Dismantled Argentina
A1: Board: ARGENTINA
A2: Chairman: Sayandeep Ghosh | CEO: ---
A3: Credits left:
A4: =100000+B6+C6+D6+F6+F11 -> 33500
A5: Players | B5: Player trade | C5: Stadium: | D5: International Series: | E5: Trophy Cabinet ( International Series) | F5: Whitewash Win:
A6: 1. Alidad | B6: =-25000 -> -25000 | C6: -30000 | D6: -11000 | F6: 0
A7: 2. Anik Mukherjee | B7: Anik from USA: 3000 | C7: Level 3 Stadiums | D7: 1. Home(Portugal): 3000 bet (Lost)
A8: 3. Aryan Das | B8: Ibrahim from USA: 3000 | C8: LA GUERRERO Cricket Stadium | D8: 2. Away(Kenya): 3000 bet (Lost)
A9: 4. Bijoy DS | B9: Bijoy from USA: 3000 | D9: 3. Home(Japan): 5000 bet (Lost)
A10: 5. Bilal | B10: Shad from USA: 3000 | F10: Whitewash loss:
A11: 6. Ibrahim Shihab | B11: Jayesh from USA: 3000 | F11: -500
A12: 7. Jayesh Nikije | B12: Kuldeep from PNG: 10000 | F12: 1. The Gaucho-Samurai Trophy(Home)
A13: 8. Wali Muhammad
A14: 9. Sarwar Kapri
A15: 10. Shad Mahar
A16: 11. Shafa Bewas
A17: 12. Raj

Sheet Australia
A1: Board: AUSTRALIA
A2: Chairman: Arnab Sarkar | Ceo: Keshav Shah
A3: Credits left:
A4: =100000+B6+C6+D6+D14+F6+G6+H6+I6+A65+L6+R6+O6 -> 6851560
A5: Players | B5: Stadium: | C5: International Series: | D5: Whitewash: | E5: Trophy Cabinet ( International series) | F5: Traded Players: | G5: IOCF T20 WORLD CUP 🏆: | H5: Player limit exceeded: -20000 | I5: IOCF WORLD TEST CHAMPIONSHIP 🏆: | L5: CONTINENTAL CUP 2026 🏆: ( OCEANIA ) | O5: ODI WORLD CUP 2026 🏆: | R5: Umpires Credits :
A6: 1. Abrar Ali | B6: -190000 | C6: 22000 | D6: 6000 | E6: 1. Kangaroo Protea Cup ( Home ) | F6: 268000 | G6: 15300 | H6: -10000 | I6: =I8+J8+K8 -> 44000 | L6: =L8 -> 431200 | O6: =O8 -> 1144000 | R6: =U10+U19+U33+U36+U50+U55+U62+U65+U76+U82+U55 -> 523250
A7: 2. Adil Rahman | B7: Level 3 Stadiums | C7: Home( Pakistan ): 5000 bet ( Lost ) | D7: Against South Africa: 1 | E7: 2. Caribbean Tri Nation Series ( Away ) | F7: 1. Yasin Iqbal - 5k | G7: Hosting Rights: -42000 | H7: 1. 20 to 25: 10000 | I7: Player Awards | J7: Match Bet Credits | K7: Entry Credits | L7: Players & Match Awards | O7: Players & Match Awards | R7: Umpire | S7: Details | T7: Total Matches | U7: Credits | V7: Points
A8: 3. Alapan Das | B8: Melbourne Cricket Ground | C8: Home( South Africa): 5000 bet ( Won ) | D8: Against Afghanistan: 1 | E8: 3. Aus Afg Power series ( Home ) | F8: 2. Karan Kumar - 5k | G8: Entry: -5000 | I8: =K27+K30+K33+K36+K39+K42+K45+K48 -> 19000 | J8: 30000 | K8: -5000 | L8: =N10+N11+N14+N15+N20+N23+N25+N26+N27 -> 431200 | O8: =Q10+Q14+Q15+Q17+Q19+Q20+Q22+Q23 -> 1144000 | R8: 1. Yasin Iqbal | S8: Club Series | T8: 16 | U8: =T8*1000 -> 16000 | V8: =T8*20 -> 320
A9: 4. Anandan Ajikumar | B9: Sydney Cricket Ground | C9: Away( West Indies/ Scotland ): 5000 ( Won ) | D9: Against England(Test): 1 | E9: 4. The Ashes( Away ) | F9: 3. Sai Naveen - 5k | G9: Players Awards: 2300 | J9: Home(Pakistan): 5000 ( Won ) | K9: Trophy Cabinet (Test) | L9: Player | M9: Award | N9: Credits | O9: Player | P9: Award | Q9: Credits | S9: T20 Tournament | T9: 7 | U9: =T9*6000 -> 42000 | V9: =T9*60 -> 420
A10: 5. Anik Dey Shanto | B10: Optus Stadium | Free T20 WC | C10: Home ( Newzealand) : 5000 bet ( Lost ) | D10: Against Newzealand: 2 | E10: 5. Southee Cummins ( Away ) | F10: 4. Bhavesh B - 5k | G10: 1. Sai Naveen | J10: Away(Pakistan): 5000 (Won) | K10: Benaud-Qadir | L10: 1. Abrar Ali | M10: Best Batsman(1000): 1 | N10: 1000 | O10: 1. Arnab Sarkar | P10: Man of the match(5000): 1 | Q10: 822000 | S10: Total Credits | U10: =U8+U9 -> 58000 | V10: =V8+V9 -> 740
A11: 6. Ankan Biswas | B11: Adelaide Oval | C11: Home ( West Indies): 5000 bet ( Lost ) | E11: 6. Southern Challenge (Away) | F11: 5. Vaibhav Batra - 5k | G11: Man of the match: 1 | J11: Away(Scotland): 5000 (Won) | K11: Scottish Wall | L11: 2. Keshav Shah | M11: Man of the match(2000): 1 | N11: =3000+5400 -> 8400 | P11: Best Bowler(3000): 4 | R11: 2. Anurag Raj | S11: Club Series | T11: 7 | U11: =T11*1000 -> 7000 | V11: =T11*20 -> 140
A12: 7. Anurag Raj Gautam | B12: Sydney Show Ground | Franchise League L1 | Upgraded | C12: Away( Scotland): 5000 bet ( Lost ) | E12: 7. Kiwi Kangaroo (Away) | F12: 6. Saketh Balne - 5k | G12: • vs Scotland: 500 | J12: Home(Scotland): 5000 (Won) | K12: Aussie Wall | M12: Best Bowler(1000): 1 | P12: Most Dot Balls(1000): 5 | S12: T20 Tournament | T12: 4 | U12: =T12*6000 -> 24000 | V12: =T12*60 -> 240
A13: 8. Aqi Syed | B13: Marvel Cricket Stadium | C13: Home( Afghanistan): 7000 bet ( Won ) | D13: Whitewash lose: | E13: 8. Kingfisher Cup (Home) | F13: 7. Summan Baig to Pak - 2k | G13: Most Sixes: 1 | J13: Home (England): 5000 (Lost) | K13: Sydney Cup | M13: Team of the tournament - 5400 | P13: Best Bowler of the tournament: 800000 | S13: T20 Series | T13: 1.5 | U13: =T13*3000 -> 4500 | V13: =T13*60 -> 90
A14: 9. Ashwini Verma | B14: The Gabba | C14: Away( England ): 10000 ( Won ) | D14: -1000 | E14: 9. KFC T20 Cup (Home) | F14: 8. Srinidhi (10k) - SA Chairman | G14: • vs Scotland: 300 | J14: Away(England): 5000 (Lost) | K14: Poker Cup | L14: 3. Waqas Mughal | M14: Best Bowler(1000): 1 | N14: 1000 | O14: 2. Rahul Gadia | P14: Most Sixes(1000): 2 | Q14: 2000 | S14: ODI Tournament | T14: 1 | U14: =T14*10000 -> 10000 | V14: =T14*100 -> 100
A15: 10. Achu Achu | B15: Ninja Stadium Hobart | C15: Away ( England ): 5000 bet ( Lost ) | D15: Against Newzealand: 1 | E15: 10. IPL Challenger Trophy (Away) | F15: 9. Donald (10k) - SA Chairman | G15: 2. Bhavesh B | J15: Home(Bangladesh): 5000 (Won) | K15: Orange - Yellow Trophy | L15: 4. Arnab Sarkar | M15: Man of the match(2000): 1 | N15: =3000+25000+50000+5400 -> 83400 | O15: 3. Malik Zubair | P15: Man of the match(5000): 1 | Q15: 8000 | S15: T10 Series | T15: 1 | U15: =T15*2000 -> 2000 | V15: =T15*40 -> 40
A16: 11. Chintan Poojari | B16: Level 2 Stadiums | C16: Away ( UAE ): 5000 bet ( Lost ) | D16: Against Scotland: 1 | E16: 11. Great Southern Dutch (Home) | F16: 10. Noor from WI - 10000 | G16: Most Sixes: 1 | J16: Away(Bangladesh): 5000 (Won) | K16: Bee Trophy | M16: Best Bowler(1000): 2 | P16: Best Bowler(3000): 1 | S16: Franchise League
A17: 12. Chiranjibi Samal | B17: None | C17: Away ( Newzealand ): 5000 bet ( Won ) | E17: 12. The Dublin Showdown (Away) | F17: 11. Mahi to SA - 2500 | G17: • vs Afghanistan: 300 | J17: Home(Netherlands): 5000 (Lost) | K17: Southern Cross Test | M17: Golden Ball Award(25000) | O17: 4. Muhammad Noor | P17: Best Batsman(3000): 1 | Q17: 5000 | S17: 100 | T17: 1 | U17: =T17*1500 -> 1500 | V17: =T17*60 -> 60
A18: 13. Hur Ali | B18: Level 1 Stadiums | C18: Away (Pakistan): 10000 bet (Won) | E18: 13. Last Of the Summer (Home) | F18: 12. K Rakesh to SA - 2500 | G18: 3. Anurag | J18: Away(Netherlands): 5000 (Won) | K18: The Gulf Test Series | M18: Player of the Tournament(50000) | P18: Most Sixes(1000): 2 | S18: BBL | T18: 4 | U18: =T18*1500 -> 6000 | V18: =T18*60 -> 240
A19: 14. Kuldeep Roy | B19: None | C19: Away (Newzealand): 5000 bet (Won) | F19: 13. Harsh from Qatar - 60000 | G19: Most Sixes: 1 | J19: Home(Srilanka): 5000 (Won) | K19: Kiwi Kangaroo Trophy | M19: Team of the tournament - 5400 | O19: 5. Abrar Ali | P19: Best Batsman(3000): 1 | Q19: 3000 | S19: Total Credits | U19: =U11+U12+U17+U18+U13+U14+U15 -> 55000 | V19: =V11+V12+V17+V18+V13+V14+V15 -> 910
A20: 15. Malaram Patel | C20: Home(Srilanka): 5000 bet (Won) | F20: 14. Ashfak from BD - 23000 | G20: • vs Afghanistan: 300 | J20: Home(Newzealand): 5000 (Won) | L20: 5. Harsh Dubey | M20: Best Batsman(1000): 1 | N20: =1000+25000+5400 -> 31400 | O20: 6. Chiranjibi Samal | P20: Best Batsman(3000): 1 | Q20: 4000 | R20: 3. Arnab Sarkar | S20: Club Series | T20: 5 | U20: =T20*1000 -> 5000 | V20: =T20*20 -> 100
A21: 16. Malik Zubair | C21: Home (England): 10000 bet (Won) | F21: 15. Mohsin to USA - free | G21: Economical bowler: 1 | J21: Away(UAE): 10000 (Won) | M21: Golden Bat Award(25000) | P21: Most Sixes(1000): 1 | S21: T20 Tournament | T21: 4 | U21: =T21*6000 -> 24000 | V21: =T21*60 -> 240
A22: 17. Manish Indoria | C22: Home(India): 5000 bet (Lost) | F22: 16. Arjun to Ireland - 7000 | G22: • vs West Indies: 300 | J22: Away(Srilanka): 10000 (Lost) | M22: Team of the tournament - 5400 | O22: Group Stage Exit | Q22: 200000 | S22: T10 Series | T22: 2 | U22: =T22*2000 -> 4000 | V22: =T22*40 -> 80
A23: 18. Muhammad Noor | C23: Away(India): 5000 bet (Won) | F23: 17. Adil to USA: 7000 | G23: 4. Rizwan | J23: Away(Newzealand): 10000(Won) | L23: 6. Mohammaed Noor | M23: Man of the match(2000): 1 | N23: 3000 | O23: Fantasy League: 3rd Place | Q23: 100000 | S23: Club Series | T23: 1 | U23: =T23*1000 -> 1000 | V23: =T23*20 -> 20
A24: 19. Nidasha Romanoff | C24: Home(Netherlands): 10000 bet (Won) | F24: 18. Lal to Italy: 50000 | G24: Economical bowler: 1 | J24: Home(India): 10000(Lost) | M24: Best Bowler(1000): 1 | S24: ODI Series | T24: 1 | U24: =T24*5000 -> 5000 | V24: =T24*100 -> 100
A25: 20. Rahul Gadia | C25: Home(England): 10000 bet (Lost) | F25: 19. Kashif to Zim: 5000 | G25: • vs Afghanistan: 300 | I25: Players Awards & Credits | L25: 7. Waqas Mughal | M25: Man of the match(2000): 1 | N25: 2000 | S25: ODI Tournament | T25: 1.5 | U25: =T25*10000 -> 15000 | V25: =T25*100 -> 150
A26: 21. Rizwan Mansoori | C26: Home(UAE): 3000 bet (Lost) | F26: 20. Waqas to BD: 200000 | G26: 5. Abrar | I26: Player | J26: Award | K26: Credits | L26: 8. Rahul Gadia | M26: Best Batsman(1000): 1 | N26: 1000 | S26: Franchise League
A27: 22. Zeeshan Yaqoob Gujjar | C27: Away(West Indies): 10000 bet (Lost) | F27: 21. Ashfaq (Banned) | G27: Most Sixes: 1 | I27: 1. Rizwan Mansoori | J27: Man of the Match: 2 (1000) | K27: 4000 | L27: Champions | N27: 300000 | S27: BBL | T27: 8 | U27: =T27*1500 -> 12000 | V27: =T27*60 -> 480
C28: Away(USA): 10000 bet (Lost) | F28: 22. Rima from Pak: 25000 | G28: • vs West Indies: 300 | J28: Best Batsman: 3 (500) | S28: BPL | T28: 2 | U28: =T28*1500 -> 3000 | V28: =T28*60 -> 120
C29: Home(Srilanka & UAE): 15000 (Lost) | F29: 23. Adil from Zim: 60000 | G29: Eliminated in Group Stage: 10k | J29: Best Bowler: 1 (500) | S29: IPL | T29: 2.5 | U29: =T29*1500 -> 3750 | V29: =T29*60 -> 150
C30: Away(Zimbabwe): 5000 (Lost) | F30: 24. Rima to Pak: 25000 | I30: 2. Keshav Shah | J30: Man of the Match: 2 (1000) | K30: 4000 | S30: KCL ( Commentory ) | T30: 1 | U30: =T30*1500 -> 1500 | V30: =T30*60 -> 60
C31: Away(Ireland): 6000 (Won) | F31: 25. Harsh to USA: 100000 | G31: Players Awards: 15000 | J31: Best Batsman: 2 (500) | S31: IPL | T31: 1 | U31: =T31*1500 -> 1500 | V31: =T31*60 -> 60
C32: Away(Canada): 5000 (Lost) | F32: 26. Shahzad to Spain: 5000 | G32: 1. Anurag Raj | J32: Best Bowler: 2 (500) | S32: CPL ( Commentory ) | T32: 1 | U32: =T32*1500 -> 1500 | V32: =T32*60 -> 60
C33: Home(West Indies): 5000 (Lost) | F33: 27. Kuldeep from Arg: 10000 | G33: Most Maidens(2): 5000 | I33: 3. Saubhagya Gupta | J33: Man of the Match: 1 (1000) | K33: 1500 | S33: Total Credits | U33: =U20+U21+U22+U27+U28+U29+U30+U31+U23+U32+U24+U25 -> 77250 | V33: =V20+V21+V22+V27+V28+V29+V30+V31+V23+V32+V24+V25 -> 1620
C34: Away(West Indies): 5000 bet (Lost) | F34: 28. Chintan from Zim: 20000 | G34: 2. Sai Naveen | J34: Best Batsman: 0 (500) | R34: 4. Abrar Ali | S34: Club Series | T34: 1 | U34: =T34*1000 -> 1000 | V34: =T34*20 -> 20
C35: Home(India): 5000 bet (Won) | G35: Highest Individual Score(140): 5000 | J35: Best Bowler: 1 (500) | S35: T20 Tournament | T35: 0.5 | U35: =T35*6000 -> 3000 | V35: =T35*60 -> 30
C36: Home(West Indies): 10000 (Lost) | G36: 3. Yasin Iqbal | I36: 4. Arnab Sarkar | J36: Man of the Match: 5 (1000) | K36: 7500 | S36: Total Credits | U36: =U34+U35 -> 4000 | V36: =V34+V35 -> 50
C37: Home(Canada & West Indies): 10000 (Lost) | G37: World cup operations Excellence: 5000 | J37: Best Batsman: 1 (500) | R37: 5. Keshav Shah | S37: Club Series | T37: 8 | U37: =T37*1000 -> 8000 | V37: =T37*20 -> 160
C38: Away(Newzealand): 10000 (Lost) | J38: Best Bowler: 4 (500) | S38: T20 Tournament | T38: 2.5 | U38: =T38*6000 -> 15000 | V38: =T38*60 -> 150
G39: Hosting Nation: 30000 | I39: 5. Anand Kumar | J39: Man of the Match: 0 (1000) | K39: 500 | S39: T10 Series | T39: 2 | U39: =T39*2000 -> 4000 | V39: =T39*40 -> 80
J40: Best Batsman: 1 (500) | S40: T20 Series | T40: 9 | U40: =T40*3000 -> 27000 | V40: =T40*60 -> 540
G41: Prediction 3rd Place: 5000 | J41: Best Bowler: 0 (500) | S41: ODI Series | T41: 2.5 | U41: =T41*5000 -> 12500 | V41: =T41*100 -> 250
I42: 6. Rahul Gadia | J42: Man of the Match: 0 (1000) | K42: 500 | S42: Test Tournament | T42: 9 | U42: =T42*8000 -> 72000 | V42: =T42*80 -> 720
J43: Best Batsman: 1 (500) | S43: ODI Tournament | T43: 2 | U43: =T43*10000 -> 20000 | V43: =T43*100 -> 200
J44: Best Bowler: 0 (500) | S44: Club Tournament | T44: 1 | U44: =T44*2000 -> 2000 | V44: =T44*20 -> 20
I45: 7. Anand Ajikumar | J45: Man of the Match: 0 (1000) | K45: 500 | S45: Franchise League
J46: Best Batsman: 1 (500) | S46: BBL | T46: 7 | U46: =T46*1500 -> 10500 | V46: =T46*60 -> 420
J47: Best Bowler: 0 (500) | S47: KCL | T47: 3 | U47: =T47*1500 -> 4500 | V47: =T47*60 -> 180
I48: 8. Anurag Raj | J48: Man of the Match: 0 (1000) | K48: 500 | S48: BPL | T48: 1 | U48: =T48*1500 -> 1500 | V48: =T48*60 -> 60
J49: Best Batsman: 1 (500) | S49: IPL | T49: 1 | U49: =T49*1500 -> 1500 | V49: =T49*60 -> 60
J50: Best Bowler: 0 (500) | S50: Total Credits | U50: =U37+U38+U39+U40+U41+U42+U46+U47+U48+U49+U43+U44 -> 178500 | V50: =V37+V38+V39+V40+V41+V42+V46+V47+V48+V49+V43+V44 -> 2840
R51: 6. Malaram Patel | S51: T20 Tournament | T51: 0.5 | U51: =T51*6000 -> 3000 | V51: =T51*60 -> 30
S52: Test Tournament | T52: 0.5 | U52: =T52*8000 -> 4000 | V52: =T52*80 -> 40
S53: ODI Series | T53: 2.5 | U53: =T53*5000 -> 12500 | V53: =T53*100 -> 250
S54: ODI Tournament | T54: 1.5 | U54: =T54*10000 -> 15000 | V54: =T54*100 -> 150
S55: Total Credits | U55: =U51+U52+U53+U54 -> 34500 | V55: =V51+V52+V53+V54 -> 470
R56: 7. Chiranjibi Samal | S56: T20 Series | T56: 0.5 | U56: =T56*3000 -> 1500 | V56: =T56*60 -> 30
S57: Franchise League
S58: BBL | T58: 2 | U58: =T58*1500 -> 3000 | V58: =T58*60 -> 120
S59: KCL | T59: 1 | U59: =T59*1500 -> 1500 | V59: =T59*60 -> 60
S60: KCL ( Commentory ) | T60: 1 | U60: =T60*1500 -> 1500 | V60: =T60*60 -> 60
S61: CPL | T61: 0.5 | U61: =T61*1500 -> 750 | V61: =T61*60 -> 30
S62: Total Credits | U62: =U58+U59+U60+U61+U56 -> 8250 | V62: =V58+V59+V60+V61+V56 -> 300
R63: 8. K Srinidhi | S63: Franchise League
A64: All Franchise League Credits Updates : | S64: BBL | T64: 3 | U64: =T64*1500 -> 4500 | V64: =T64*60 -> 180
A65: =A67+A89+A115+A137+A165+A196+A240+A259+A275+A294 -> 4498810 | S65: Total Credits | U65: =U64 -> 4500 | V65: =V64 -> 180
A66: THE HUNDRED : 42400 | R66: 9. Waqas Mughal | S66: T10 Series | T66: 1 | U66: =T66*2000 -> 2000 | V66: =T66*40 -> 40
A67: 42400 | S67: Test Tournament | T67: 2.5 | U67: =T67*8000 -> 20000 | V67: =T67*80 -> 200
A68: 2026 | S68: ODI Tournament | T68: 1.5 | U68: =T68*10000 -> 15000 | V68: =T68*100 -> 150
A69: London Spirit | B69: Southern Brave | C69: Welsh Fire | D69: MI London | E69: Sunrisers Leeds | S69: T20 Series | T69: 1 | U69: =T69*3000 -> 3000 | V69: =T69*60 -> 60
A70: Team Profit: 2500 | B70: Team Profit: 4800 | C70: Team Profit: 3000 | D70: Team Profit: 32300 | S70: Club Tournament | T70: 1 | U70: =T70*2000 -> 2000 | V70: =T70*20 -> 20
A71: 1. Rahul Gadia | B71: 1. Sai Naveen | C71: 1. Rizwan Mansoori | D71: 1. Arnab Sarkar | S71: ODI Series | T71: 1 | U71: =T71*5000 -> 5000 | V71: =T71*100 -> 100
A72: Salary: 2500 | B72: Salary: 2800 | C72: Salary: 2800 | D72: Salary: 3500 | S72: Franchise League
B73: 2. Anand Akj | C73: Best Bowler:1 ( 200 ) | D73: Best Batsman: 1 ( 200 ) | S73: BBL | T73: 1 | U73: =T73*1500 -> 1500 | V73: =T73*60 -> 60
B74: Salary: 1000 | D74: Man of the match: 1 ( 500 ) | S74: IPL | T74: 1 | U74: =T74*1500 -> 1500 | V74: =T74*60 -> 60
B75: 3. Bhavesh B | D75: Champions: 5300 | S75: CPL | T75: 0.5 | U75: =T75*1500 -> 750 | V75: =T75*60 -> 30
B76: Salary: 1000 | D76: 2. Keshav Shah | S76: Total Credits | U76: =U66+U67+U73+U74+U75+U68+U69+U70+U71 -> 50750 | V76: =V66+V67+V73+V74+V75+V68+V69+V70+V71 -> 720
D77: Salary: 2800 | R77: 10. Muhammad Noor | S77: Test Tournament | T77: 1 | U77: =T77*8000 -> 8000 | V77: =T77*80 -> 80
D78: Best Bowler: 2 ( 400 ) | S78: ODI Series | T78: 1 | U78: =T78*5000 -> 5000 | V78: =T78*100 -> 100
D79: Man of the match: 1 ( 500 ) | S79: ODI Tournament | T79: 0.5 | U79: =T79*10000 -> 5000 | V79: =T79*100 -> 50
D80: Champions: 5300 | S80: Franchise League
D81: 3. Chiranjibi Samal | S81: CPL | T81: 1.5 | U81: =T81*1500 -> 2250 | V81: =T81*60 -> 90
D82: Salary: 1700 | S82: Total Credits | U82: =U77+U78+U79 -> 18000 | V82: =V77+V78+V79 -> 230
D83: Champions: 5300
D84: 4. Abrar Ali
D85: Salary: 1500
D86: Champions: 5300
A88: Pakistan Super League :
A89: 47360
A90: 2026
A91: LAHORE QALANDARS | B91: PINDIZ | C91: MULTAN SULTANS | D91: KARACHI KINGS | E91: QUETTA GLADIATORS | F91: HYDERABAD KINGSMEN
A92: Team Profit: | B92: Team Profit: 10550 | C92: Team Profit: 15750 | D92: Team Profit: 7300 | E92: Team Profit: | F92: Team Profit: 13760
B93: 1. Saubhagya Gupta | C93: 1. Arnab Sarkar | D93: 1. Anand AJK | F93: 1. Chiranjibi Samal
B94: Salary: 2200 | C94: Direct Signing: 5000 | D94: Salary: 500 | F94: Salary: 4000
B95: 2. Anurag Raj | C95: Man of the match: 1 (500) | D95: Best Batsman:2 (400) | F95: Man of the match: 1 (500)
B96: Salary: 2700 | C96: Best Batsman: 2 (400) | D96: 2. Rizwan Mansoori | F96: Best Bowler: 1 (200)
B97: 3. Abrar Ali | C97: Best Bowler: 1 (200) | D97: Salary: 3300 | F97: Runners up: 2480
B98: Salary: 3750 | C98: 2. Keshav Shah | D98: Man of the match: 1 (500) | F98: 2. K Rakesh
B99: Man of the match: 1 (500) | C99: Salary: 2850 | D99: Best Batsman:1 (200) | F99: Salary: 3000
B100: Best Bowler: 2 (400) | C100: Man of the match: 1 (500) | D100: Best Bowler: 1 (200) | F100: Man of the match: 1 (500)
B101: 4. Rahul Gadia | C101: Best Bowler: 1 (200) | D101: 3. Waqas Mughal | F101: Best Batsman:2 (400)
...

Sheet Bangladesh
A1: Board: Bangladesh
A2: Chairman: Sai Naveen | CEO: Bhargab Kashyap
A3: TITLE SPONSORS: CrazieCric asmr
A4: Credits left:
A5: =100000+B7+C7+D7+F7+I7+A84+E19+D28+J7+S7+P7+M7+I18+E24 -> 5510745
A6: Players | B6: Stadium: | C6: Traded Palyers: | D6: International Series: | E6: Trophy Cabinet ( International Series) | F6: IOCF WORLD TEST CHAMPIONSHIP 🏆: | I6: Player limit exceeded: -10000 | J6: CONTINENTAL CUP 2026 🏆: ( ASIA ) | M6: Women's Global League 2026 🏆: | P6: ODI WORLD CUP 2026 🏆: | S6: Umpires Credits :
A7: 1. Abhishek Adhikary | B7: -230000 | C7: =10000-400000-15000 -> -405000 | D7: 46000 | E7: 1. Greater Asia Cup ( Home ) | F7: =F9+G9+H9 -> -21000 | I7: -20000 | J7: =-60000+J10 -> 123200 | M7: =M9 -> 330000 | P7: =P9 -> 1795000 | S7: =V10+V21+V35+V40+V44+V54+V57+V62+V65 -> 381250
A8: 2. Ahsan Siddiqui | B8: Level 3 Stadiums | C8: 1. Yasin Iqbal - 5k | D8: Home ( Afghanistan ): 5000 bet ( Won ) | E8: 2. Boult Taskin ( Away ) | F8: Player Awards | G8: Match Bet Credits | H8: Entry Credits | I8: 1. 20 to 25: 10000 | J8: Hosting Amount: 60k | M8: Players & Match Awards | P8: Players & Match Awards | S8: Umpire | T8: Details | U8: Total Matches | V8: Credits | W8: Points
A9: 3. Ali Khan | B9: Padma - Meghna Cricket Arena | C9: 2. Karan Kumar - 5k | D9: Away ( Newzealand ): 5000 bet ( Won ) | E9: 3. Battle of Giants ( Away ) | F9: =H27+H30+H33+H36+H39+H42+H45+H48 -> 13000 | G9: -29000 | H9: -5000 | I9: 2. 25 to 30: 10000 | J9: Players & Match Awards | M9: =O11+O12+O13+O14+O15 -> 330000 | P9: =R11+R13+R16+R18+R19+R20+R24+R26+R27+R28+R29 -> 1795000 | S9: 1. Vaibhav Batra | T9: Club Series | U9: 0.5 | V9: =U9*1000 -> 500 | W9: =U9*20 -> 10
A10: 4. Allabux Kapri | B10: Hilsha Heritage Stadium | Franchise League L1 | Upgraded | C10: 3. Sai Naveen - 5k | D10: Home (West Indies): 7000 bet (Lost) | E10: 4. Dutch Bangla Battle (Away) | G10: Away ( West Indies ): 6000 bet ( Lost ) | H10: Trophy Cabinet (Test) | J10: =L12+L15+L18+L21+L22 -> 183200 | M10: Player | N10: Award | O10: Credits | P10: Player | Q10: Award | R10: Credits | T10: Total Credits | V10: =V9 -> 500 | W10: =W9 -> 10
A11: 5. Asad KB | B11: Karnaphuli Cricket Park | C11: 4. Bhavesh B - 5k | D11: Away (England): 10000 bet ( Won ) | E11: 5. Lords Clash (Away) | G11: Home ( West Indies ): 6000 bet ( Lost ) | H11: 1. Redball War ( Away ) | J11: Player | K11: Award | L11: Credits | M11: Best Women Talent Discovery Board | O11: 20000 | P11: 1. Ali Khan | Q11: Man of the match(5000): 1 | R11: 7000 | S11: 2. Sai Naveen | T11: Club Series | U11: 1.5 | V11: =U11*1000 -> 1500 | W11: =U11*20 -> 30
A12: 6. Ishaq Farid | B12: Mango Fortress Stadium | C12: 5. Vaibhav Batra - 5k | D12: Away (Netherlands): 4000 bet (Won) | E12: 6. The Royal Protea Trophy (Home) | G12: Away (England): 10000 bet (Won) | H12: 2. North Sea-Bay Challenge | J12: 1. Bhargab Kashyap | K12: Man of the match(2000): 2 | L12: =7000+5400 -> 12400 | M12: Isitha | N12: Best Captain | O12: 30000 | Q12: Most Sixes(1000): 2 | T12: T10 Series | U12: 1.5 | V12: =U12*2000 -> 3000 | W12: =U12*40 -> 60
A13: 7. Ishita Sharma | B13: Sylhet Jewel Stadium | C13: 6. Saketh Balne - 5k | D13: Home (Pakistan): 5000 bet (Lost) | E13: 7. Anglo Bengal ODI Trophy (Away) | G13: Home (Scotland): 5000 bet (Won) | H13: 3. Tiger Tulip (Home) | K13: Best Batsman(1000): 3 | M13: Tasnim | N13: Best Bowler | O13: 30000 | P13: 2. Sai Naveen | Q13: Best Bowler(3000): 1 | R13: 5000 | T13: Test Tournament | U13: 5.5 | V13: =U13*8000 -> 44000 | W13: =U13*80 -> 440
A14: 8. Karan Kumar | B14: Sundarbans Cricket Fortress | C14: Harsh Dubey(Ban) - 20000 | D14: Away(England): 5000 bet (Won) | E14: 8. Tiger Orange Cup (Home) | G14: Away (Scotland): 5000 bet (Lost) | H14: 4. Solidarity Cup (Away) | K14: Team of the tournament - 5400 | N14: Player of the tournament | O14: 50000 | Q14: Most Sixes(1000): 1 | T14: ODI Series | U14: 1 | V14: =U14*5000 -> 5000 | W14: =U14*100 -> 100
A15: 9. Kalpana Bhujel | B15: Sonar Bangla Cricket Arena | C15: 8. Aashutosh from ND: 15000 | D15: Away(Pakistan): 5000 bet (Lost) | E15: 9. American-Bangla Trophy (Away) | G15: Home (Pakistan): 5000 bet (Lost) | H15: 5. Arabia-Bengal Test (Away) | J15: 2. Ahsan Siddiqui | K15: Man of the match(2000): 2 | L15: =5000+5400 -> 10400 | M15: Champions | O15: 200000 | Q15: Most Dot Balls(1000): 1 | T15: ODI Tournament | U15: 3 | V15: =U15*10000 -> 30000 | W15: =U15*100 -> 300
A16: 10. Kaushik Kalita | B16: Sands cox's Bazar | C16: 9. Bhavin to SA - 2500 | D16: Home(South Africa): 5000 bet (Won) | E16: 10. Tigers - Lions Forest Trophy (Home) | G16: Home(Netherlands): 4000 bet (Won) | K16: Best Bowler(1000): 1 | P16: 3. Yasin Iqbal | Q16: Man of the match(5000): 1 | R16: 7000 | T16: Club Tournament | U16: 1 | V16: =U16*2000 -> 2000 | W16: =U16*20 -> 20
A17: 11. Mahira | B17: Level 2 Stadiums | C17: 10. Raksh to SA - 2500 | D17: Away(England): 5000 bet (Lost) | G17: Away(Newzeland): 6000 bet (Lost) | I17: Sponsors | K17: Team of the tournament - 5400 | Q17: Most Dot Balls(1000): 2 | T17: Franchise League
A18: 12. Manan Irfan | B18: None | C18: 11. Saketh to SA - 2500 | D18: Home(Netherlands/West Indies): 15000 (Lost) | E18: Whitewash lose: | G18: Home(Newzealand): 5000 bet (Lost) | I18: 100000 | J18: 3. Yasin Iqbal | K18: Man of the match(2000): 1 | L18: =4000+5400 -> 9400 | P18: 4. Manan Irfan | Q18: Most Sixes(1000): 1 | R18: 1000 | T18: KCL | U18: 1 | V18: =U18*1500 -> 1500 | W18: =U18*60 -> 60
A19: 13. Partha Pratim Bora | B19: Level 1 Stadiums | C19: 12. Bhavesh to SA - 2500 | D19: Away(England): 5000 bet (Lost) | E19: -1000 | G19: Away(Pakistan): 5000 bet (Won) | I19: 1. Crazie Cric asmr (Title Sponsors) | K19: Best Bowler(1000): 2 | P19: 5. Princhi Bora | Q19: Most Dot Balls(1000): 1 | R19: 1000 | T19: BPL | U19: 2 | V19: =U19*1500 -> 3000 | W19: =U19*60 -> 120
A20: 14. Pinky Kashyap | B20: None | C20: 13. Ahmed to Qatar - 2000 | D20: Away(England): 5000 bet (Won) | E20: 1. Sons & Daughter (Pakistan) : Home | G20: Away(Australia): 5000 bet (Lost) | K20: Team of the tournament - 5400 | P20: 6. Waqas Mughal | Q20: Man of the match(5000): 2 | R20: 20000 | T20: IPL | U20: 1 | V20: =U20*1500 -> 1500 | W20: =U20*60 -> 60
A21: 15. Popi Sultana | C21: 14. Ebad to Qatar - 2000 | D21: Home(UAE): 5000 bet (Lost) | E21: 2. The Stars & Tigers series (USA) : Home | G21: Home(Australia): 5000 bet (Lost) | J21: 4. Sai Naveen | K21: Best Bowler(1000): 1 | L21: 1000 | Q21: Best Batsman(3000): 1 | T21: Total Credits | V21: =V11+V12+V13+V18+V19+V20+V14+V15+V16 -> 91500 | W21: =W11+W12+W13+W18+W19+W20+W14+W15+W16 -> 1190
A22: 16. Princhi Pratim Bora | C22: 15. Abdul to Qatar - 2000 | D22: Home (Netherlands): 7000 bet (Won) | G22: Home( Bangladesh): 5000 bet (Lost) | J22: Runners-UP | L22: 150000 | Q22: Best Bowler(3000): 2 | S22: 3. Yasin Iqbal | T22: Club Series | U22: 1 | V22: =U22*1000 -> 1000 | W22: =U22*20 -> 20
A23: 17. Rahees Ashiq | C23: 16. Ashutosh to NZ- 5000 | D23: Away(Italy): 5000 (Lost) | E23: Whitewash Won: | G23: Away(Qatar): 5000 bet (Won) | Q23: Most Sixes(1000): 1 | T23: Club Tournament | U23: 1 | V23: =U23*2000 -> 2000 | W23: =U23*20 -> 20
A24: 18. Rajab Baloch | C24: 17. Rao Abul to Qatar - 15000 | D24: Home(USA): 5000 (Lost) | E24: 1000 | G24: Home(South Africa): 10000 (Lost) | P24: 7. Tanusri Dutta | Q24: Best Batsman(3000): 1 | R24: 4000 | T24: T10 Series | U24: 1 | V24: =U24*2000 -> 2000 | W24: =U24*40 -> 40
A25: 19. Shubham Dudi | C25: 18. Harsh Dubey to Qatar - 15000 | D25: Away(USA): 5000 (Won) | E25: 1. Tigers - Lions Forest Trophy (Home) | F25: Players Awards & Credits | Q25: Most Sixes(1000): 1 | T25: T20 Series | U25: 2 | V25: =U25*3000 -> 6000 | W25: =U25*60 -> 120
A26: 20. Sidd V Jain | C26: 19. Adithya to RSA - 15000 | D26: Home(England): 10000 (Won) | F26: Player | G26: Award | H26: Credits | P26: 8. Ahsan Siddiqui | Q26: Emerging Player of the Tournament: 200000 | R26: 200000 | T26: ODI Series | U26: 3 | V26: =U26*5000 -> 15000 | W26: =U26*100 -> 300
A27: 21. Suraj Shetty | C27: 20. Ritik from Ned - 1000 | D27: IOCF HALL OF FAME | F27: 1. Yasin Iqbal | G27: Man of the Match: 3 (1000) | H27: 6000 | P27: Semifinalists | R27: 1000000 | T27: Test Tournament | U27: 1.5 | V27: =U27*8000 -> 12000 | W27: =U27*80 -> 120
A28: 22. Tasnim | C28: 21. Ashfak to Aus - 23000 | D28: 50000 | G28: Best Batsman: 1 (500) | P28: Prediction Contest: 1st Place | R28: 500000 | T28: ODI Tournament | U28: 4.5 | V28: =U28*10000 -> 45000 | W28: =U28*100 -> 450
A29: 23. Tansuri Dutta | C29: 22. Rohan (10k) - USA Chairman | D29: Yasin Iqbal | G29: Best Bowler: 5 (500) | P29: Fantasy League: 5th Place | R29: 50000 | T29: Franchise League
A30: 24. Tanushree | C30: 23. Gaurav to USA - 2000 | D30: Ice in their Veins : Top Wicket Taker | F30: 2. Karan Kumar | G30: Man of the Match: 0 (1000) | H30: 1000 | T30: 100 | U30: 1.5 | V30: =U30*1500 -> 2250 | W30: =U30*60 -> 90
A31: 25. Vaibhav Batra | C31: 24. Adil from USA: 10000 | G31: Best Batsman: 2 (500) | T31: PSL | U31: 2 | V31: =U31*1500 -> 3000 | W31: =U31*60 -> 120
A32: 26. Waqas Mughal | C32: 25. Waqas from Aus: 200000 | G32: Best Bowler: 0 (500) | T32: KCL | U32: 2 | V32: =U32*1500 -> 3000 | W32: =U32*60 -> 120
A33: 27. Yasin Iqbal | C33: 26. Sajjad to Canada: 25000 | F33: 3. Harsh Dubey | G33: Man of the Match: 0 (1000) | H33: 1000 | T33: BPL | U33: 1 | V33: =U33*1500 -> 1500 | W33: =U33*60 -> 60
C34: 27. Allabux from Canada: 25000 | G34: Best Batsman: 2 (500) | T34: IPL | U34: 1 | V34: =U34*1500 -> 1500 | W34: =U34*60 -> 60
C35: 25. Adil to USA: Free | G35: Best Bowler: 0 (500) | T35: Total Credits | V35: =V22+V23+V24+V25+V26+V27+V30+V31+V32+V33+V34+V28 -> 94250 | W35: =W22+W23+W24+W25+W26+W27+W30+W31+W32+W33+W34+W28 -> 1520
C36: 26. Shubham from Kenya: 15000 | F36: 4. Ahsan Siddiqui | G36: Man of the Match: 1 (1000) | H36: 1500 | S36: 4. Harsh Dubey | T36: T20 Series | U36: 1 | V36: =U36*3000 -> 3000 | W36: =U36*60 -> 60
C37: 27. Sid from SA: 100000 | G37: Best Batsman: 0 (500) | T37: Franchise League
C38: 28. Kaushik from SA: 100000 | G38: Best Bowler: 1 (500) | T38: PSL | U38: 0.5 | V38: =U38*1500 -> 750 | W38: =U38*60 -> 30
C39: 29. Gamshad to Spain: Free | F39: 5. Manan Irfan | G39: Man of the Match: 0 (1000) | H39: 500 | T39: BBL | U39: 0.5 | V39: =U39*1500 -> 750 | W39: =U39*60 -> 30
G40: Best Batsman: 1 (500) | T40: Total Credits | V40: =V36+V38+V39 -> 4500 | W40: =W36+W38+W39 -> 120
G41: Best Bowler: 0 (500) | S41: 5. Ahsan Siddiqui | T41: ODI Tournament | U41: 1 | V41: =U41*10000 -> 10000 | W41: =U41*100 -> 100
F42: 6. Adithya Mahajan | G42: Man of the Match: 1 (1000) | H42: 1500 | T42: Franchise League
G43: Best Batsman: 0 (500) | T43: BPL | U43: 3 | V43: =U43*1500 -> 4500 | W43: =U43*60 -> 180
G44: Best Bowler: 1 (500) | T44: Total Credits | V44: =V43+V41 -> 14500 | W44: =W43+W41 -> 280
F45: 7. Bhargab Kashyap | G45: Man of the Match: 0 (1000) | H45: 500 | S45: 6. Princhi Bora | T45: Club Series | U45: 5 | V45: =U45*1000 -> 5000 | W45: =U45*20 -> 100
G46: Best Batsman: 1 (500) | T46: T10 Series | U46: 4 | V46: =U46*2000 -> 8000 | W46: =U46*40 -> 160
G47: Best Bowler: 0 (500) | T47: Test Tournament | U47: 2 | V47: =U47*8000 -> 16000 | W47: =U47*80 -> 160
F48: 8. Ali Khan | G48: Man of the Match: 0 (1000) | H48: 1000 | T48: ODI Tournament | U48: 4.5 | V48: =U48*10000 -> 45000 | W48: =U48*100 -> 450
G49: Best Batsman: 2 (500) | T49: Club Tournament | U49: 3 | V49: =U49*2000 -> 6000 | W49: =U49*20 -> 60
G50: Best Bowler: 0 (500) | T50: T20 Series | U50: 2 | V50: =U50*3000 -> 6000 | W50: =U50*60 -> 120
T51: Franchise League
T52: BPL | U52: 3 | V52: =U52*1500 -> 4500 | W52: =U52*60 -> 180
T53: IPL | U53: 1 | V53: =U53*1500 -> 1500 | W53: =U53*60 -> 60
T54: Total Credits | V54: =V46+V47+V52+V53+V48+V45+V49+V50 -> 92000 | W54: =W46+W47+W52+W53+W48+W45+W49+W50 -> 1290
S55: 7. Partha Bora | T55: Club Tournament | U55: 0.5 | V55: =U55*2000 -> 1000 | W55: =U55*20 -> 10
T56: ODI Tournament | U56: 0.5 | V56: =U56*10000 -> 5000 | W56: =U56*100 -> 50
T57: Total Credits | V57: =V55+V56 -> 6000 | W57: =W55+W56 -> 60
S58: 8. Abhishek Adhikary | T58: Club Series | U58: 3 | V58: =U58*1000 -> 3000 | W58: =U58*20 -> 60
T59: ODI Tournament | U59: 3 | V59: =U59*10000 -> 30000 | W59: =U59*100 -> 300
T60: T20 Series | U60: 3 | V60: =U60*3000 -> 9000 | W60: =U60*60 -> 180
T61: Test Tournament | U61: 2 | V61: =U61*8000 -> 16000 | W61: =U61*80 -> 160
T62: Total Credits | V62: =V59+V60+V58+V61 -> 58000 | W62: =W59+W60+W58+W61 -> 700
S63: 9. Waqas Mughal | T63: T10 Series | U63: 1 | V63: =U63*2000 -> 2000 | W63: =U63*40 -> 40
T64: T20 Series | U64: 6 | V64: =U64*3000 -> 18000 | W64: =U64*60 -> 360
T65: Total Credits | V65: =V64+V63 -> 20000 | W65: =W64+W63 -> 400
A83: All Franchise League Credits Updates :
A84: =A86+A93+A122+A151+A173+A199+A229+A254+A277 -> 3261295
A85: THE HUNDRED :
A86: -15000
A87: 2026
A88: London Spirit | B88: Southern Brave | C88: Welsh Fire | D88: MI London | E88: Sunrisers Leeds
A89: No one is playing: They're new to IOCF
A90: Sai Naveen, Bhavesh & Siddiqui called for national duty ( Bangladesh ) for 15k
A92: Pakistan Super League : 51070
A93: 51070
A94: 2026
A95: LAHORE QALANDARS | B95: PINDIZ | C95: MULTAN SULTANS | D95: KARACHI KINGS | E95: QUETTA GLADIATORS | F95: HYDERABAD KINGSMEN
A96: Team Profit: 5490 | B96: Team Profit: 1200 | D96: Team Profit: 17400 | F96: Team Profit: 21980
A97: 1. Rajab Baloch | B97: 1. Vaibhav Batra | D97: 1. Yasin Iqbal | F97: 1. Sai Naveen
A98: Salary: 500 | B98: Salary: 1000 | D98: Direct Signing: 5000 | F98: Direct Signing: 3000
A99: Champions: 4990 | B99: Best Batsman: 1 (200) | D99: Man of the match: 1 (500) | F99: Man of the match: 1 (500)
D100: Best Bowler:1 (200) | F100: Best Batsman: 1 (200)
D101: 2. Karan Kumar | F101: Best Bowler: 2 (400)
D102: Salary: 3000 | F102: Runners up: 2480
D103: 3. Siddiqui Ahsan | F103: 2. Bhavesh
D104: Salary: 1800 | F104: Salary: 1000
D105: Man of the match: 1 (500) | F105: Runners up: 2480
D106: Best Bowler:2 (400) | F106: 3. Saketh
D107: 4. Harsh | F107: Salary: 500
D108: Salary: 1500 | F108: Runners up: 2480
D109: 5. Asad | F109: 4. Sajjad Kapri
D110: Salary: 500 | F110: Salary: 500
D111: 6. Ghamshad | F111: Runners up: 2480
... D117: 9. Edad | F117: Runners up: 2480
D118: Salary: 500
D119: Man of the match: 1 (500)
A121: Big Bash League :
A122: 145800
A123: 2026
A124: All Team Profit: 145800
...

Sheet Canada
A1: Board: Canada
A2: Chairman: Farhan Rizvi | CEO: Faraz Kapri
A3: Credits left:
A4: =100000+B6+C6+E6+J6+A27 -> 251500
A5: Players | B5: Stadium: | C5: International Series: | D5: Trophy Cabinet ( International series) | E5: Umpires Credits : | J5: Associate Nations CUP 2026 🏆:
A6: 1. Aftab | B6: -30000 | C6: 14500 | D6: 1. Croco-Owl Series ( Away ) | E6: =H9+H11 -> 4000 | J6: =J8 -> 142000
A7: 2. Akash | B7: Level 3 Stadiums | C7: Away( Zimbabwe ): 5000 bet ( Won ) | D7: 2. Red Leaf Cup (Home) | E7: Umpire | F7: Details | G7: Total Matches | H7: Credits | I7: Points | J7: Players & Match Awards
A8: 3. Arsalan Kapri | B8: CAA Centre | C8: Home(USA & Uganda): 5000 bet (Won) | D8: 3. ODI WC Warmup 1 (Home) | E8: 1. Farhan Rizvi | F8: Club Series | G8: 3 | H8: =G8*1000 -> 3000 | I8: =G8*20 -> 60 | J8: =L10+L15+L17+L18 -> 142000
A9: 4. Ayaz | B9: Level 2 Stadiums | C9: Away(USA): 3000 (Lost) | D9: 4. Rhino - Owl Cup (Away) | F9: Total Credits | H9: =H8 -> 3000 | I9: =I8 -> 60 | J9: Player | K9: Award | L9: Credits
A10: 5. Blassy | B10: None | C10: Home(West Indies): 5000 (Lost) | D10: 5. Irish Canadian Cup (Away) | E10: 2. Faraz Kapri | F10: Club Series | G10: 1 | H10: =G10*1000 -> 1000 | I10: =G10*20 -> 20 | J10: 1. Naveen Gupta | K10: Man of the Match(2000): 3 | L10: 50000
A11: 6. Chaitanya Deshpande | B11: Level 1 Stadiums | C11: Home(Australia): 5000 (Won) | D11: 6. The Latitude Clash (Away) | F11: Total Credits | H11: =H10 -> 1000 | I11: =I10 -> 20 | K11: Best Batsman (1000): 1
A12: 7. Faizan | B12: None | C12: Away(South Africa): 5000 (Won) | D12: 7. RED & GREEN RIVALRY II (Away) | K12: Best Bowler(1000): 3
A13: 8. Manjeet | C13: Away(Ireland): 5000 (Won) | K13: Best Bat Average(10000)
A14: 9. Mansoor | C14: Home(Newzealand): 5000 (Lost) | K14: Player of the Tournament(30000)
A15: 10. Najibullah | C15: Away(PNG,Netherlands & West Indies): 7500 (Lost) | J15: 2. Rehan | K15: Best Batsman (1000): 1 | L15: 16000
A16: 11. Ahsas Kapri | C16: Home(Spain & Kenya): 5000 bet (Lost) | K16: Best Batsman of the Tournament(15000)
A17: 12. Neak Mohammad | C17: Away(Australia & West Indies): 10000 (Lost) | J17: 3. Akash Pol | K17: Best Bowler(1000): 1 | L17: 1000
A18: 13. Rehan | C18: Away(West Indies): 5000 (Won) | J18: Runners Up | L18: 75000
A19: 14. Romeo | B19: Traded Palyers: | C19: Away(Ireland): 5000 (Lost)
A20: 15. Sajjad Kapri | B20: 0 | C20: Away(Ireland): 5000 (Won)
A21: 16. Sahnavaz | B21: 1. Sajjad from Bangladesh: 25000
A22: 17. Shebin | B22: 2. Allabux to Bangladesh: 25000
A23: 18. Vishesh | B23: 3. Naveen to PNG: Free
A24: 19. Fawad Kapri
A26: All Franchise League Credits Updates :
A27: =A29 -> 21000
A28: Qatar Elite Crown League :
A29: =A32 -> 21000
A30: 2026
A31: All Team Profit:
A32: =A35+B35+C35+D35+E35+F35+G35+H35 -> 21000
A33: AL KHOR PREDATORS | B33: AL RAYYAN RAIDERS | C33: AL WAKRAH DUKES | D33: DOHA STALLIONS | E33: LUSAIL KNIGHTS | F33: MESAEID BLAZE | G33: QATAR VENOMS | H33: UMM SALAL SPARTANS
A34: Team Profit: | B34: Team Profit: | C34: Team Profit: | D34: Team Profit: | E34: Team Profit: | F34: Team Profit: | G34: Team Profit: | H34: Team Profit:
A35: 0 | B35: 15000 | C35: 0 | D35: 6000 | E35: 0 | F35: 0 | G35: 0 | H35: 0
B36: 1. Naveen Gupta | D36: 1. Blessy
B37: Salary: 15000 | D37: Salary: 6000

Sheet England
A1: Board: England
A2: Chairman: Diljith Das | CEO: Sujith CS Ctr
A3: TITLE SPONSORS: Cricket Circle
A4: KIT SPONSORS: S-Mark SportsWear
A5: MERCHANDISE SPONSORS: Brand Sports
A6: Credits left:
A7: =100000+B9+C9+D9+F9+G9+I9+A74+E30+L9+F28+E34+N9+W9+F34+T9+Q9 -> 3834985
A8: Players | B8: Stadium: | C8: International Series: | D8: Whitewash lose: | E8: Trophy Cabinet ( International series) | F8: Traded Player: | G8: IOCF T20 WORLD CUP 🏆 : | I8: IOCF WORLD TEST CHAMPIONSHIP 🏆: | L8: EMERGING TALENTS LEAGUE: | N8: CONTINENTAL CUP 2026 🏆: ( EURO ) | Q8: Women's Global League 2026 🏆: | T8: ODI WORLD CUP 2026 🏆: | W8: Umpires Credits :
A9: 1. Aash Muhammad | B9: -260000 | C9: 87000 | D9: -1500 | E9: 1. Sir Vivian Richards Trophy ( Away ) | F9: 24000 | G9: 92600 | I9: =I11+J11+K11 -> -1000 | L9: 135000 | N9: =N11 -> 403200 | Q9: =Q11 -> 50000 | T9: =T11 -> 1053000 | W9: =Z18+Z23+Z40+Z43+Z51+Z54+Z57+Z59+Z61 -> 481000
A10: 2. Abhijith | B10: Level 3 Stadiums | C10: Away( West Indies ): 10000 bet ( Won ) | D10: 1. Anderson Tendulkar ( India ) | E10: 2. Anglo Scotish Trophy ( Home ) | F10: 1. Subaida to SA : 7000 | G10: Entry: -5000 | H10: Players Awards: 30000 | I10: Player Awards | J10: Match Bet Credits | K10: Entry Credits | L10: Tournament Awards: | M10: Award Winners | N10: Players & Match Awards | Q10: Players & Match Awards | T10: Players & Match Awards | W10: Umpire | X10: Details | Y10: Total Matches | Z10: Credits | AA10: Points
A11: 3. Achuz Sukumaran | B11: Lords International Stadium | C11: Home( India ): 5000 bet ( Lost ) | D11: 2. The Ashes ( Test - Australia ) | E11: 3. Commonwealth Crown ( Home ) | F11: 2. Hirak to Ned: 5000 | G11: Players Awards: 7600 | H11: 1. Toby Joseph | I11: =K29+K32+K35+K38+K41+K44+K47+K50+K53+K56+K59 -> 15000 | J11: -11000 | K11: -5000 | L11: Match of the Tournament: | M11: Eng vs WI (15000) | N11: =P13+P17+P18+P21+P23+P25 -> 403200 | Q11: =S13+S14 -> 50000 | T11: =V13+V14+V19+V21+V23+V24+V26+V27+V28 -> 1053000 | W11: 1. Diljith Das | X11: Club Series | Y11: 11 | Z11: =Y11*1000 -> 11000 | AA11: =Y11*20 -> 220
A12: 4. Ajin P Anil | B12: WGG International Stadium | C12: Home ( Scotland ): 5000 bet ( Won ) | E12: 4. Crown series ( Home ) | F12: 3. Ashuotsh to Ned: 5000 | G12: 1. Rahees | H12: Most Dot Balls(65): 5000 | J12: Home(West Indies): 6000 bet (Lost) | K12: Trophy Cabinet (Test) | L12: Best Talent Discovery Board: | M12: England (10000) | N12: Player | O12: Award | P12: Credits | Q12: Player | R12: Award | S12: Credits | T12: Player | U12: Award | V12: Credits | X12: T20 Series | Y12: 0.5 | Z12: =Y12*3000 -> 1500 | AA12: =Y12*40 -> 20
A13: 5. Arjun AKJ | B13: The Rose Bowl | C13: Away ( Afghanistan): 3000 bet ( Lost ) | E13: 5. Yuvraj Flintoff ( Away ) | F13: 4. Subaida to Italy: 7000 | G13: Man of the match: 1 | H13: 2. Rejith Mohan | J13: Home (Italy): 5000 bet (Won) | K13: 1. Royal Test | L13: Fair Play: | M13: England(15000) | N13: 1. Safeer Babu | O13: Man of the match(2000): 4 | P13: =12000+25000+5400 -> 42400 | Q13: Best Women Talent Discovery Board | S13: 20000 | T13: 1. Sujith CS Ctr | U13: Best Bowler(3000): 1 | V13: 3000 | X13: Test Tournament | Y13: 1.5 | Z13: =Y13*8000 -> 12000 | AA13: =Y13*80 -> 120
A14: 6. Dileep Kumar | B14: Trent Bridge | Franchise League L1 | Upgraded | C14: Home ( Srilanka): 5000 bet ( Lost) | E14: 6. Ashes Blitz ( Home ) | F14: 5. Vishnu to Italy: 3000 | G14: • vs Australia: 500 | H14: Fastest Century(24B): 5000 | J14: Home(Bangladesh): 10000 bet (Lost) | K14: 2. Royal Lion | L14: Best Batsman: | M14: Shajahan (20000) | O14: Best Bowler(1000): 4 | Q14: Sneha Jyothish | R14: Best Batsman | S14: 30000 | T14: 2. Safeer Babu | U14: Man of the match(5000): 2 | V14: 23000 | X14: Club Tournament | Y14: 1.5 | Z14: =Y14*2000 -> 3000 | AA14: =Y14*20 -> 30
A15: 7. Gowri Madhu | B15: The Oval | C15: Home ( Newzealand): 5000 bet ( Won ) | E15: 7. Dutch Anglo ( Away ) | F15: 6. Aneesh to WI: 20000 | G15: Economical bowler: 3 | H15: Most Fours:5000 | J15: Home (Pakistan): 10000 bet (Won) | K15: 3. Great Subcontinent Clash | L15: Player of the Tournament: | M15: Shajahan (25000) | O15: Golden Ball Award(25000) | U15: Best Batsman(3000): 1 | X15: Franchise League
A16: 8. Jyothish | B16: Old Trafford | C16: Home ( Pakistan): 5000 bet ( Won ) | E16: 8. Karachi London (Away ) | F16: 7. Harshad Vanimal | Removed | G16: • vs Australia: 300 | H16: Best Batsman: 10000 | J16: Home (India): 5000 bet (Won) | K16: 4. Fortress Cup | L16: Runners UP: | M16: 50000 | O16: Team of the tournament - 5400 | U16: Best Bowler(3000): 2 | X16: 100 | Y16: 3.5 | Z16: =Y16*1500 -> 5250 | AA16: =Y16*60 -> 210
A17: 9. Molly Stephan | B17: Yorkshire Headingley | C17: Home ( Australia ): 10000 bet ( Lost ) | E17: 9. London Trophy (Home) | F17: 8. Karthik Verma | Removed | G17: • vs West Indies: 300 | H17: 3. Diljith Das | J17: Away (Newzealand): 5000 bet (Lost) | K17: 5. London Trophy | N17: 2. Sanoop | O17: Best Batsman(1000): 1 | P17: =1000 -> 1000 | U17: Most Sixes(1000): 2 | X17: 100 ( Commentory ) | Y17: 1 | Z17: =Y17*1500 -> 1500 | AA17: =Y17*60 -> 60
A18: 10. Nechuz | B18: Somerset County Ground | C18: Away ( India ): 10000 bet ( Won ) | E18: 10. Northwave Trophy (Away) | F18: 9. Amith | Removed | G18: • vs Newzealand: 300 | H18: Fastest Fifty(10B): 5000 | J18: Away (Australia): 5000 bet (Won) | K18: 6. Imperial Lords | N18: 3. Rahees | O18: Man of the match(2000): 1 | P18: =3000+5400 -> 8400 | U18: Most Dot Balls(1000): 2 | X18: Total Credits | Z18: =Z11+Z12+Z16+Z17+Z13+Z14 -> 34250 | AA18: =AA11+AA12+AA16+AA17+AA13+AA14 -> 660
A19: 11. Nisham | B19: Level 2 Stadiums | C19: Home ( Australia ): 5000 bet ( Won ) | E19: 11. The Arabian Challenge (Home) | F19: 10. Sadik | Removed | G19: Most Sixes: 1 | J19: Home (Australia): 5000 bet (Won) | K19: 7. Royal WTC Clash | O19: Best Bowler(1000): 1 | T19: 3. Sunaif | U19: Best Batsman(3000): 1 | V19: 4000 | W19: 2. Achuz | X19: Club Series | Y19: 2 | Z19: =Y19*1000 -> 2000 | AA19: =Y19*20 -> 40
A20: 12. Rahees | B20: Middlesex Lords County Cricket Ground | C20: Away (England): 5000 bet (Won) | E20: 12. Anz ODI Clash (Home) | F20: 11. Shajahan | | Removed | G20: • vs Afghanistan: 300 | H20: Runners Up: 40000 | J20: Away(Qatar): 5000 bet (Lost) | O20: Team of the tournament - 5400 | U20: Most Sixes(1000): 1 | X20: Franchise League
A21: 13. Rashid | B21: Durahm Riverside Ground | C21: Home ( West Indies): 6000 bet (Lost) | E21: 13. Royal Anglo Trophy (Home) | F21: 12. Sujith to Portugal: 2000 | G21: 2. Aneesh | J21: Home(Netherlands): 5000 bet (Won) | N21: 4. Diljith Das | O21: Best Captain Award(15000) | P21: =15000+6000 -> 21000 | T21: 4. Renjish | U21: Man of the match(5000): 1 | V21: 8000 | X21: 100 | Y21: 0.5 | Z21: =Y21*1500 -> 750 | AA21: =Y21*60 -> 30
A22: 14. Renjish | B22: Level 1 Stadiums | C22: Home (Italy): 5000 bet (Lost) | E22: 14. Unity T20 Cup (Home) | F22: 13. Dileep from PNG: 15000 | G22: Most sixes: 1 | H22: Prediction Winners: 20000 | J22: Away (Bangladesh): 5000 bet (Won) | O22: Team of the tournament(Captain) - 6000 | U22: Best Batsman(3000): 1 | X22: CPL | Y22: 2 | Z22: =Y22*1500 -> 3000 | AA22: =Y22*60 -> 120
A23: 15. Sachin P | B23: None | C23: Home (Bangladesh): 10000 bet ( Lost ) | E23: 15. Legacy Cup (Away) | G23: • vs Australia: 300 | J23: Away(UAE): 5000 bet (Lost) | N23: 5. Sunaif | O23: Golden Bat Award(25000) | P23: =25000+5400 -> 30400 | T23: 5. Rahees | U23: Best Bowler(3000): 1 | V23: 3000 | X23: Total Credits | Z23: =Z19+Z21+Z22 -> 5750 | AA23: =AA19+AA21+AA22 -> 190
A24: 16. Safeer Babu | C24: Away (Pakistan): 5000 bet (Won) | E24: 16. Royal Rivalry Cup (Home) | G24: 3. Toby | J24: Away(Netherlands): 10000 (Lost) | O24: Team of the tournament - 5400 | T24: 6. Diljith Das | U24: Man of the match(5000): 1 | V24: 8000 | W24: 3. Jyothish | X24: Club Series | Y24: 17.5 | Z24: =Y24*1000 -> 17500 | AA24: =Y24*20 -> 350
A25: 17. Sanoop | C25: Home (West Indies): 5000 bet (Won) | E25: 17. Crown & Pearl (Home) | G25: Man of the match: 2 | J25: Home(Scotland): 10000 (Lost) | N25: Champions | P25: 300000 | U25: Best Bowler(3000): 1 | X25: Club Tournament | Y25: 4 | Z25: =Y25*2000 -> 8000 | AA25: =Y25*20 -> 80
A26: 18. Sri Vishnu | C26: Away (Netherlands): 4000 bet (Won) | E26: 18. ODI WC Warmup 5 (Home) | G26: • vs Afghanistan: 500 | T26: 7. Ajin | U26: Best Batsman(3000): 1 | V26: 3000 | X26: T10 Series | Y26: 7.5 | Z26: =Y26*2000 -> 15000 | AA26: =Y26*40 -> 300
A27: 19. Sunaif | C27: Home(Bangladesh): 5000 bet(Lost) | E27: 19. Kingstown Cup (Away) | F27: Player limit exceeded: | G27: • vs South Africa: 500 | I27: Players Awards & Credits | T27: 8. Sanoop | U27: Most Sixes(1000): 1 | V27: 1000 | X27: T20 Series | Y27: 20 | Z27: =Y27*3000 -> 60000 | AA27: =Y27*40 -> 800
C28: Away (Netherlands): 5000 bet (Lost) | F28: -10000 | G28: Economical bowler: 3 | I28: Player | J28: Award | K28: Credits | T28: Semifinalists | V28: 1000000 | X28: ODI Series | Y28: 7 | Z28: =Y28*5000 -> 35000 | AA28: =Y28*100 -> 700
C29: Home(Srilanka): 5000 bet (Lost) | E29: IOCF LONE WARRIOR | F29: 1. 20 to 25: 10000 | G29: • vs Scotland: 300 | I29: 1. Aneesh | J29: Man of the Match: 0 (1000) | K29: 500 | X29: T20 Tournament | Y29: 4.5 | Z29: =Y29*6000 -> 27000 | AA29: =Y29*40 -> 180
C30: Home(UAE): 5000 bet (Won) | E30: 40000 | G30: • vs South Africa: 300 | J30: Best Batsman: 1 (500) | X30: Test Tournament | Y30: 17 | Z30: =Y30*8000 -> 136000 | AA30: =Y30*80 -> 1360
C31: Away(Australia): 10000 bet (Lost) | E31: Champion: Diljith Das | G31: • vs Scotland(Final): 500 | J31: Best Bowler: 0 (500) | X31: ODI Tournament | Y31: 7 | Z31: =Y31*10000 -> 70000 | AA31: =Y31*100 -> 700
C32: Home(Newzealand): 10000 bet (Won) | G32: 4. Rejith | I32: 2. Jyothish S | J32: Man of the Match: 4 (1000) | K32: 6000 | X32: Test Series | Y32: 2.5 | Z32: =Y32*4000 -> 10000 | AA32: =Y32*80 -> 200
C33: Home(Bangladesh): 5000 bet(Won) | E33: IOCF HALL OF FAME | F33: Sponsors | G33: Man of the match: 2 | J33: Best Batsman: 0 (500) | X33: Franchise League
C34: Home(Bangladesh): 5000 bet (Won) | E34: 100000 | F34: 300000 | G34: • vs West Indies: 500 | J34: Best Bowler: 4 (500) | X34: 100 | Y34: 3 | Z34: =Y34*1500 -> 4500 | AA34: =Y34*60 -> 180
C35: Home(Bangladesh): 5000 bet (Lost) | E35: Molly Stephan | F35: 1. Cricket Circle (Title Sponsors) | G35: • vs Newzealand: 500 | I35: 3. Toby Joseph | J35: Man of the Match: 0 (1000) | K35: 500 | X35: PSL | Y35: 4 | Z35: =Y35*1500 -> 6000 | AA35: =Y35*60 -> 240
C36: Home(UAE): 5000 bet (Lost) | E36: Ring of Fire : Top Scorer | F36: 2. S-Mark SportsWear (Kit Sponsors) | G36: Most sixes: 1 | J36: Best Batsman: 1 (500) | X36: KCL | Y36: 3 | Z36: =Y36*1500 -> 4500 | AA36: =Y36*60 -> 180
C37: Away(Australia): 10000 bet (Won) | E37: Jyothish S | F37: 3. Brand Sports ( Merchandise Sponsor ) | G37: • vs West Indies: 300 | J37: Best Bowler: 0 (500) | X37: IPL | Y37: 5 | Z37: =Y37*1500 -> 7500 | AA37: =Y37*60 -> 300
C38: Home(India): 10000 bet (Won) | E38: Ring of Fire : Top Wicket Taker | G38: • vs Newzealand: 300 | I38: 4. Safeer Babu | J38: Man of the Match: 1 (1000) | K38: 2000 | X38: BBL | Y38: 2 | Z38: =Y38*1500 -> 3000 | AA38: =Y38*60 -> 120
C39: Home(South Africa): 5000 (Won) | G39: 5. Achuz | J39: Best Batsman: 0 (500) | X39: CPL | Y39: 4 | Z39: =Y39*1500 -> 6000 | AA39: =Y39*60 -> 240
C40: Home(Uganda): 5000 (Won) | G40: Man of the match: 1 | J40: Best Bowler: 2 (500) | X40: Total Credits | Z40: =Z24+Z25+Z26+Z27+Z28+Z29+Z30+Z34+Z35+Z36+Z37+Z38+Z39+Z31+Z32 -> 410000 | AA40: =AA24+AA25+AA26+AA27+AA28+AA29+AA30+AA34+AA35+AA36+AA37+AA38+AA39+AA31+AA32 -> 5930
C41: Home(India): 5000 bet (Won) | G41: • vs Scotland: 500 | I41: 5. Rahees | J41: Man of the Match: 0 (1000) | K41: 1500 | W41: 4. Arjun AKJ | X41: Franchise League
C42: Away(West indies): 10000 (Won) | G42: 6. Diljith | J42: Best Batsman: 2 (500) | X42: 100 | Y42: 0.5 | Z42: =Y42*1500 -> 750 | AA42: =Y42*60 -> 30
C43: Home(Italy & Newzealand): 10000 (Lost) | G43: Most Sixes:1 | J43: Best Bowler: 1 (500) | X43: Total Credits | Z43: =Z42 -> 750 | AA43: =AA42 -> 30
C44: Home(India): 10000 bet (Lost) | G44: • vs Scotland: 300 | I44: 6. Molly | J44: Man of the Match: 0 (1000) | K44: 500 | W44: 5. Sujith CS Ctr | X44: Club Series | Y44: 4 | Z44: =Y44*1000 -> 4000 | AA44: =Y44*20 -> 80
C45: Away(Bangladesh): 10000 bet (Lost) | G45: 7. Safeer Babu | J45: Best Batsman: 1 (500) | X45: T20 Series | Y45: 1 | Z45: =Y45*3000 -> 3000 | AA45: =Y45*40 -> 40
C46: Away(Nepal & Portugal): 3000 bet (Lost) | G46: Man of the match: 1 | J46: Best Bowler: 0 (500) | X46: Test Tournament | Y46: 1.5 | Z46: =Y46*8000 -> 12000 | AA46: =Y46*80 -> 120
G47: • vs West Indies(Semis): 500 | I47: 7. Sujith Kumar | J47: Man of the Match: 0 (1000) | K47: 500 | X47: Club Tournament | Y47: 1 | Z47: =Y47*2000 -> 2000 | AA47: =Y47*20 -> 20
G48: Economical bowler: 1 | J48: Best Batsman: 1 (500) | X48: T10 Series | Y48: 1 | Z48: =Y48*2000 -> 2000 | AA48: =Y48*40 -> 40
G49: • vs West Indies(Semis): 300 | J49: Best Bowler: 0 (500) | X49: Franchise League
G50: 8. Sujith CS Ctr | I50: 8. Karthik Verma | J50: Man of the Match: 0 (1000) | K50: 500 | X50: 100 | Y50: 0.5 | Z50: =Y50*1500 -> 750 | AA50: =Y50*60 -> 30
G51: Most Sixes:1 | J51: Best Batsman: 1 (500) | X51: Total Credits | Z51: =Z50+Z46+Z45+Z44+Z47+Z48 -> 23750 | AA51: =AA50+AA46+AA45+AA44+AA47+AA48 -> 330
G52: • vs West Indies(Semis): 300 | J52: Best Bowler: 0 (500) | W52: 6. Aniket Gavit | X52: Franchise League
I53: 9. Ajin | J53: Man of the Match: 0 (1000) | K53: 500 | X53: 100 | Y53: 2 | Z53: =Y53*1500 -> 3000 | AA53: =Y53*60 -> 120
J54: Best Batsman: 1 (500) | X54: Total Credits | Z54: =Z53 -> 3000 | AA54: =AA53 -> 120
J55: Best Bowler: 0 (500) | W55: 7. Rahees | X55: Franchise League
I56: 10. Aash | J56: Man of the Match: 2 (1000) | K56: 1500 | X56: 100 ( Commentory ) | Y56: 1 | Z56: =Y56*1500 -> 1500 | AA56: =Y56*60 -> 60
J57: Best Batsman: 0 (500) | X57: Total Credits | Z57: =Z56 -> 1500 | AA57: =AA56 -> 60
J58: Best Bowler: 1 (500) | W58: 8. Sanoop | X58: Club Series | Y58: 1 | Z58: =Y58*1000 -> 1000 | AA58: =Y58*20 -> 20
I59: 11. Diljith Das | J59: Man of the Match: 0 (1000) | K59: 1000 | X59: Total Credits | Z59: =Z58 -> 1000 | AA59: =AA58 -> 20
J60: Best Batsman: 2 (500) | W60: 9. Ajin P Anil | X60: Club Series | Y60: 1 | Z60: =Y60*1000 -> 1000 | AA60: =Y60*20 -> 20
J61: Best Bowler: 0 (500) | X61: Total Credits | Z61: =Z60 -> 1000 | AA61: =AA60 -> 20
A73: All Franchise League Credits Updates :
A74: =A138+A117+A103+A76+A154+A169+A195+A208+A233+A244 -> 1241685
A75: THE HUNDRED ( Own League )
A76: 145500
A77: 2026
A78: Hosting Rights : 40000
A79: All Team Profit: 123200
A80: London Spirit | B80: Southern Brave | C80: Welsh Fire | D80: MI London | E80: Sunrisers Leeds
A81: Team Profit: 14500 | B81: Team Profit: 26600 | C81: Team Profit: 14500 | D81: Team Profit: 32100 | E81: Team Profit: 42800
A82: 1. Shibasis | B82: 1. Rejith Mohan | C82: 1. Arjun Akj | D82: 1. Aniket Gavit | E82: 1. Achuz Sukumaran
A83: Captain Salary: 8000 | B83: Captain Salary: 8000 | C83: Captain Salary: 8000 | D83: Captain Salary: 8000 | E83: Captain Salary: 8000
A84: 2. Toby Joseph | B84: Man of the match: 1 ( 500 ) | C84: 2. Diljith Das | D84: Man of the match:1 ( 500 ) | E84: Best Bowler: 1 ( 200 )
A85: Marquee Salary: 2000 | B85: Best Batsman: 1 ( 200 ) | C85: Marquee Salary: 2000 | D85: Champions: 5800 | E85: Runners up: 2950
A86: 3. Sujith Kumar | B86: Best Bowler: 1 ( 200 ) | C86: 3. Rahees | D86: 2. Sujith CS Ctr | E86: 2. Safeer Babu
A87: Salary: 4500 | B87: 2. Jyothish S | C87: Salary: 4500 | D87: Marquee Salary: 2000 | E87: Marquee Salary: 2000
A88: 4. Nadirsha Nachu | B88: Marquee Salary: 2000 | C88: 4. Sreeju | D88: Man of the match:1 ( 500 ) | E88: Best Bowler: 3 ( 600 )
A89: Salary: 4000 | B89: 3. Aash Muhammad | C89: Salary: 4000 | D89: Best Batsman: 1 ( 200 ) | E89: Man of the match: 2 (1000)
B90: Salary: 4500 | D90: Champions: 5300 | E90: Best Bowler of the tournament: 10000
B91: Best Bowler: 1 ( 200 ) | D91: 3. Rashid | E91: Runners up: 2850
B92: 4. Vishnu CV | D92: Salary: 4500 | E92: 3. Molly
B93: Salary: 4000 | D93: Champions: 5300 | E93: Salary: 4500
B94: Emerging Player award: 5000 | D94: 4. Sadik | E94: Runners up: 2850
B95: 5. Sadik | D95: Salary: 4000 | E95: 4. Aneesh
B96: Salary: 2000 | E96: Salary: 4000
E97: Runners up: 2850
A98: Sai Naveen, Bhavesh & Siddiqui called for national duty ( Bangladesh ) for 15k
A99: Suman called for National Duty ( NZ ) for 1k
A100: Rating By All Boards on The Hundred 2026(8 out of 10): 40000 credits
A102: Pakistan Super League :
A103: 24980
A104: 2026
A105: LAHORE QALANDARS | B105: PINDIZ | C105: MULTAN SULTANS | D105: KARACHI KINGS | E105: QUETTA GLADIATORS | F105: HYDERABAD KINGSMEN
A106: Team Profit: 18080 | B106: Team Profit: 2500 | C106: Team Profit: 3400
A107: 1. Subaida Subi | B107: 1. Achuz Sukumaran | C107: 1. Aniket Gavit
A108: Salary: 6200 | B108: Salary: 1500 | C108: Salary: 3400
A109: Man of the match: 2 ( 1000 ) | B109: Man of the match: 2 ( 1000 )
A110: Best Bowler: 2 ( 400 )
A111: Champions: 4990
A112: 2. Vishnu
...

Sheet India
A1: Board: INDIA
A2: Chairman: Shivaji Prakash | CEO: Jana CP
A3: Credits left:
A4: =100000+B6+C6+D6+E6+F6+G6+A53+C24+F12+J6+P6+M6 -> 3852710
A5: Players | B5: Stadium: | C5: International Series: | D5: Whitewash: | E5: IOCF T20 WORLD CUP 🏆: | F5: Player limit Increased: | G5: IOCF WORLD TEST CHAMPIONSHIP 🏆: | J5: CONTINENTAL CUP 2026 🏆: ( ASIA ) | M5: ODI WORLD 2026 🏆: | P5: Umpires Credits :
A6: 1. Abheshek | B6: -170000 | C6: 17000 | D6: 1000 | E6: 35000 | F6: -10000 | G6: =G8+H8+I8 -> -500 | J6: =J8 -> 21800 | M6: =M8 -> 846000 | P6: =S16+S19+S23+S26+S29+S33+S36+S39 -> 145750
A7: 2. Abin | B7: Level 3 Stadiums | C7: Away( England ): 5000 bet ( Won ) | D7: 1. Anderson Tendulkar ( England ) | E7: Entry: -5000 | F7: 1. 20 to 25: 10000 | G7: Player Awards | H7: Match Bet Credits | I7: Entry Credits | J7: Players & Match Awards | M7: Players & Match Awards | P7: Umpire | Q7: Details | R7: Total Matches | S7: Credits | T7: Points
A8: 3. Ajith | B8: Eternal Coliseum | C8: Away( Srilanka): 6000 bet ( Lost ) | E8: Players Awards: 5000 | G8: =I21+I24+I27+I30+I33+I36 -> 9000 | H8: -4500 | I8: -5000 | J8: =L10+L13+L15+L16 -> 21800 | M8: =O10+O15+O17+O20+O21+O22+O23 -> 846000 | P8: 1. Shivaji Prakash | Q8: Club Series | R8: 18 | S8: =R8*1000 -> 18000 | T8: =R8*20 -> 360
A9: 4. Anshad P | B9: Sree Padmanaba Cricket Park | C9: Home ( England): 10000 ( Lost ) | E9: 1. Anshad | H9: Away (Afghanistan): 7000 bet (Lost) | I9: Trophy Cabinet (Test) | J9: Player | K9: Award | L9: Credits | M9: Player | N9: Award | O9: Credits | Q9: T10 Series | R9: 5 | S9: =R9*2000 -> 10000 | T9: =R9*40 -> 200
A10: 5. Asish Anandhu | B10: Jannat Wadi | Franchise League L1 | Upgraded | C10: Away (Netherlands): 2000 (Lost) | E10: Man of the match: 1 | H10: Away(Netherlands): 2500 bet (Won) | I10: 1. Zubeen Garg Rhine A | J10: 1. Shivaji Prakash | K10: Best Batsman(1000): 1 | L10: =2000+5400 -> 7400 | M10: 1. Shivaji Prakash | N10: Man of the match(5000): 2 | O10: 324000 | Q10: Test Tournament | R10: 3 | S10: =R10*8000 -> 24000 | T10: =R10*80 -> 240
A11: 6. Asru | B11: Level 2 Stadiums | C11: Away(Australia): 5000 (Won) | E11: • vs Pakistan: 500 | F11: Players Trade | H11: Away (England): 5000 bet (Lost) | I11: 2. Legacy Trophy | K11: Best Bowler(1000): 1 | N11: Best Bowler(3000): 2 | Q11: ODI Tournament | R11: 3 | S11: =R11*10000 -> 30000 | T11: =R11*80 -> 240
A12: 7. Aswin Babu | B12: None | C12: Home(Australia): 5000 (Lost) | E12: Economical Bowler: 2 | F12: -270000 | H12: Home (Pakistan): 5000 bet (Won) | I12: 3. Border-Gavaskar Test | K12: Team of the tournament - 5400 | N12: Most Sixes(1000): 2 | Q12: Franchise League
A13: 8. Athif Basheer K | B13: Level 1 Stadiums | C13: Away(England): 10000 (Lost) | E13: • vs Pakistan: 300 | F13: 1. Ajith from NZ: 10000 | H13: Away(South Africa): 5000 bet (Lost) | I13: 4. Italia–Bharat Test | J13: 2. Asru KSD | K13: Man of the match(2000): 2 | L13: 6000 | N13: Most Dot Balls(1000): 6 | Q13: KCL | R13: 1 | S13: =R13*1500 -> 1500 | T13: =R13*60 -> 60
A14: 9. Farhaan | B14: Prince's Arena | C14: Away(UAE): 5000 (Lost) | E14: • vs Newzealand: 300 | F14: 2. Mowglee from WI: 100000 | H14: Home(South Africa): 5000 bet (Lost) | K14: Best Bowler(1000): 2 | N14: Most Dot Balls in the Tournament: 300000 | Q14: IPL | R14: 9 | S14: =R14*1500 -> 13500 | T14: =R14*60 -> 540
A15: 10. George | B15: Lion's Citadel | C15: Home(UAE): 5000 (Lost) | E15: 2. Raheem | F15: 3. George from WI: 100000 | H15: Home(Italy): 10000 bet (Lost) | J15: 3. Anshad P | K15: Best Batsman(1000): 1 | L15: 1000 | M15: 2. Farhan | N15: Best Batsman(3000): 1 | O15: 4000 | Q15: CPL | R15: 1 | S15: =R15*1500 -> 1500 | T15: =R15*60 -> 60
A16: 11. Gopikrishnan SV | B16: Master's Arena | C16: Away(England): 5000 (Lost) | D16: Trophy Cabinet | E16: Most Sixes: 1 | F16: 4. Aswin from USA: 60000 | H16: Away(Australia): 10000 bet (Won) | J16: 4. Jana CP | K16: Man of the match(2000): 1 | L16: =2000+5400 -> 7400 | N16: Most Sixes(1000): 1 | Q16: Total Credits | S16: =S8+S9+S10+S13+S14+S15+S11 -> 98500 | T16: =T8+T9+T10+T13+T14+T15+T11 -> 1700
A17: 12. Harish Byndoor | B17: King's Fortress | C17: Away(Australia): 5000 (Lost) | D17: 1. Coca Cola Cup | E17: • vs Pakistan: 300 | H17: Away(Italy): 10000 (Won) | K17: Team of the tournament - 5400 | M17: 3. Anshad Parakkadan | N17: Man of the match(5000): 1 | O17: 9000 | P17: 2. Jana CP | Q17: Franchise League
A18: 13. Mowglee | B18: Marusthal Arena | C18: Home(West Indies): 10000 (Won) | D18: 2. India - Carribbean Showdown Series(Home) | E18: 3. Shivaji Prakash | N18: Best Bowler(3000): 1 | Q18: IPL | R18: 4.5 | S18: =R18*1500 -> 6750 | T18: =R18*60 -> 270
A19: 14. Peter John | B19: Imperial Stadium | C19: Home(West Indies): 10000 (Won) | D19: 3. India - Caribbean ODI Showdown Series (Home) | E19: Man of the match: 1 | G19: Players Awards & Credits | N19: Most Sixes(1000): 1 | Q19: Total Credits | S19: =S18 -> 6750 | T19: =T18 -> 270
A20: 15. Pradeesh P | B20: Dwarka Coliseum | C20: Away(India): 10000 (Won) | D20: 4. Anderson-Tendulker t20 trophy (Away) | E20: • vs Srilanka: 500 | G20: Player | H20: Award | I20: Credits | M20: 4. Jana CP | N20: Most Dot Balls(1000): 1 | O20: 1000 | P20: 3. Abhishek | Q20: Franchise League
A21: 16. Raheem K | B21: Royal Deccan | C21: Away(UAE): 10000 (Won) | D21: 5. TITANS Cup (Away) | E21: Economical bowler: 2 | G21: 1. Rahul Seenu | H21: Man of the Match: 0 (1000) | I21: 500 | M21: 5. Peter John | N21: Man of the match(5000): 1 | O21: 5000 | Q21: IPL | R21: 5 | S21: =R21*1500 -> 7500 | T21: =R21*60 -> 300
A22: 17. Rahman SN | B22: Eternal Aryavarta | C22: Away(Newzealand): 10000 (Lost) | E22: • vs South Africa: 300 | H22: Best Batsman: 0 (500) | M22: 6. Asru MSD | N22: Best Bowler(3000): 1 | O22: 3000 | Q22: CPL | R22: 2 | S22: =R22*1500 -> 3000 | T22: =R22*60 -> 120
A23: 18. Rahul Roy | B23: Sher-E-Punjab | C23: IOCF LONE WARRIOR | E23: • vs Scotland(Semis): 300 | H23: Best Bowler: 1 (500) | M23: Quarterfinalists | O23: 500000 | Q23: Total Credits | S23: =S21+S22 -> 10500 | T23: =T21+T22 -> 420
A24: 19. Rahul Seenu | C24: 10000 | E24: Most Sixes: 1 | G24: 2. Farhan | H24: Man of the Match: 1 (1000) | I24: 2000 | P24: 4. Athif Basheer | Q24: Franchise League
A25: 20. Rajeev | C25: Semifinalit: Anshad | E25: • vs Newzealand: 300 | H25: Best Batsman: 2 (500) | Q25: IPL | R25: 4 | S25: =R25*1500 -> 6000 | T25: =R25*60 -> 240
A26: 21. Robert John | E26: 4. Pradeesh | H26: Best Bowler: 0 (500) | Q26: Total Credits | S26: =S25 -> 6000 | T26: =T25 -> 240
A27: 22. Sanjith | E27: Economical Bowler: 1 | G27: 3. Jana | H27: Man of the Match: 2 (1000) | I27: 4000 | P27: 5. Robert John | Q27: Franchise League
A28: 21. Niyas | E28: • vs Srilanka: 300 | H28: Best Batsman: 2 (500) | Q28: IPL | R28: 3 | S28: =R28*1500 -> 4500 | T28: =R28*60 -> 180
A29: 22. Mashoo | E29: 5. Jana | H29: Best Bowler: 2 (500) | Q29: Total Credits | S29: =S28 -> 4500 | T29: =T28 -> 180
A30: 23. Zachu | E30: Man of the match: 1 | G30: 4. Asru | H30: Man of the Match: 1 (1000) | I30: 1500 | P30: 6. Farhan | Q30: Franchise League
A31: 24. Achu RVD | E31: • vs South Africa: 500 | H31: Best Batsman: 1 (500) | Q31: IPL | R31: 3 | S31: =R31*1500 -> 4500 | T31: =R31*60 -> 180
E32: 6. Abin | H32: Best Bowler: 0 (500) | Q32: IPL ( Commentator ) | R32: 1 | S32: =R32*1500 -> 1500 | T32: =R32*60 -> 60
E33: Most Sixes: 1 | G33: 5. Shivaji Prakash | H33: Man of the Match: 0 (1000) | I33: 500 | Q33: Total Credits | S33: =S31+S32 -> 6000 | T33: =T31+T32 -> 240
E34: • vs South Africa: 300 | H34: Best Batsman: 0 (500) | P34: 7. Gopikrishnan | Q34: Franchise League
E35: 7. Farhaan | H35: Best Bowler: 1 (500) | Q35: IPL ( Commentator ) | R35: 1 | S35: =R35*1500 -> 1500 | T35: =R35*60 -> 60
E36: Man of the match: 1 | G36: 6. Pradeesh P Nair | H36: Man of the Match: 0 (1000) | I36: 500 | Q36: Total Credits | S36: =S35 -> 1500 | T36: =T35 -> 60
E37: • vs England: 500 | H37: Best Batsman: 0 (500) | P37: 8. Mowglee | Q37: T10 Series | R37: 1 | S37: =R37*2000 -> 2000 | T37: =R37*40 -> 40
E38: Most Sixes: 1 | H38: Best Bowler: 1 (500) | Q38: ODI Tournament | R38: 1 | S38: =R38*10000 -> 10000 | T38: =R38*80 -> 80
E39: • vs England: 300 | Q39: Total Credits | S39: =S38+S37 -> 12000 | T39: =T38+T37 -> 120
E40: 8. Gopi SV
E41: Economical Bowler: 1
E42: • vs England: 300
E43: Semifinalists: 20000
E45: Players Awards: 5000
E46: 1. Anshad
E47: Best Bowling Figure(7-21) : 5000
E49: Prediction Runners: 10000
A52: All Franchise League Credits Updates :
A53: =A55+A73+A89+A105+A121+A141+A172+A204+A226 -> 3126660
A54: THE HUNDRED :
A55: 44550
A56: 2026
A57: London Spirit | B57: Southern Brave | C57: Welsh Fire | D57: MI London | E57: Sunrisers Leeds
B58: Team Profit: 5400 | C58: Team Profit: 31400 | E58: Team Profit: 7750
B59: 1. Gopikrishnan SV | C59: 1. Shivaji Prakash | E59: 1. Anshad
B60: Salary: 3500 | C60: Salary: 3500 | E60: Salary: 3500
B61: Best Batsman: 1 ( 200 ) | C61: Man of the match: 2 ( 1000 ) | E61: Man of the match: 2 ( 1000 )
B62: 2. Athif Basheer K | C62: Best Bowler: 2 ( 400 ) | E62: Best Batsman:2 ( 400 )
B63: Salary: 1200 | C63: Best Batsman: 1 ( 200 ) | E63: Runners up: 2850
B64: Man of the match: 1 ( 500 ) | C64: Player of the tournament: 20000
C65: 2. Jana CP
C66: Salary: 3000
C67: 3. Rahul Seenu
C68: Salary: 2300
C69: 4. Farhaan
C70: Salary: 1000
A72: Pakistan Super League :
A73: 29860
A74: 2026
A75: LAHORE QALANDARS | B75: PINDIZ | C75: MULTAN SULTANS | D75: KARACHI KINGS | E75: QUETTA GLADIATORS | F75: HYDERABAD KINGSMEN
B76: Team Profit: 3050 | C76: Team Profit: 500 | E76: Team Profit: 21790 | F76: Team Profit: 8660
B77: 1. Athif Basheer | C77: 1. Gopikrishnan SV | E77: 1. Shivaji Prakash | F77: 1. Farhaan
B78: Salary: 2850 | C78: Salary: 500 | E78: Direct Signing: 3000 | F78: Salary: 1500
B79: Best Batsman: 1 ( 200 ) | E79: Man of the match: 1 (500) | F79: Runners up: 2480
E80: Fair Play: 1380 | F80: 2. Rahul Seenu
E81: 2. Jana CP | F81: Salary: 2200
E82: Salary: 7400 | F82: Runners up: 2480
E83: Fair Play: 1380
E84: 3. Anshad
E85: Salary: 6750
E86: Fair Play: 1380
A88: Big Bash League :
A89: 34800
A90: 2026
A91: All Team Profit: 34800
A92: Adelaide Strikers | B92: Brisbane Heat | C92: Hobart Hurricanes | D92: Melbourne Renegades | E92: Melbourne Stars | F92: Perth Scorchers | G92: Sydney Sixers | H92: Sydney Thunders
A93: Team Profit: | B93: Team Profit: | C93: Team Profit: 6000 | D93: Team Profit: 500 | E93: Team Profit: | F93: Team Profit: 8300 | G93: Team Profit: | H93: Team Profit: 21000
C94: 1. Shivaji Prakash | D94: 1. Athif | F94: 1. Rahul Seenu | H94: 1. Anshad Parakkadan
C95: Direct Signing: 5000 | D95: Salary: 500 | F95: Salary: 2200 | H95: Direct Signing: 5000
C96: Best Bowler: 1 (500) | F96: Man of the match:1 (1000) | H96: Man of the match: 1 (1000)
C97: 2. Abhishek | F97: Best Batsman: 2 (1000) | H97: 2. Jana CP
C98: Salary: 500 | F98: Best Bowler: 1 (500) | H98: Salary: 14000
F99: 2. Farhaan | H99: Man of the match: 1 (1000)
F100: Salary: 2400
F101: Best Batsman: 1 (500)
F102: 3. Rahul Roy
F103: Salary: 700
A104: Kiwi Crown League :
A105: =A108 -> 80700
A106: 2026
...

Sheet Ireland
A1: Board: Ireland
A2: Chairman: Ali Abbas Bangash | CEO: Sunny
A3: CLOTHING SPONSORS: VYLAX Clothing
A4: Credits left:
A5: =100000+B7+C7+E7+F7+F15+A30+G7+L7+B16 -> 718775
A6: Players | B6: Traded Player: | C6: Stadium: | D6: Trophy Cabinet | E6: International Series: | F6: Whitewash Win: | G6: Umpires Credits : | L6: Associate Nations CUP 2026 🏆:
A7: 1. Abhishek | B7: 47000 | C7: -60000 | D7: 1. The Green & Gold Derby( Home) | E7: 30000 | F7: 1000 | G7: =J15 -> 43000 | L7: =L9 -> 225000
A8: 2. Akshay | B8: 1. Arjun from Aus: 7000 | C8: Level 3 Stadiums | D8: 2. Sukumara Kurup Memorial Trophy (Away) | E8: Home(Zimbabwe): 3000 (Won) | F8: Against Zimbabwe: 1 | G8: Umpire | H8: Details | I8: Total Matches | J8: Credits | K8: Points | L8: Players & Match Awards
A9: 3. Alan Aji | B9: 2. Biswajit from Ned: 10000 | C9: The Village | D9: 3. Ire-Zim Clash (Home) | E9: Away(USA): 5000 (Lost) | G9: 1. Ali Abbas | H9: Club Tournament | I9: 1 | J9: =I9*2000 -> 2000 | K9: =I9*20 -> 20 | L9: =N11+N13+N15+N17+N19+N20+N21 -> 225000
A10: 4. Athulnath | B10: 3. Sayandeep (Chairman Argentina): 10k | C10: Pareed Storziwal Sports Arena | D10: 4. ODI WC Warmup 7 (Home) | E10: Away(Uganda): 5000 (Won) | H10: Test Series | I10: 1 | J10: =I10*4000 -> 4000 | K10: =I10*80 -> 80 | L10: Player | M10: Award | N10: Credits
A11: 5. Fakhar Abbas Bangash | B11: 4. Arsal (Chairman Nepal): 10k | C11: Level 2 Stadiums | D11: 5. Emerald & Stars Trophy (Home) | E11: Home (Australia): 6000 (Lost) | H11: Test Tournament | I11: 2 | J11: =I11*8000 -> 16000 | K11: =I11*80 -> 160 | L11: 1. Ali Abbas Bangash | M11: Man of the match (2000): 1 | N11: 4000
A12: 6. Huzaifa | B12: 5. Seru (Chairman Japan): 10k | C12: None | D12: 6. Irish-Caribbean Challenge (Home) | E12: Home(Zimbabwe): 5000 (Won) | H12: T10 Series | I12: 7 | J12: =I12*2000 -> 14000 | K12: =I12*40 -> 280 | M12: Best Bowler (1000): 2
A13: 7. Karthik Varma | C13: Level 1 Stadiums | D13: 7. Emerald - Dutch Trophy (Home) | E13: Away(Qatar): 5000 (Lost) | H13: Club Series | I13: 1 | J13: =I13*1000 -> 1000 | K13: =I13*20 -> 20 | L13: 2. Rahim Ullah | M13: Man of the match (2000): 2 | N13: 6000
A14: 8. Kranthi Smith | C14: None | D14: 8. RED & GREEN RIVALRY I (Home) | E14: Home(Pakistan): 5000 (Won) | F14: Whitewash lose: | H14: T20 Series | I14: 2 | J14: =I14*3000 -> 6000 | K14: =I14*40 -> 80 | M14: Best Bowler (1000): 2
A15: 9. Noufal | B15: Sponsors | E15: Home(USA): 5000 (Won) | F15: -500 | H15: Total Credits | J15: =J9+J10+J11+J12+J13+J14 -> 43000 | K15: =K9+K10+K11+K12+K13+K14 -> 640 | L15: 3. Noufal | M15: Best Batsman(1000): 1 | N15: 11000
A16: 10. Poorna Kavishka | B16: 100000 | E16: Home(Canada): 5000 (Lost) | F16: Against West Indies: 1 | M16: Highest Individual Score(10000)
A17: 11. Rahim Ullah | B17: 1. VYLAX Clothing (Clothing Sponsors) | E17: Home(West Indies): 5000 (Won) | L17: 4. Karthik Varma | M17: Man of the match (2000): 1 | N17: 3000
A18: 12. Sammar Rehman | E18: Home(Bangladesh): 5000 (Won) | M18: Best Batsman(1000): 1
A19: 13. Shahmeer Baloch | E19: Home(Spain): 5000 (Lost) | L19: 5. Akshay Dileep | M19: Best Batsman(1000): 1 | N19: 1000
A20: 14. Talal Choudhary | E20: Away(Netherlands): 5000 (Lost) | L20: Champions | N20: 150000
A21: 15. Zain Gujjar | E21: Home(West Indies): 5000 (Lost) | L21: ODI WC 2026 Fantasy League: 3rd Place | N21: 50000
A22: 16. Zain Ul Hassan | E22: Home(Canada): 5000 (Won)
A23: 17. Thulanja Teekshana | E23: Home(Canada): 5000 (Lost)
A24: 18. Siyad | E24: Away(PNG): 5000 (Lost)
A25: 19. Shifa Noor
A29: All Franchise League Credits Updates :
A30: =A32+A46 -> 233275
A31: Scottish Premier League
A32: =A35 -> 37000
A33: 2026
A34: All Team Profit:
A35: =A38+B38+C38+D38+E38+F38+G38+H38+I38+J38 -> 37000
A36: ABERDEEN TITANS | B36: DUNDEE WARRIORS | C36: EDINBURGH ROYALS | D36: GLASGOW GIANTS | E36: HIGHLAND HAWKS | F36: INVERNESS EAGLES | G36: LOTHIAN LIONS | H36: PERTH PANTHERS | I36: STIRLING KNIGHTS | J36: TARTAN STRIKERS
A37: Team Profit: | B37: Team Profit: | C37: Team Profit: | D37: Team Profit: | E37: Team Profit: | F37: Team Profit: | G37: Team Profit: | H37: Team Profit: | I37: Team Profit: | J37: Team Profit:
A38: 0 | B38: 0 | C38: 0 | D38: 0 | E38: =5000+32000 -> 37000 | F38: 0 | G38: 0 | H38: 0 | I38: 0 | J38: 0
E39: 1. Ali Abbas Bangash
E40: Traded (No Salary)
E41: Best Batsman: 1 (5000)
E42: Fair Play: 32000
A45: Qatar Elite Crown League :
A46: =A49 -> 196275
A47: 2026
A48: All Team Profit:
A49: =A52+B52+C52+D52+E52+F52+G52+H52 -> 196275
A50: AL KHOR PREDATORS | B50: AL RAYYAN RAIDERS | C50: AL WAKRAH DUKES | D50: DOHA STALLIONS | E50: LUSAIL KNIGHTS | F50: MESAEID BLAZE | G50: QATAR VENOMS | H50: UMM SALAL SPARTANS
A51: Team Profit: | B51: Team Profit: | C51: Team Profit: | D51: Team Profit: | E51: Team Profit: | F51: Team Profit: | G51: Team Profit: | H51: Team Profit:
A52: =35000+59825 -> 94825 | B52: =19000+(33725*2) -> 86450 | C52: 0 | D52: 15000 | E52: 0 | F52: 0 | G52: 0 | H52: 0
A53: 1. Ali Abbas Bangash | B53: 1. Sammar | D53: 1. Talal Choudary
A54: Salary: 30000 | B54: Salary: 17000 | D54: Salary: 15000
A55: Best Bowler: 1 (5000) | B55: Fair Play: 33725
A56: Runners Up: 59825 | B56: 2. Zain Gujjar
B57: Salary: 2000
B58: Fair Play: 33725

Sheet Italy
A1: Board: Italy
A2: Chairman: Rince Thomas | CEO: Akhil Viratian
A3: Credits left:
A4: =100000+B6+C6+D6+F6+I6+A51+J6+P6+M6 -> 1781475
A5: Players | B5: Stadium: | C5: Player trade: | D5: International Series: | E5: Trophy Cabinet ( International Series) | F5: IOCF WORLD TEST CHAMPIONSHIP 🏆: | I5: Player limit exceeded: -10000 | J5: CONTINENTAL CUP 2026 🏆: ( EURO ) | M5: Women's Global League 2026 🏆: | P5: ODI WORLD CUP 2026 🏆:
A6: 1. Aakash | B6: -60000 | C6: =-220000+-70000+-50000-50000-35000 -> -425000 | D6: 87000 | E6: 1. Romo Carribbean ( Home ) | F6: =F8+G8+H8 -> -18500 | I6: -10000 | J6: =J8 -> 233200 | M6: =M8 -> 120000 | P6: =P8 -> 849000
A7: 2. Abhishek | B7: Level 3 Stadiums | C7: Vipin Venu from Italy: -20000 | D7: Home ( West Indies ): 5000 bet ( Won ) | E7: 2. Zeus Trophy (Away) | F7: Player Awards | G7: Match Bet Credits | H7: Entry Credits | I7: 1. 20 to 25: 10000 | J7: Players & Match Awards | M7: Players & Match Awards | P7: Players & Match Awards
A8: 3. Afsal | B8: Vivian Richards Cricket Ground | C8: Subaida from England: 7000 | D8: Away (Srilanka): 6000 bet (Won) | E8: 3. Roman Crown (Away) | F8: =H22+H25+H28+H31+H34 -> 6500 | G8: -20000 | H8: -5000 | J8: =L10+L11+L16+L20+L22 -> 233200 | M8: =O10+O11 -> 120000 | P8: =R10+R13+R17+R19+R22+R23+R24+R27+R28 -> 849000
A9: 4. Albin | B9: Ovale di Carteria | C9: Vishnu from England: 3000 | D9: Away (England): 5000 bet (Won) | E9: 4. Hayley Matthews Cup (Away) | G9: Home (Scotland): 5000 bet (Lost) | H9: Trophy Cabinet (Test) | J9: Player | K9: Award | L9: Credits | M9: Player | N9: Award | O9: Credits | P9: Player | Q9: Award | R9: Credits
A10: 5. Anandhu Reddy | B10: Level 2 Stadiums | C10: Vignesh from WI: 200000 | D10: Away(West Indies): 7000 bet (Won) | E10: 5. Onakkali (Away) | G10: Away (Italy): 5000 bet (Lost) | H10: 1. Unity Nations Trophy (Away) | J10: 1. Akshay | K10: Best Batsman(1000): 1 | L10: 1000 | M10: Best Women Talent Discovery Board | O10: 20000 | P10: 1. Lal Krishna | Q10: Best Batsman(3000): 1 | R10: 7000
A11: 6. Appu | B11: None | C11: Haseeb to Uganda: 10000 | D11: Away(West Indies): 10000 bet (Won) | E11: 6. ODI WC Warmup 4 (Home) | G11: Away (Afghanistan): 5000 bet (Lost) | H11: 2. The Clash of Blues (Away) | J11: 2. Subaida Subi | K11: Man of the match(2000): 3 | L11: =60000+5400 -> 65400 | M11: Runners UP | O11: 100000 | Q11: Best Bowler(3000): 1
A12: 7. Arathy | B12: Level 1 Stadiums | C12: Jinson from USA: 70000 | D12: Home(Bangladesh): 5000 bet (Won) | E12: 7. Royal Trinity Cup (Away) | G12: Away (Scotland): 5000 bet (Lost) | H12: 3. Bengal-Italia Test (Away) | K12: Best Batsman(1000): 3 | Q12: Most Dot Balls(1000): 1
A13: 8. Aravind | B13: None | C13: Lal from Aus: 50000 | D13: Home(Nepal): 3000 bet (Lost) | E13: 8. THE THUNDER CROWN (Away) | G13: Away (South Africa): 5000 bet (Won) | K13: Best Bowler(1000): 1 | P13: 2. Shuhaib | Q13: Man of the match(5000): 1 | R13: 309000
A14: 9. Arjun | C14: Josin from WI: 50000 | D14: Away(England & Newzealand): 10000 (Won) | E14: 9. The Golden Horizon Cup (Home) | G14: Home(Newzealand): 5000 bet (Lost) | K14: Player of the Tournament(50000) | Q14: Best Bowler(3000): 1
A15: 10. Ashik | C15: Firoze from Nepal: 35000 | D15: Away(Zimbabwe): 5000 (Lost) | E15: 10. The Sun & Olive Cup | G15: Away(India): 10000 bet (Won) | K15: Team of the tournament - 5400 | Q15: Most Sixes(1000): 1
A16: 11. Chinju | D16: Away(Newzealand): 7000 (Won) | G16: Away(Newzealand): 10000 bet (Lost) | J16: 3. Huzain | K16: Man of the match(2000): 1 | L16: =5000+5400 -> 10400 | Q16: Fastest 50: 300000
A17: 12. Firoz | D17: Home(West Indies): 7000 (Won) | G17: Away(Bangladesh): 10000 (Won) | K17: Best Batsman(1000): 2 | P17: 3. Subaida Subi | Q17: Best Bowler(3000): 2 | R17: 8000
A18: 13. Greeshma | D18: Home(Spain): 3000 (Won) | G18: Home(India): 10000 (Lost) | K18: Best Bowler(1000): 1 | Q18: Most Dot Balls(1000): 2
A19: 14. Greeshma | K19: Team of the tournament - 5400 | P19: 4. Shajahan | Q19: Man of the match(5000): 1 | R19: 9000
A20: 15. Huzain | F20: Players Awards & Credits | J20: 4. Rince Thomas | K20: Best Bowler(1000): 1 | L20: =1000+5400 -> 6400 | Q20: Best Batsman(3000): 1
A21: 16. Hybi | F21: Player | G21: Award | H21: Credits | K21: Team of the tournament - 5400 | Q21: Most Sixes(1000): 1
A22: 17. Jessy | F22: 1. Rince Thomas | G22: Man of the Match: 1 (1000) | H22: 2000 | J22: Runners-UP | L22: 150000 | P22: 5. Greeshma | Q22: Best Batsman(3000): 1 | R22: 3000
A23: 18. Jishan | G23: Best Batsman: 0 (500) | P23: 6. Hybi Anil | Q23: Best Bowler(3000): 1 | R23: 3000
A24: 19. Jinson | G24: Best Bowler: 2 (500) | P24: 7. Vignesh | Q24: Man of the match(5000): 1 | R24: 9000
A25: 20. Josin | F25: 2. Shuhaib | G25: Man of the Match: 0 (1000) | H25: 500 | Q25: Best Batsman(3000): 1
A26: 21. Krishadev | G26: Best Batsman: 0 (500) | Q26: Most Sixes(1000): 1
A27: 22. Lal Krishna | G27: Best Bowler: 1 (500) | P27: 8. Rince Thomas | Q27: Most Dot Balls(1000): 1 | R27: 1000
A28: 23. Manju | F28: 3. Muhammed Ali | G28: Man of the Match: 1 (1000) | H28: 1500 | P28: Quarterfinalists | R28: 500000
A29: 24. Mohammad Ali | G29: Best Batsman: 0 (500)
A30: 25. Nisa Navas | G30: Best Bowler: 1 (500)
A31: 26. Nobin | F31: 4. Subaida Subi | G31: Man of the Match: 1 (1000) | H31: 2000
A32: 27. Renjini | G32: Best Batsman: 1 (500)
A33: 28. Sanasil | G33: Best Bowler: 1 (500)
A34: 29. Shijo | F34: 5. Rejini | G34: Man of the Match: 0 (1000) | H34: 500
A35: 30. Shuhaib | G35: Best Batsman: 1 (500)
A36: 31. Sreesankar | G36: Best Bowler: 0 (500)
A37: 32. Subi
A38: 33. Sumesh
A39: 34. Thaneem
A40: 35. Thoufee
A41: 36. Tom
A42: 37. Ubai Nisa
A43: 38. Vignesh
A44: 39. Vipin Sai
A45: 40. Vishnu C V
A46: 41. Vishnu Vijay
A50: All Franchise League Credits Updates :
A51: =A63+A78+A94+A111+A136+A182 -> 905775
A52: THE HUNDRED : 000
A53: 2026
A54: London Spirit | B54: Southern Brave | C54: Welsh Fire | D54: MI London | E54: Sunrisers Leeds
A55: No Players Sold
A57: Pakistan Super League : 000
A58: 2026
A59: LAHORE QALANDARS | B59: PINDIZ | C59: MULTAN SULTANS | D59: KARACHI KINGS | E59: QUETTA GLADIATORS | F59: HYDERABAD KINGSMEN
A60: No Players Sold
A62: Big Bash League :
A63: 19100
A64: 2026
A65: All Team Profit: 19100
A66: Adelaide Strikers | B66: Brisbane Heat | C66: Hobart Hurricanes | D66: Melbourne Renegades | E66: Melbourne Stars | F66: Perth Scorchers | G66: Sydney Sixers | H66: Sydney Thunders
A67: Team Profit: | B67: Team Profit: 6600 | C67: Team Profit: 500 | D67: Team Profit: 1000 | E67: Team Profit: | F67: Team Profit: 9500 | G67: Team Profit: | H67: Team Profit: 1500
B68: 1. Hybi Anil | C68: 1. Akhil Mohan | D68: 1. Vishnu CV | F68: 1. Subaida | H68: 1. Huzain
B69: Salary: 500 | C69: Salary: 500 | D69: Salary: 500 | F69: Salary: 7000 | H69: Salary: 500
B70: Man of the match: 2 (2000) | D70: 2. Rince | F70: Man of the Match: 2 (2000) | H70: 2. Sanazil
B71: Best Bowler: 2 (1000) | D71: Salary: 500 | F71: Best Bowler: 1 ( 500 ) | H71: Salary: 500
B72: Fair Play Award: 3100 | H72: 3. Vishnu Vijay
H73: Salary: 500
A77: Kiwi Crown League :
A78: =A81 -> 113850
A79: 2026
A80: All Team Profit:
A81: =A84+B84+C84+D84+E84+F84+G84+H84 -> 113850
A82: Wellington Warriors | B82: Auckland Aces | C82: Canterbury Kings | D82: Otago Volts | E82: Northern Knights | F82: Central Stags | G82: Queenstown Royals | H82: Tauranga Titans
A83: Team Profit: | B83: Team Profit: | C83: Team Profit: | D83: Team Profit: | E83: Team Profit: | F83: Team Profit: | G83: Team Profit: | H83: Team Profit:
A84: 12000 | B84: 0 | C84: 0 | D84: 0 | E84: 83400 | F84: 0 | G84: 1500 | H84: 16950
A85: 1. Subaida Subi | E85: 1. Vishnu Vijay | G85: 1. Sanazil | H85: 1. Hybi Anil
A86: Salary: 12000 | E86: Salary: 500 | G86: Salary: 500 | H86: Salary: 7000
E87: Man of the match: 1 (1500) | G87: 2. Rince Thomas | H87: Runners Up: 9950
E88: Best Batsman: 2 (1500) | G88: Salary: 1000
E89: Most Sixes: 20000
E90: Best Batsman of the tournament: 40000
E91: Champions: 19900
A93: Bangladesh Premier League :
A94: =A97 -> 50900
A95: 2026
A96: All Team Profit:
A97: =A100+B100+C100+D100+E100+F100+G100+H100+I100+J100 -> 50900
A98: BARISAL RIVER RIDERS | B98: CHANDPUR ILLISH TITANS | C98: SYLHET EMERALD BLADES | D98: RAJSHAHI MANGO LEGION | E98: DHAKA BURIGANGA BLAZERS | F98: CHITTAGONG MARINERS | G98: MAINAMATI TITANS | H98: SONARGAON ROYALS | I98: MYMENSINGH MAVERICKS | J98: CUMILA FALCONS
A99: Team Profit: | B99: Team Profit: | C99: Team Profit: | D99: Team Profit: | E99: Team Profit: | F99: Team Profit: | G99: Team Profit: | H99: Team Profit: | I99: Team Profit: | J99: Team Profit:
A100: 12200 | B100: 900 | C100: 1100 | D100: 1500 | E100: 0 | F100: 1100 | G100: 0 | H100: 27000 | I100: 1000 | J100: 6100
A101: 1. Vishnu Vijay | B101: 1. Vishnu CV | C101: 1. Haseeb | D101: 1. Akhil | F101: 1. Shubaib | H101: 1. Subaida | I101: 1. Thaneem | J101: 1. Rince
A102: Salary: 10000 | B102: Salary: 900 | C102: Salary: 1100 | D102: Salary: 700 | F102: Salary: 600 | H102: Salary: 27000 | I102: Salary: 1000 | J102: Salary: 500
A103: Best Batsman: 1 (1000) | D103: 2. Hybi Anil | F103: 2. Huzain | J103: 2. Sanzail
A104: 2. Vipin | D104: Salary: 800 | F104: Salary: 500 | J104: Salary: 500
A105: Salary: 1200 | J105: 3. Afsal
J106: Salary: 600
J107: 4. Albin
J108: Salary: 4500
A109: Tournament Cancelled
...

Sheet Japan
A1: Board: Japan
A2: Chairman: Seru Yuvi | CEO: Churami
A3: Credits left:
A4: =100000+B6+C6+D6+F6+F11+G6 -> 81500
A5: Players | B5: Player trade | C5: Stadium: | D5: International Series: | E5: Trophy Cabinet ( International series) | F5: Whitewash Win: | G5: Umpires Credits :
A6: 1. Ahmed Mahsoof | B6: -5000 | C6: -30000 | D6: 9000 | E6: 1. The Ultimate Arena Cup (Away) | F6: 1000 | G6: =J10 -> 7000
A7: 2. Vipin Kuttu | B7: 1. Ahmed from Ind: Free | C7: Level 3 Stadiums | D7: 1. Away(Netherlands): 3000 (Lost) | E7: 2. Samurai Falcons Cup (Away) | F7: 1. The Gaucho-Samurai Trophy(Away) | G7: Umpire | H7: Details | I7: Total Matches | J7: Credits | K7: Points
A8: 3. Athul | B8: 2. Athul from Scot: Free | C8: Sano International Cricket Stadium | D8: 2. Away(Netherlands): 3000 (Won) | E8: 3. The Gaucho-Samurai Trophy (Away) | G8: 1. Akshay | H8: T10 Series | I8: 2 | J8: =I8*2000 -> 4000 | K8: =I8*40 -> 80
A9: 4. Akshay | B9: 3. Akshay from Italy: Free | C9: Level 2 Stadiums | D9: 3. Away(UAE): 5000 (Won) | E9: 4. The Mount Fuji & Mount Kenya Cup (Home) | H9: T20 Series | I9: 1 | J9: =I9*3000 -> 3000 | K9: =I9*40 -> 40
A10: 5. Arun Ozil | B10: 4. Arun from Italy: Free | C10: None | D10: 4. Home(Japan): 5000 (Won) | E10: 5. The Sakura & Shujaa Trophy (Home) | F10: Whitewash loss: | H10: Total Credits | J10: =J8+J9 -> 7000 | K10: =K8+K9 -> 120
A11: 6. Nahas | B11: 5. Zuhair from Scot: 5k | C11: Level 1 Stadiums | D11: 5. Away(Argentina): 5000 (Won) | F11: -500
A12: 7. Murshid | C12: None | D12: 6. Home(Kenya): 3000 (Won) | F12: 1. Crimson Samurai Clash (Home)
A13: 8. Machan | D13: 7. Home(Kenya): 3000 (Won)
A14: 9. Hanan | D14: 8. Away(Spain): 5000 (Lost)
A15: 10. Mahi
A16: 11. Nihal
A17: 12. Sreelal
A18: 13. Abhi Gulan
A19: 14. Mujeeb
A20: 15. Deepesh
A21: 16. Payeez
A22: 17. Sarath
A23: 18. Anas
A24: 19. Hafsal
A25: 20. Zuhair
A26: 21. Shareef
... A35: 30. Ajeeb

Sheet Kenya
A1: Board: KENYA
A2: Chairman: Yohaan Daruwalla | CEO: Zayn Bhuyan
A3: Credits left:
A4: =100000+B6+D6 -> 127000
A5: Players | B5: Player trade | C5: Stadium: | D5: International Series: | E5: Trophy Cabinet ( International series)
A6: 1. Anas Khan | B6: 20000 | D6: 7000 | E6: 1. Copa Del Umoja (Away)
A7: 2. Ankit Saxena | B7: 1. Shubham to BD: 15K | D7: 1. Away(Argentina): 3000 bet (Won) | E7: 2. APEX TRINITY SERIES (Away)
A8: 3. Shafique Ahmed | B8: 2. Fraz Ali to Spain: 5k | D8: 2. Away(Spain & Canada): 5000 bet (Won)
A9: 4. Huzaifa | D9: 3. Away(Japan): 3000 bet (Lost)
A10: 5. Khair Mohammed | D10: 4. Away(Japan): 3000 bet (Lost)
A11: 6. Malik Ahmed
A12: 7. Mohd Asif
A13: 8. Mohd Waseem
A14: 9. Rehan Ali
A15: 10. Samiullah Shar
A16: 11. Abdullah
A17: 12. Sooraj Sial
A18: 13. Suraj Shah

Sheet Nepal
A1: Board: NEPAL
A2: Chairman: Arsal Chaudry| CEO: Abhay Brucelee
A3: TITLE SPONSORS: CRICKET HOLIC
A4: Credits left:
A5: =100000+B7+B18+C7+D7+F7 -> 164000
A6: Players | B6: Player trade: | C6: Stadium: | D6: International Series: | E6: Trophy Cabinet ( International Series) | F6: Umpires Credits :
A7: 1. Abdullah Jutt | B7: =35000-15000 -> 20000 | C7: -60000 | D7: 3000 | E7: 1. Everest–Pacific Cup | F7: =I10+I12 -> 1000
A8: 2. Abhinav Sham | B8: 1. Krathik from ZIM: 5000 | C8: Level 3 Stadiums | D8: 1. Home(PNG): 3000 (Won) | E8: 2. Italia vs Himalaya | F8: Umpire | G8: Details | H8: Total Matches | I8: Credits | J8: Points
A9: 3. Ajmal Khan | B9: 2. Muneef from ZIM: 5000 | C9: Thribhuvan University ICS | D9: 2. Away(Italy): 3000 (Won) | F9: 1. Arsal Chaudry | G9: Club Series | H9: 1 | I9: =H9*1000 -> 1000 | J9: =H9*20 -> 20
A10: 4. Christy Royson | B10: 3. Kashif from ZIM: 5000 | C10: Gautam Buddha ICS | D10: 3. Home(Netherlands): 3000 (Lost) | G10: Total Credits | I10: =I9 -> 1000 | J10: =J9 -> 20
A11: 5. Emil Bentoo | B11: 4. Firoze to Italy: 35000 | D11: 4. Home(Portugal & England): 3000 (Lost)
A12: 6. Zubair Ahmed
A13: 7. Kashif Ramzan
A14: 8. Kashif Ramzan
A15: 9. Krathik Mogaveera
A16: 10. Mohammed Fadil
A17: 11. Muneef | B17: Sponsors
A18: 12. Nandita | B18: 100000
A19: 13. Ridhwan | B19: 1. Cricket Holic (Title Sponsors)
A20: 14. Shahabaz KS
A21: 15. Shaila
A22: 16. Thushara
A23: 17. Visakh

Sheet Netherlands
A1: Board: Netherlands
A2: Chairman: Debajit Borthakur | CEO: Nirmal
A3: Credits left:
A4: =100000+B6+C6+D6+E6+G6+H6+A41+K6+Q6+N6 -> 1087315
A5: Players | B5: Stadium: | C5: Player trade: | D5: International Series: | E5: Whitewash lose: | F5: Trophy Cabinet ( International Series) | G5: Player limit increased: -10000 | H5: IOCF WORLD TEST CHAMPIONSHIP 🏆: | K5: CONTINENTAL CUP 2026 🏆: ( EURO ) | N5: ODI WORLD CUP 2026 🏆: | Q5: Umpires Credits :
A6: 1. Ali Akbor Ahmed | B6: -150000 | C6: 36000 | D6: -47500 | E6: -500 | F6: 1. Atlantic Smash ( Home ) | G6: -20000 | H6: =H8+I8+J8 -> 9000 | K6: =K8 -> 39200 | N6: =N8 -> 432000 | Q6: =T19+T22+T25+T27 -> 149250
A7: 2. Anamika | B7: Level 3 Stadiums | C7: 1. Hirak From Eng: 5000 | D7: Home ( Afghanistan) : 5000 ( Lost ) | E7: 1. Dutch Carribbean ( Home ) | F7: 2. Zubeen Garg Rhine ODI (Home) | G7: 1. 20 to 25: 10000 | H7: Player Awards | I7: Match Bet Credits | J7: Entry Credits | K7: Players & Match Awards | N7: Players & Match Awards | Q7: Umpire | R7: Details | S7: Total Matches | T7: Credits | U7: Points
A8: 3. Biki | B8: Maya Stadium Amsterdam | C8: 2. Ashutoh from Eng: 5000 | D8: Home ( UAE ): 5000 bet ( Lost ) | F8: 3. Dutch Caribbean 2 ODI (Home) | G8: 2. 26 to 30: 10000 | H8: =J23+J26+J29+J32+J35+J38+J41+J44+J47+J50+J53 -> 14000 | I8: 0 | J8: -5000 | K8: =0+M10+M11+M14+M16+M17 -> 39200 | N8: =P10+P12+P14+P15+P17+P20 -> 432000 | Q8: 1. Debajit | R8: Club Series | S8: 32.5 | T8: =S8*1000 -> 32500 | U8: =S8*20 -> 650
A9: 4. Bikram Saikia | B9: Dutch Cricket Arena Hague | C9: 3. Aashutosh to Ban: 15000 | D9: Home ( Newzealand ): 5000 bet ( Lost ) | F9: 4. European Beaver-Hedgehog Trophy (Home) | I9: Home(India): 2500 bet (Lost) | J9: Trophy Cabinet (Test) | K9: Player | L9: Award | M9: Credits | N9: Player | O9: Award | P9: Credits | R9: T10 Series | S9: 2.5 | T9: =S9*2000 -> 5000 | U9: =S9*40 -> 100
A10: 5. Bimal Baral | B10: Zubeen Garg Heritage Stadium | C10: 4. Veer to Qatar: 10000 | D10: Home ( West Indies ): 5000 bet ( Lost ) | F10: 5. ODI WC Warmup 2 (Home) | I10: Away (India): 2500 bet (Won) | J10: 1. Zubeen Gard Rhine B | K10: 1. Bimal Baral | L10: Best Batsman(1000): 2 | M10: 2000 | N10: 1. Nirmal | O10: Man of the match(5000): 1 | P10: 6000 | R10: T20 Series | S10: 11.5 | T10: =S10*3000 -> 34500 | U10: =S10*40 -> 460
A11: 6. Biswajit Dutta | B11: Pragjyotish Ground | C11: 5. Ritik to Ban: 1000 | D11: Home ( USA ): 5000 bet ( Won ) | F11: 6. The Dutch–Nippon Heritage Cup (Home) | I11: Home (Srilanka): 5000 bet (Lost) | J11: 2. Northern Heritage | K11: 2. Nirmal Baishya | L11: Man of the match(2000): 1 | M11: =3000+5400 -> 8400 | O11: Most Sixes(1000): 1 | R11: ODI Series | S11: 1 | T11: =S11*5000 -> 5000 | U11: =S11*100 -> 100
A12: 7. Bitupan | B12: Nilachal Khel Pathar | C12: 6. Kartik to Zim: 5000 | D12: Home ( Scotland ): 5000 bet ( Lost ) | F12: 7. Dutch - Himalayan Trophy (Away) | I12: Home(Scotland): 3000 bet (Won) | J12: 3. Tulip Desert | L12: Best Bowler(1000): 1 | N12: 2. Dipankar | O12: Best Batsman(3000): 3 | P12: 209000 | R12: Club Tournament | S12: 4 | T12: =S12*2000 -> 8000 | U12: =S12*20 -> 80
A13: 8. Deepak Das | B13: Level 2 Stadiums | C13: 7. Dhurbo to Zim: 5000 | D13: Home ( Pakistan ): 3000 bet ( Lost ) | F13: 8. Millstone-Jamieson Gold Trophy (Home) | I13: Home(Bangladesh): 4000 bet (Won) | J13: 4. Yellow - Orange Trophy | L13: Team of the tournament - 5400 | O13: Highest Batting Average: 200000 | R13: T20 Tournament | S13: 2 | T13: =S13*6000 -> 12000 | U13: =S13*40 -> 80
A14: 9. Deepjyoti | B14: None | C14: 8. Biswajit to Ireland: 20000 | D14: Home (England): 5000 bet (Lost) | I14: Away(Qatar): 5000 bet (Lost) | J14: 5. Lowlands–Lions Test | K14: 3. Pinku | L14: Best Bowler(1000): 2 | M14: =2000+5400 -> 7400 | N14: 3. Biki | O14: Best Bowler(3000): 1 | P14: 3000 | R14: Test Tournament | S14: 4 | T14: =S14*8000 -> 32000 | U14: =S14*80 -> 320
A15: 10. Devasish | B15: Level 1 Stadiums | D15: Home (India): 2000 bet (Won) | I15: Home (Qatar): 5000 bet (Won) | J15: 6. Dutch–Caribbean Test | L15: Team of the tournament - 5400 | N15: 4. Marami Ahmed | O15: Best Bowler(3000): 1 | P15: 5000 | R15: ODI Tournament | S15: 1 | T15: =S15*8000 -> 8000 | U15: =S15*80 -> 80
A16: 11. Dipankar | B16: None | D16: Away (Afghanistan): 4000 bet (Lost) | I16: Away (Australia): 5000 bet (Won) | K16: 4. Rahul Sharma | L16: Best Batsman(1000): 1 | M16: 1000 | O16: Most Dot Balls(1000): 2 | R16: Franchise League
A17: 12. Hirak | D17: Home (West Indies): 4000 bet (Won) | I17: Home(Australia): 5000 bet (Lost) | K17: 5. Jihan | L17: Emerging Player Award | M17: =15000+5400 -> 20400 | N17: 5. Debajit | O17: Man of the match(5000): 1 | P17: 9000 | R17: 100 | S17: 1.5 | T17: =S17*1500 -> 2250 | U17: =S17*40 -> 60
A18: 13. Hrishikesh Barman | D18: Home (Bangladesh): 4000 bet (Lost) | I18: Away(Pakistan): 5000 bet (Lost) | L18: Team of the tournament - 5400 | O18: Best Batsman(3000): 1 | R18: KCL | S18: 1 | T18: =S18*1500 -> 1500 | U18: =S18*40 -> 40
A19: 14. Jack Dipu | D19: Home (England): 4000 bet (Lost) | I19: Home(England): 10000 (Won) | O19: Most Sixes(1000): 1 | R19: Total Credits | T19: =T8+T9+T10+T11+T12+T13+T14+T17+T18+T15 -> 140750 | U19: =U8+U9+U10+U11+U12+U13+U14+U17+U18+U15 -> 1970
A20: 15. Jahirul | D20: Away(West Indies): 5000 bet (Lost) | I20: Home(West Indies): 10000 (Won) | N20: Group Stage Exit | P20: 200000 | Q20: 2. Nirmal | R20: Franchise League
A21: 16. Jihan | D21: Home (England): 5000 bet (Won) | H21: Players Awards & Credits | R21: PSL ( Commentory ) | S21: 1 | T21: =S21*1500 -> 1500 | U21: =S21*40 -> 40
A22: 17. Khagen Saikia | D22: Away(Bangladesh/West Indies): 15000 (Lost) | H22: Player | I22: Award | J22: Credits | R22: Total Credits | T22: =T21 -> 1500 | U22: =U21 -> 40
A23: 18. Kiran | D23: Away(Australia): 10000 (Lost) | H23: 1. Marami Ahmed | I23: Man of the Match: 0 (1000) | J23: 500 | Q23: 3. Jahirul | R23: Club Tournament | S23: 1 | T23: =S23*2000 -> 2000 | U23: =S23*20 -> 20
A24: 19. Kritartha Kalita | D24: Away(Bangladesh): 7000 (Lost) | I24: Best Batsman: 0 (500) | R24: T20 Series | S24: 1 | T24: =S24*3000 -> 3000 | U24: =S24*40 -> 40
A25: 20. Manuranjan Deka | D25: Home(West Indies): 5000 (Won) | I25: Best Bowler: 1 (500) | R25: Total Credits | T25: =T23+T24 -> 5000 | U25: =U23+U24 -> 60
A26: 21. Marami | D26: Away(West Indies): 10000 bet (Lost) | H26: 2. Nirmal | I26: Man of the Match: 1 (1000) | J26: 1500 | Q26: 4. Bimal Baral | R26: T10 Series | S26: 1 | T26: =S26*2000 -> 2000 | U26: =S26*40 -> 40
A27: 22. Mayank | D27: Home(West Indies): 5000 (Lost) | I27: Best Batsman: 0 (500) | R27: Total Credits | T27: =T26 -> 2000 | U27: =U26 -> 40
A28: 23. Niyor J Kashyap | D28: Away(USA): 5000 (Lost) | I28: Best Bowler: 1 (500)
A29: 24. Pinku | D29: Home(Bangladesh): 5000 (Lost) | H29: 3. Rahul Sharma | I29: Man of the Match: 0 (1000) | J29: 500
A30: 25. Prabal | D30: Home(PNG,Canada & West Indies): 7500 (Lost) | I30: Best Batsman: 1 (500)
A31: 26. Prince Gogoi | D31: Home(Japan): 3000 (Won) | I31: Best Bowler: 0 (500)
A32: 27. Rahul | D32: Home(Japan): 3000 (Lost) | H32: 4. Hirak | I32: Man of the Match: 0 (1000) | J32: 1500
A33: 28. Rishi Raj | D33: Away(Nepal): 3000 (Won) | I33: Best Batsman: 3 (500)
A34: 29. Sagar | D34: Home(Ireland): 5000 (Won) | I34: Best Bowler: 0 (500)
A35: 30. Shabir Alam | H35: 5. Debajit | I35: Man of the Match: 2 (1000) | J35: 3000
A36: 31. Shon | I36: Best Batsman: 1 (500)
A37: 32. Surashri C | I37: Best Bowler: 1 (500)
H38: 6. Devasish | I38: Man of the Match: 3 (1000) | J38: 4000
I39: Best Batsman: 0 (500)
A40: All Franchise League Credits Updates : | I40: Best Bowler: 2 (500)
A41: =A43+A62+A89+A106+A125+A147+A179 -> 539865 | H41: 7. Bimal | I41: Man of the Match: 0 (1000) | J41: 1000
A42: THE HUNDRED : | I42: Best Batsman: 2 (500)
A43: 30650 | I43: Best Bowler: 0 (500)
A44: 2026 | H44: 8. Rishiraj | I44: Man of the Match: 0 (1000) | J44: 500
A45: London Spirit | B45: Southern Brave | C45: Welsh Fire | D45: MI London | E45: Sunrisers Leeds | I45: Best Batsman: 1 (500)
A46: Team Profit: 4500 | C46: Team Profit: 1500 | E46: Team Profit: 24650 | I46: Best Bowler: 0 (500)
A47: 1. Mayank Das ( Replacement ) | C47: 1. Hirak Jyothi | E47: 1. Nirmal Baishya | H47: 9. Dipankar | I47: Man of the Match: 0 (1000) | J47: 500
A48: Salary: 4000 | C48: Salary: 1500 | E48: Salary: 2000 | I48: Best Batsman: 0 (500)
A49: Man of the match: 1 ( 500 ) | E49: Best Bowler: 1 ( 200 ) | I49: Best Bowler: 1 (500)
E50: Best Batsman of the Tournament: 10000 | H50: 10. Jahirul | I50: Man of the Match: 0 (1000) | J50: 500
E51: Runners up: 2850 | I51: Best Batsman: 0 (500)
E52: 2. Marami Ahmed | I52: Best Bowler: 1 (500)
E53: Salary: 1700 | H53: 11. Dipak Das | I53: Man of the Match: 0 (1000) | J53: 500
E54: Man of the match: 1 ( 500 ) | I54: Best Batsman: 1 (500)
E55: Runners up: 2850 | I55: Best Bowler: 0 (500)
E56: 3. Debajit Borthakur
E57: Salary: 1500
E58: Best Batsman: 1 ( 200 )
E59: Runners up: 2850
A61: Pakistan Super League :
A62: 37690
A63: 2026
A64: LAHORE QALANDARS | B64: PINDIZ | C64: MULTAN SULTANS | D64: KARACHI KINGS | E64: QUETTA GLADIATORS | F64: HYDERABAD KINGSMEN
A65: Team Profit: 30860 | C65: Team Profit: 1000 | D65: Team Profit: 2150 | F65: Team Profit: 3680
A66: 1. Marami Ahmed | C66: 1. Biswajit Dutta | D66: 1. Nirmal | F66: 1. Rahul Sharma
A67: Salary: 6000 | C67: Salary: 1000 | D67: Salary: 1950 | F67: Salary: 1000
A68: Champions: 4990 | D68: Best Bowler: 1 (200) | F68: Best Batsman: 1 ( 200 )
A69: 2. Debajit | F69: Runners up: 2480
A70: Salary: 3900
A71: Champions: 4990
A72: 3. Kiran Nath
A73: Salary: 500
A74: Champions: 4990
A75: 4. Hirak
A76: Salary: 500
A77: Champions: 4990
A79: Big Bash League : 0
A80: 2026
A81: All Team Profit: 0
A82: Adelaide Strikers | B82: Brisbane Heat | C82: Hobart Hurricanes | D82: Melbourne Renegades | E82: Melbourne Stars | F82: Perth Scorchers | G82: Sydney Sixers | H82: Sydney Thunders
A83: Team Profit: | B83: Team Profit: | C83: Team Profit: | D83: Team Profit: | E83: Team Profit: | F83: Team Profit: | G83: Team Profit: | H83: Team Profit:
A88: Kiwi Crown League :
A89: =A92 -> 27500
A90: 2026
A91: All Team Profit:
A92: =A95+B95+C95+D95+E95+F95+G95+H95 -> 27500
A93: Wellington Warriors | B93: Auckland Aces | C93: Canterbury Kings | D93: Otago Volts | E93: Northern Knights | F93: Central Stags | G93: Queenstown Royals | H93: Tauranga Titans
A94: Team Profit: | B94: Team Profit: | C94: Team Profit: | D94: Team Profit: | E94: Team Profit: | F94: Team Profit: | G94: Team Profit: | H94: Team Profit:
A95: 9500 | B95: 0 | C95: 0 | D95: 0 | E95: 0 | F95: 0 | G95: 8250 | H95: 9750
A96: 1. Marami Ahmed | G96: 1. Nirmal Baishya | H96: 1. Aashutosh Jha
A97: Salary: 7000 | G97: Salary: 3500 | H97: Salary: 9000
A98: Man of the match: 1 (1500) | G98: 2. Debajit | H98: Best Batsman: 1 (750)
A99: 2. Hirakjyothi | G99: Salary: 3000
A100: Salary: 1000 | G100: Best Batsman: 1 (750)
G101: 3. Mayank Das
G102: Salary: 1000
A105: Bangladesh Premier League :
A106: =A109 -> 55900
A107: 2026
A108: All Team Profit:
...

Sheet Newzealand
A1: Board: Newzealand
A2: Chairman: Srajan Poojari | CEO: Gautam Shankara Ram
A3: Credits left:
A4: TITLE SPONSORS: CricTV Edits
A5: =100000+B7+C7+E7+E12+F7+G7+H7+A51+B23+K7+M7+S7+P7+E17 -> 4298385
A6: Players | B6: Stadium: | C6: International Series: | D6: Trophy Cabinet ( International series) | E6: Whitewash: | F6: IOCF T20 WORLD CUP 🏆 : | G6: Player limit increased: | H6: IOCF WORLD TEST CHAMPIONSHIP 🏆: | K6: EMERGING TALENTS LEAGUE: | M6: CONTINENTAL CUP 2026 🏆: ( OCEANIA ) | P6: ODI WORLD CUP 2026 🏆: | S6: Umpires Credits :
A7: 1. Abu Shazan | B7: -160000 | C7: 70000 | D7: 1. Crowe Nabi ( Home ) | E7: 1000 | F7: 14200 | G7: -20000 | H7: =H9+I9+J9 -> 53500 | K7: 5000 | M7: =-100000+O10+O13+O17+O20+O25+O26+O22+O27+O24 -> 249600 | P7: =P9 -> 218000 | S7: =V14+V23+V33+V36+V38 -> 244250
A8: 2. Adarsh | B8: Level 3 Stadiums | C8: Home( Afghanistan ): 3000 bet ( Won ) | D8: 2. Silk Steel ( Home ) | E8: 1. Silk Steel ( Pakistan ) | F8: Entry: -5000 | G8: 1. 20 to 25: 10000 | H8: Player Awards | I8: Match Bet Credits | J8: Entry Credits | K8: Tournament Awards: | L8: Award Winners | M8: Hosting Amount: 100k | P8: Players & Match Awards | S8: Umpire | T8: Details | U8: Total Matches | V8: Credits | W8: Points
A9: 3. Aniket Gavit | B9: Eden Park | C9: Home( Pakistan ): 3000 bet ( Won ) | D9: 3. Fleming Lara ( Home ) | E9: 2. Trans Tasman( Australia) | F9: Players Awards: 4200 | G9: 2. 25 to 30: 10000 | H9: =J27+J30+J33+J36+J39+J42+J45+J48+J51+J54 -> 16500 | I9: 42000 | J9: -5000 | K9: Best Talent Discovery Board: | L9: Newzealand (5000) | M9: Player | N9: Award | O9: Credits | P9: =R11+R12+R14+R15+R17 -> 218000 | S9: 1. Srajan Poojari | T9: Club Series | U9: 10 | V9: =U9*1000 -> 10000 | W9: =U9*20 -> 200
A10: 4. Ashutosh Sha | B10: Sky International Stadium | C10: Home( West Indies): 5000 bet ( Won ) | D10: 4. Trans Tasman ( Away ) | E10: 3. THE OCEANIC SHOWDOWN (Home) | F10: 1. Ram | I10: Home (Scotland): 5000 (Lost ) | J10: Trophy Cabinet (Test) | M10: 1. Aniket Gavit | N10: Man of the match(2000): 2 | O10: =6000+5400 -> 11400 | P10: Player | Q10: Award | R10: Credits | T10: T20 Series | U10: 4 | V10: =U10*3000 -> 12000 | W10: =U10*40 -> 160
A11: 5. Ashwini | B11: Sovereign Crown Arena | C11: Away( Australia): 5000 bet ( Won ) | D11: 5. Orange Black ( Away ) | E11: Whitewash loss: | F11: Man of the match: 2 | I11: Away (Scotland): 5000 bet (Lost) | J11: 1. Soverign Crown | N11: Best Bowler(1000): 2 | P11: 1. Toby Joseph | Q11: Man of the match(5000): 1 | R11: 5000 | T11: ODI Series | U11: 1 | V11: =U11*5000 -> 5000 | W11: =U11*100 -> 100
A12: 6. Azeem | B12: Thunder Dome | C12: Home ( South Africa ): 5000 bet ( Lost) | D12: 6. Silver Emerald ( Home ) | E12: -1000 | F12: • vs South Africa: 500 | I12: Home(England): 5000 bet (Won) | J12: 2. Kiwi Elephant | N12: Team of the tournament - 5400 | P12: 2. Hasan Musabbir | Q12: Best Batsman(3000): 1 | R12: 4000 | T12: Franchise League
A13: 7. Gokul G | B13: Inferno Bay Arena | C13: Home ( Scotland ): 5000 bet ( Lost ) | D13: 7. Taylor Nabi ( Home ) | E13: 1. Mccullum Graveney ( Scotland) | F13: • vs India: 500 | I13: Home(India): 6000 bet (Won) | J13: 3. Kiwi Tiger | M13: 2. Hrushikesh HD | N13: Man of the match(2000): 1 | O13: =5000+5400 -> 10400 | Q13: Most Sixes(1000): 1 | T13: KCL | U13: 1.5 | V13: =U13*1500 -> 2250 | W13: =U13*40 -> 60
A14: 8. Hasan Musabir | B14: Ironhold Park | C14: Away ( England): 5000 bet ( Lost ) | D14: 8. Archipelago Series (Home) | E14: 2. Southee Cummins( Australia ) | F14: Most sixes: 1 | I14: Home(Bangladesh): 6000 bet (Won) | J14: 4. Italio Kiwi | N14: Best Batsman(1000): 2 | P14: 3. Gautam Shankara Ram | Q14: Most Sixes(1000): 1 | R14: 1000 | T14: Total Credits | V14: =V9+V10+V11+V13 -> 29250 | W14: =W9+W10+W11+W13 -> 520
A15: 9. Hrushikesh HD | B15: Alpine Crown Arena | C15: Away ( Netherlands ): 5000 bet ( Won ) | D15: 9. Vellas Trophy (Away) | F15: • vs South Africa: 300 | I15: Away (Bangladesh): 5000 bet (Won) | J15: 5. Tasman Indus | N15: Best Bowler(1000): 1 | P15: 4. Aniket Gavit | Q15: Man of the match(5000): 1 | R15: 8000 | S15: 2. Kishore Gowda | T15: Club Series | U15: 3 | V15: =U15*1000 -> 3000 | W15: =U15*20 -> 60
A16: 10. Huzaifa Kaukawala | B16: Titan Bay Coliseum | Franchise League L1 | Ugraded | C16: Home ( Srilanka): 5000 bet ( Won ) | D16: 10. Aurora Cup (Away) | E16: Sponsors | F16: Economical bowler: 1 | I16: Away (Italy): 5000 bet (Won) | J16: 6. Desert Kiwis | N16: Team of the tournament - 5400 | Q16: Best Bowler(3000): 1 | T16: T10 Series | U16: 0.5 | V16: =U16*2000 -> 1000 | W16: =U16*40 -> 20
A17: 11. Karthik Devadiga | B17: Level 2 Stadiums | C17: Home ( USA ): 5000 bet ( Won ) | D17: 11. THE OCEANIC SHOWDOWN (Home) | E17: 100000 | F17: • vs Srilanka: 300 | I17: Away(Pakistan): 5000 bet (Won) | J17: 7. THE KIWI–AZZURRI CROWN | M17: 3. Gautam Shankara Ram | N17: Man of the match(2000): 1 | O17: =3000+5400 -> 8400 | P17: Group Stage Exit | R17: 200000 | T17: T20 Series | U17: 0.5 | V17: =U17*3000 -> 1500 | W17: =U17*40 -> 20
A18: 12. Kishore Gowda | B18: None | C18: Home ( Bangladesh ): 5000 bet ( Lost ) | D18: 12. THE EDEN PARK RUMBLE (Home) | E18: 1. Crictv Edits (Title Sponsors) | F18: 2. Kishore Gowda | I18: Away(Qatar): 5000 bet (Won) | J18: 8. Kiwis–Shaheens Test | N18: Best Batsman(1000): 1 | T18: ODI Series | U18: 3.5 | V18: =U18*5000 -> 17500 | W18: =U18*100 -> 350
A19: 13. Mahesh Margol | B19: Level 1 Stadiums | C19: Home ( Afghanistan ): 5000 bet ( Won ) | D19: 13. THE INFERNO CLASH (Home) | F19: Economical bowler: 1 | I19: Away(Australia): 5000 bet (Lost) | J19: 9. Kiwis–Falcons Test | N19: Team of the tournament - 5400 | T19: Test Tournament | U19: 1.5 | V19: =U19*8000 -> 12000 | W19: =U19*80 -> 120
A20: 14. Yeshwanth Chinni | B20: None | C20: Home ( Australia ): 5000 bet ( Lost ) | F20: • vs South Africa: 300 | I20: Home(Australia): 10000 bet (Lost) | M20: 4. Azeem | N20: Man of the match(2000): 1 | O20: 3000 | T20: ODI Tournament | U20: 0.5 | V20: =U20*8000 -> 4000 | W20: =U20*80 -> 40
A21: 15. Nithin Poojary | C21: Home (West Indies): 5000 bet (Won) | F21: 3. Mahesh | I21: Home(Italy): 10000 bet (Won) | N21: Best Batsman(1000): 1 | T21: Franchise League
A22: 16. Pratyush Mishra | B22: Traded Players: | C22: Home (Australia): 5000 bet (Lost) | F22: Most Sixes: 1 | I22: Home(Pakistan): 10000 (Won) | M22: 5. Toby Joseph | N22: Best Captain Award(15000) | O22: =15000+6000 -> 21000 | T22: CPL | U22: 1.5 | V22: =U22*1500 -> 2250 | W22: =U22*40 -> 60
A23: 17. Ram Thakkar | B23: 45000 | C23: Away (Pakistan): 5000 bet (Won) | F23: • vs Srilanka: 300 | I23: Home(Qatar): 10000 (Won) | N23: Team of the tournament(Captain) - 6000 | T23: Total Credits | V23: =V15+V16+V17+V22+V18+V19+V20 -> 41250 | W23: =W15+W16+W17+W22+W18+W19+W20 -> 670
A24: 18. Ramith Acharya | B24: 1. Shibasis to SA: 5000 | C24: Away(England): 10000 bet (Lost) | F24: 4. Gautam | M24: 6. Srajan Poojari | N24: Team of the tournament - 5400 | O24: 5400 | S24: 3. Aniket Gavit | T24: T20 Series | U24: 7 | V24: =U24*3000 -> 21000 | W24: =U24*40 -> 280
A25: 19. Salar Shah | B25: 2. Ashutoh from BD: 5000 | C25: Away(Qatar): 5000 bet (Lost) | F25: Man of the match: 1 | H25: Players Awards & Credits | M25: Official Host | O25: 100000 | T25: ODI Series | U25: 4 | V25: =U25*5000 -> 20000 | W25: =U25*100 -> 400
A26: 20. Sanan Abrar | B26: 3. Ajith to India: 10000 | C26: Away(Canada): 5000 bet (Won) | F26: • vs Pakistan: 500 | H26: Player | I26: Award | J26: Credits | M26: Fair Play Award | O26: 40000 | T26: Test Tournament | U26: 8 | V26: =U26*8000 -> 64000 | W26: =U26*80 -> 640
A27: 21. Toby Joseph | B27: 4. Naveen to PNG: 5000 | C27: Away(England & Italy): 10000 (Lost) | F27: Most sixes: 1 | H27: 1. Shibasis | I27: Man of the Match: 1 (1000) | J27: 2000 | M27: Runners-UP | O27: 150000 | T27: ODI Tournament | U27: 5 | V27: =U27*8000 -> 40000 | W27: =U27*80 -> 400
A28: 22. Tukaram Parabat | B28: 5. Jabir to PNG: 30000 | C28: Home(West Indies): 15000 (Won) | F28: • vs Pakistan: 300 | I28: Best Batsman: 0 (500) | T28: Franchise League
A29: 23. Vikas Acharya | C29: Home(Italy): 7000 (Lost) | F29: Economical bowler: 1 | I29: Best Bowler: 2 (500) | T29: BBL | U29: 3 | V29: =U29*1500 -> 4500 | W29: =U29*40 -> 120
A30: 24. Yashwanth Yash | C30: Home(India): 10000 (Won) | F30: • vs West Indies: 300 | H30: 2. Nithin Poojary | I30: Man of the Match: 1 (1000) | J30: 3000 | T30: BBL ( Commentator ) | U30: 1 | V30: =U30*1500 -> 1500 | W30: =U30*40 -> 40
C31: Home(Australia): 10000 (Won) | F31: 5. Harish | I31: Best Batsman: 4 (500) | T31: KCL | U31: 10.5 | V31: =U31*1500 -> 15750 | W31: =U31*40 -> 420
F32: Most sixes: 2 | I32: Best Bowler: 0 (500) | T32: BPL | U32: 1.5 | V32: =U32*1500 -> 2250 | W32: =U32*40 -> 60
F33: • vs West Indies: 300 | H33: 3. Ram Thakkar | I33: Man of the Match: 0 (1000) | J33: 500 | T33: Total Credits | V33: =V24+V25+V26+V29+V30+V31+V32+V27 -> 169000 | W33: =W24+W25+W26+W29+W30+W31+W32+W27 -> 2360
F34: • vs Scotland: 300 | I34: Best Batsman: 0 (500) | S34: 4. Azeem | T34: Franchise League
F35: 6. Yashwanth | I35: Best Bowler: 1 (500) | T35: CPL | U35: 0.5 | V35: =U35*1500 -> 750 | W35: =U35*40 -> 20
F36: Economical bowler: 1 | H36: 4. Hasan Musabbir | I36: Man of the Match: 1 (1000) | J36: 1500 | T36: Total Credits | V36: =V35 -> 750 | W36: =W35 -> 20
F37: • vs Scotland: 300 | I37: Best Batsman: 1 (500) | S37: 5. Tejasvin AV | T37: ODI Tournament | U37: 0.5 | V37: =U37*8000 -> 4000 | W37: =U37*80 -> 40
F38: Eliminated in Super Six: 15000 | I38: Best Bowler: 0 (500) | T38: Total Credits | V38: =V37 -> 4000 | W38: =W37 -> 40
H39: 5. Toby Joseph | I39: Man of the Match: 3 (1000) | J39: 4000
I40: Best Batsman: 0 (500)
I41: Best Bowler: 2 (500)
H42: 6. Srajan Poojari | I42: Man of the Match: 0 (1000) | J42: 500
I43: Best Batsman: 1 (500)
I44: Best Bowler: 0 (500)
H45: 7. Gautam Shankara Ram | I45: Man of the Match: 2 (1000) | J45: 2000
I46: Best Batsman: 0 (500)
I47: Best Bowler: 0 (500)
H48: 8. Kishore Gowda | I48: Man of the Match: 0 (1000) | J48: 500
I49: Best Batsman: 1 (500)
A50: All Franchise League Credits Updates : | I50: Best Bowler: 0 (500)
A51: =A53+A76+A92+A111+A131+A150+A182+A211+A236 -> 3378835 | H51: 9. Hrushikesh HD | I51: Man of the Match: 1 (1000) | J51: 1500
A52: THE HUNDRED : | I52: Best Batsman: 1 (500)
A53: 54150 | I53: Best Bowler: 0 (500)
A54: 2026 | H54: 10. Tejasvin Av | I54: Man of the Match: 1 (1000) | J54: 1000
A55: London Spirit | B55: Southern Brave | C55: Welsh Fire | D55: MI London | E55: Sunrisers Leeds | I55: Best Batsman: 0 (500)
A56: Team Profit: 9500 | C56: Team Profit: 1200 | D56: Team Profit: 35400 | E56: Team Profit: 6250 | I56: Best Bowler: 0 (500)
A57: 1. Ram Thakkar | C57: 1. Gowri Madhu | D57: 1. Srajan Poojary | E57: 1. Kishore Gowda
A58: Salary: 3500 | C58: Salary: 1200 | D58: Salary: 3000 | E58: Salary: 2500
A59: Man of the match: 1 ( 500 ) | D59: Best Bowler: 2 ( 400 ) | E59: Man of the match: 1 ( 500 )
A60: Best Bowler: 3 ( 600 ) | D60: Man of the match: 2 ( 1000 ) | E60: Best Batsman: 2 ( 400 )
A61: Best Batsman:1 ( 200 ) | D61: Champions: 5300 | E61: Runners up: 2850
A62: 2. Yashwanth Yash | D62: 2. Gautam Shankara Ram | E62: 2. Suman
A63: Salary: 3000 | D63: Salary: 2500 | E63: Salary: 1000
A64: 3. Mahesh Margol | D64: Champions: 5300
A65: Salary: 1500 | D65: 3. Hasan Musabbir
A66: Best Bowler: 1 ( 200 ) | D66: Salary: 1000
D67: Best Batsman: 2 ( 400 )
D68: Man of the match: 1 ( 500 )
D69: Most Sixes Tournament Award: 5000
D70: Champions: 5300
D71: 4. Harish
D72: Salary: 1200
D73: Champions: 5300
A75: Pakistan Super League :
A76: 42660
A77: 2026
A78: LAHORE QALANDARS | B78: PINDIZ | C78: MULTAN SULTANS | D78: KARACHI KINGS | E78: QUETTA GLADIATORS | F78: HYDERABAD KINGSMEN
A79: Team Profit: 5490 | B79: Team Profit: 9100 | C79: Team Profit: 6600 | D79: Team Profit: 5850 | E79: Team Profit: 5160 | F79: Team Profit: 11460
A80: 1. Karthik | B80: 1. Kishore Gowda | C80: 1. Srajan Poojary | D80: 1. Ram Thakkar | E80: 1. Mahesh Margol | F80: 1. Gautam
A81: Salary: 500 | B81: Direct Signing: 4500 | C81: Salary: 5200 | D81: Salary: 5250 | E81: Salary: 500 | F81: Salary: 3200
A82: Champions: 4990 | B82: 2. Yashwanth Yash | C82: 2. Gowri Madhu | D82: Best Batsman: 2 ( 400 ) | E82: Fair Play: 1380 | F82: Man of the Match: 1 (500)
B83: Salary: 2400 | C83: Salary: 500 | D83: Best Bowler:1 (200) | E83: 2. Tukaram Parabat | F83: Best Batsman: 1 ( 200 )
B84: 3. Hrushikesh HD | C84: 3. Harish | E84: Salary: 500 | F84: Runners up: 2480
B85: Salary: 500 | C85: Salary: 500 | E85: Man of the match: 2 (1000) | F85: 2. Hasan
B86: Man of the Match: 1 (500) | C86: Best Batsman: 1 ( 200 ) | E86: Best Bowler:2 (400) | F86: Salary: 2600
B87: Best Batsman: 1 ( 200 ) | C87: 4. Aniket Gavi | E87: Fair Play: 1380 | F87: Runners up: 2480
C88: No Salary(Traded)
C89: Best Batsman: 1 ( 200 )
A91: Big Bash League :
A92: 118800
A93: 2026
A94: All Team Profit: 118800
A95: Adelaide Strikers | B95: Brisbane Heat | C95: Hobart Hurricanes | D95: Melbourne Renegades | E95: Melbourne Stars | F95: Perth Scorchers | G95: Sydney Sixers | H95: Sydney Thunders
A96: Team Profit: 7000 | B96: Team Profit: 7600 | C96: Team Profit: 25500 | D96: Team Profit: 24500 | E96: Team Profit: 17700 | F96: Team Profit: 6000 | G96: Team Profit: | H96: Team Profit: 31000
A97: 1. Harish | B97: 1. Hasan | C97: 1. Mahesh | D97: 1. Srajan Poojari | E97: 1. Aniket | F97: 1. Kishore | H97: 1. Ram
A98: Salary: 3500 | B98: Salary: 4000 | C98: Salary: 3500 | D98: Direct Signing: 5000 | E98: Salary: 11000 | F98: Salary: 6000 | H98: Salary: 21000
A99: 2. Hrushikesh | B99: Best Bowler: 1 ( 500 ) | C99: 2. Tukaram | D99: Man of the match: 1 ( 1000 ) | E99: Best Batsman: 1 (500) | H99: Best Batsman: 1 (500)
A100: Salary: 3500 | B100: Fair Play Award: 3100 | C100: Salary: 4500 | D100: Best Bowler: 2 ( 1000 ) | E100: Runners up: 6200 | H100: 2. Shibasis
C101: Man of the Match: 2 ( 2000 ) | D101: 2. Gautam | H101: Salary: 7000
C102: Best Bowler: 1 ( 500 ) | D102: Salary: 16000 | H102: Man of the match: 1 ( 1000 )
...

Sheet Pakistan
A1: Board: Pakistan
A2: Chairman: Shamroz | CEO: Nasrullah Kapri
A3: Credits left:
A4: =100000+B6+C6+E6+E12+F6+G6+H6+A69+F13+D17+K6+T6+Q6+N6 -> 6798500
A5: Players | B5: Stadium: | C5: International Series: | D5: Trophy Cabinet ( International Series) | E5: Whitewash win: | F5: Player limit exceeded: | G5: IOCF T20 WORLD CUP 🏆: | H5: IOCF WORLD TEST CHAMPIONSHIP 🏆: | K5: CONTINENTAL CUP 2026 🏆: ( ASIA ) | N5: Women's Global League 2026 🏆: | Q5: ODI WORLD CUP 🏆: | T5: Umpires Credits :
A6: 1. Aaiz Khan | B6: -230000 | C6: 2000 | D6: 1. Pointing - Inzamam ( Away ) | E6: 3000 | F6: -40000 | G6: 17000 | H6: =H8+I8+J8 -> -3500 | K6: =K8 -> 8000 | N6: =N8 -> 70000 | Q6: =-1200000+Q9 -> 1892000 | T6: =W24+W29+W45+W53+W65+W69+W71 -> 1171500
A7: 2. Aena Khan | B7: Level 3 Stadiums | C7: Away( Australia ): 5000 bet ( Won ) | D7: 2. Thistle Shaheen ( Away ) | E7: 1. Thistle Shaheen ( Away ) | F7: 1. 20 to 25: 10000 | G7: Entry: -5000 | H7: Player Awards | I7: Match Bet Credits | J7: Entry Credits | K7: Players & Match Awards | N7: Players & Match Awards | Q7: Hosting Amount: 12L | T7: Umpire | U7: Details | V7: Total Matches | W7: Credits | X7: Points
A8: 3. Ayaan Sheikh | B8: Pindi International Stadium | C8: Away( Srilanka ): 6000 bet ( Lost ) | D8: 3. Crecsent Carnage ( Away ) | E8: 2. Crecsent Carnage ( Away ) | F8: 2. 26 to 30: 10000 | G8: Players Awards: 2000 | H8: =J24+J27+J30+J33+J36+J39+J42 -> 6500 | I8: -5000 | J8: -5000 | K8: =M9+M10+M11+M12+M13 -> 8000 | N8: =P10+P11 -> 70000 | Q8: Players & Match Awards | T8: 1. Nasrullah Kapri | U8: Club Series | V8: 14 | W8: =V8*1000 -> 14000 | X8: =V8*20 -> 280
A9: 4. Ayat | B9: Karachi International Stadium | C9: Away( Newzealand): 3000 bet ( Lost ) | D9: 4. Rhine Indus ( Away ) | E9: 3. Sons & Daughter (Away) | F9: 3. 30 to 35: 10000 | G9: 1. Bhavin | I9: Away(Australia): 5000 (Lost) | J9: Trophy Cabinet (Test) | K9: 1. Wajdan | L9: Man of the match(2000): 1 | M9: 2000 | N9: Player | O9: Award | P9: Credits | Q9: =S11+S12+S14+S17+S21+S22+S26+S29+S30+S31+S32+S33+S34+S35 -> 3092000 | U9: T10 Series | V9: 5 | W9: =V9*2000 -> 10000 | X9: =V9*40 -> 200
A10: 5. Ayla Ali | B10: Gaddafi Stadium Lahore | Franchise League L1 | Upgraded | C10: Home( West Indies): 5000 bet ( Lost ) | D10: 5. Khyber Cup (Away ) | F10: 4. 36 to 40: 10000 | G10: Most Sixes: 1 | I10: Away (West Indies): 5000 (Won) | J10: 1. Mallu Pak | K10: 2. Ayaan Sheikh | L10: Best Batsman(1000): 2 | M10: 2000 | N10: Best Women Talent Discovery Board | P10: 20000 | Q10: Player | R10: Award | S10: Credits | U10: T20 Series | V10: 4.5 | W10: =V10*3000 -> 13500 | X10: =V10*40 -> 180
A11: 6. Daniyal Sheikh | B11: Multan International Stadium | C11: Away( Scotland): 5000 bet ( Won ) | D11: 6. Pollard Akhter (Away) | E11: Whitewash lose: | G11: • vs India: 300 | I11: Away (Bangladesh): 5000 (Won) | J11: 2. Bangladesh Shaheen | K11: 3. Zarnish Saira | L11: Best Bowler(1000): 1 | M11: 1000 | N11: Fair Play | P11: 50000 | Q11: 1. Hizbullah Sahito | R11: Man of the match(5000): 1 | S11: 5000 | U11: Test Series | V11: 3 | W11: =V11*4000 -> 12000 | X11: =V11*80 -> 240
A12: 7. Farhan Mohammad | B12: Hyder Cricket Stadium | C12: Away(SL,Scot,WI): 6000 bet ( Lost) | D12: 6. Sons & Daughters of Mother Trophy (Away) | E12: -500 | F12: Player Trade: | G12: Man of the match:1 | I12: Away(India): 5000 bet (Lost) | J12: 3. Green & Orange Test | K12: 4. Shamroz | L12: Man of the match(2000): 1 | M12: 2000 | Q12: 2. Shamroz | R12: Best Bowler(3000): 1 | S12: 3000 | U12: T20 Tournament | V12: 8 | W12: =V12*6000 -> 48000 | X12: =V12*40 -> 320
A13: 8. Ganesh Chunduru | B13: Quetta Cricket Arena | C13: Away( England): 5000 bet ( Lost) | D13: 7. BANK AL-HABIB (Home) | E13: 1. Silk Steel ( Newzealand) | F13: =28000 -> 28000 | G13: • vs Srilanka: 500 | I13: Home(Bangladesh): 5000 (Lost) | K13: 5. Muhammad Ahmed | L13: Best Bowler(1000): 1 | M13: 1000 | R13: Most Dot Balls(1000): 1 | U13: Test Tournament | V13: 6 | W13: =V13*8000 -> 48000 | X13: =V13*80 -> 480
A14: 9. Ghamshad Baloch | B14: Karakoram Stadium Skardu | C14: Away( Scotland): 10000 bet ( Won ) | D14: 8. Summer Series (Home) | F14: 1. Summan Baig from Aus - 2k | G14: 2. Zarnish | I14: Home(Newzealand): 5000 (Lost) | Q14: 3. Muhammad Ahmed | R14: Man of the match(5000): 1 | S14: 307000 | U14: ODI Series | V14: 1 | W14: =V14*5000 -> 5000 | X14: =V14*100 -> 100
A15: 10. Hizbullah Sahito | B15: Khyber Stadium Peshawar | C15: Away ( UAE ): 5000 bet ( Lost ) | F15: 2. Engr to Afg( Comp for Chairman): 10000 | G15: Economical bowler: 1 | I15: Home(Netherlands): 5000 (Won) | R15: Most Sixes(1000): 2 | U15: ODI Tournament | V15: 13.5 | W15: =V15*10000 -> 135000 | X15: =V15*100 -> 1350
A16: 11. Iqra Batool | B16: Level 2 Stadiums | C16: Away ( Afghanistan ): 5000 bet ( Lost ) | D16: IOCF LONE WARRIOR | F16: 3. Ali Abbas to Ireland(Compt for Chairman): 10000 | G16: • vs South Africa: 300 | I16: Away(Newzealand): 10000 (Lost) | R16: Fastest 50: 300000 | U16: Franchise League
A17: 12. Khan Mahar | B17: None | C17: Away ( Netherlands): 3000 bet ( Won ) | D17: 20000 | F17: 4. Rima to Aus: 25000 | G17: 3. Nasrullah | I17: Away(Srilanka): 10000 (Lost) | Q17: 4. Umar Abbas | R17: Man of the match(5000): 1 | S17: 110000 | U17: PSL | V17: 10 | W17: =V17*1500 -> 15000 | X17: =V17*40 -> 400
A18: 13. Maheen Khan | B18: Level 1 Stadiums | C18: Home (Australia): 10000 bet (Lost) | D18: Runners Up: Shamroz | F18: 5. Rima from Aus: 25000 | G18: Most Sixes: 1 | R18: Best Batsman(3000): 1 | U18: PSL ( Commentator ) | V18: 1 | W18: =V18*1500 -> 1500 | X18: =V18*40 -> 40
A19: 14. Manasa | B19: None | C19: Away ( Afghanistan ): 5000 bet ( Won ) | F19: 6. Talha to Spain(Compt for Chairman): 10000 | G19: • vs Newzealand: 300 | R19: Most Sixes(1000): 2 | U19: BBL | V19: 1 | W19: =V19*1500 -> 1500 | X19: =V19*40 -> 40
A20: 15. Mansuri | C20: Away (West Indies): 5000 bet (Won) | G20: 4. Ans Sheikh | R20: Best Umpire(100000) | U20: KCL | V20: 1 | W20: =V20*1500 -> 1500 | X20: =V20*40 -> 40
A21: 16. Marukh Khan | C21: Home (Afghanistan): 5000 bet (Lost) | G21: Economical bowler: 1 | Q21: 5. Maheen Khan | R21: Best Batsman(3000): 1 | S21: 3000 | U21: BPL | V21: 2 | W21: =V21*1500 -> 3000 | X21: =V21*40 -> 80
A22: 17. Masrifa Munni | C22: Home (England): 5000 bet (Lost) | G22: • vs Newzealand: 300 | H22: Players Awards & Credits | Q22: 6. Aaiz Khan | R22: Man of the match(5000): 1 | S22: 309000 | U22: IPL | V22: 1 | W22: =V22*1500 -> 1500 | X22: =V22*40 -> 40
A23: 18. Mian Bilal | C23: Away (Bangladesh): 5000 bet (Won) | G23: 5. Talha | H23: Player | I23: Award | J23: Credits | R23: Best Batsman(3000): 1 | U23: QECL | V23: 2 | W23: =V23*1500 -> 3000 | X23: =V23*40 -> 80
A24: 19. Moiz Mohsin | C24: Home (Newzealand): 5000 bet (Lost) | G24: Economical bowler: 1 | H24: 1. Nasrullah Kapri | I24: Man of the Match: 1 (1000) | J24: 1500 | R24: Most Sixes(1000): 1 | U24: Total Credits | W24: =W8+W9+W10+W11+W12+W13+W17+W18+W19+W20+W21+W22+W14+W15+W23 -> 312500 | X24: =X8+X9+X10+X11+X12+X13+X17+X18+X19+X20+X21+X22+X14+X15+X23 -> 3870
A25: 20. Muhammad Ahmad | C25: Home(Bangladesh): 5000 bet (Won) | G25: • vs Srilanka: 300 | I25: Best Batsman: 1 (500) | R25: Highest Score in a Match: 300000 | T25: 2. Shamroz | U25: Club Series | V25: 2 | W25: =V25*1000 -> 2000 | X25: =V25*20 -> 40
A26: 21. Muhammad Ali | C26: Home(Qatar): 5000 bet (Won) | G26: Eliminated In Group Stage: 10k | I26: Best Bowler: 0 (500) | Q26: 7. Sidra | R26: Best Bowler(3000): 1 | S26: 204000 | U26: T20 Series | V26: 0.5 | W26: =V26*3000 -> 1500 | X26: =V26*40 -> 20
A27: 22. Muhammad Huzaifa | C27: Away(Ireland): 5000 bet (Lost) | H27: 2. Zarnish Saira | I27: Man of the Match: 1 (1000) | J27: 1500 | R27: Most Dot Balls(1000): 1 | U27: Franchise League
A28: 23. Rima Naskar Sona | G28: Players Awards: 10000 | I28: Best Batsman: 1 (500) | R28: Best Bowling Figures in a Match: 200000 | U28: PSL | V28: 0.5 | W28: =V28*1500 -> 750 | X28: =V28*40 -> 20
A29: 24. Rima Roy | G29: 1. Bhavin Kumar | I29: Best Bowler: 0 (500) | Q29: 8. Zarnish Saira | R29: Most Dot Balls(1000): 1 | S29: 1000 | U29: Total Credits | W29: =W25+W26+W28 -> 4250 | X29: =X25+X26+X28 -> 80
A30: 25. Sanjana | G30: Best Bat Average(65.5): 5000 | H30: 3. Iqra | I30: Man of the Match: 0 (1000) | J30: 500 | Q30: 9. Ganesh Chunduru | R30: Best Umpire(100000) | S30: 100000 | T30: 3. Ganesh Chunduru | U30: Club Series | V30: 14 | W30: =V30*1000 -> 14000 | X30: =V30*20 -> 280
A31: 26. Sheikh Arhum | G31: 2. Nasrullah | I31: Best Batsman: 1 (500) | Q31: 10. Nasrullah Kapri | R31: Word Cup Operations Excellence (100000) | S31: 100000 | U31: T10 Series | V31: 6 | W31: =V31*2000 -> 12000 | X31: =V31*40 -> 240
A32: 27. Shumaila | G32: Fastest Host of IOCF: 5000 | I32: Best Bowler: 0 (500) | Q32: Hosting Board | S32: 1000000 | U32: T20 Series | V32: 6 | W32: =V32*3000 -> 18000 | X32: =V32*40 -> 240
A33: 28. Sidra | H33: 4. Muhammad Ahmed | I33: Man of the Match: 0 (1000) | J33: 500 | Q33: Quarterfinalists | S33: 500000 | U33: ODI Series | V33: 9.5 | W33: =V33*5000 -> 47500 | X33: =V33*100 -> 950
A34: 29. Summan Baig | I34: Best Batsman: 0 (500) | Q34: Prediction Contest: 2nd Place | S34: 250000 | U34: Club Tournament | V34: 2 | W34: =V34*2000 -> 4000 | X34: =V34*20 -> 40
A35: 30. Suranja Deepal | I35: Best Bowler: 1 (500) | Q35: Fantasy League: 2nd Place | S35: 200000 | U35: Test Tournament | V35: 12 | W35: =V35*8000 -> 96000 | X35: =V35*80 -> 960
A36: 31. Taniya | H36: 5. Hizbullah Sahito | I36: Man of the Match: 1 (1000) | J36: 1500 | U36: ODI Tournament | V36: 27 | W36: =V36*10000 -> 270000 | X36: =V36*100 -> 2700
A37: 32. Umar Abbas | I37: Best Batsman: 0 (500) | U37: Franchise League
A38: 33. Usman | I38: Best Bowler: 1 (500) | U38: 100 | V38: 1 | W38: =V38*1500 -> 1500 | X38: =V38*40 -> 40
A39: 34. Wafa Baloch | H39: 6. Muhammad Ali | I39: Man of the Match: 0 (1000) | J39: 500 | U39: PSL | V39: 12 | W39: =V39*1500 -> 18000 | X39: =V39*40 -> 480
A40: 35. Wajdan | I40: Best Batsman: 1 (500) | U40: KCL | V40: 1 | W40: =V40*1500 -> 1500 | X40: =V40*40 -> 40
A41: 36. Zarnish Saira | I41: Best Bowler: 0 (500) | U41: BPL | V41: 1.5 | W41: =V41*1500 -> 2250 | X41: =V41*40 -> 60
H42: 7. Daniyal | I42: Man of the Match: 0 (1000) | J42: 500 | U42: IPL | V42: 4 | W42: =V42*1500 -> 6000 | X42: =V42*40 -> 160
I43: Best Batsman: 1 (500) | U43: CPL | V43: 1 | W43: =V43*1500 -> 1500 | X43: =V43*40 -> 40
I44: Best Bowler: 0 (500) | U44: QECL | V44: 4 | W44: =V44*1500 -> 6000 | X44: =V44*40 -> 160
U45: Total Credits | W45: =W30+W31+W32+W33+W34+W35+W38+W39+W40+W41+W42+W43+W36+W44 -> 498250 | X45: =X30+X31+X32+X33+X34+X35+X38+X39+X40+X41+X42+X43+X36+X44 -> 6390
T46: 4. Muhammad Ahmed | U46: Club Series | V46: 5 | W46: =V46*1000 -> 5000 | X46: =V46*20 -> 100
U47: T10 Series | V47: 2 | W47: =V47*2000 -> 4000 | X47: =V47*40 -> 80
U48: Test Tournament | V48: 1 | W48: =V48*8000 -> 8000 | X48: =V48*80 -> 80
U49: ODI Tournament | V49: 3 | W49: =V49*10000 -> 30000 | X49: =V49*100 -> 300
U50: Franchise League
U51: PSL | V51: 2 | W51: =V51*1500 -> 3000 | X51: =V51*40 -> 80
U52: PSL ( Commentator ) | V52: 1 | W52: =V52*1500 -> 1500 | X52: =V52*40 -> 40
U53: Total Credits | W53: =W46+W47+W48+W51+W52+W49 -> 51500 | X53: =X46+X47+X48+X51+X52+X49 -> 680
T54: 5. Hizbullah Sahito | U54: Club Series | V54: 5 | W54: =V54*1000 -> 5000 | X54: =V54*20 -> 100
U55: T20 Series | V55: 7 | W55: =V55*3000 -> 21000 | X55: =V55*40 -> 280
U56: Club Tournament | V56: 2 | W56: =V56*2000 -> 4000 | X56: =V56*20 -> 40
U57: Test Tournament | V57: 6.5 | W57: =V57*8000 -> 52000 | X57: =V57*80 -> 520
U58: ODI Series | V58: 2.5 | W58: =V58*5000 -> 12500 | X58: =V58*100 -> 250
U59: ODI Tournament | V59: 8 | W59: =V59*10000 -> 80000 | X59: =V59*100 -> 800
U60: T10 Series | V60: 1 | W60: =V60*2000 -> 2000 | X60: =V60*40 -> 40
U61: Franchise League
U62: BPL | V62: 2 | W62: =V62*1500 -> 3000 | X62: =V62*40 -> 80
U63: IPL | V63: 2 | W63: =V63*1500 -> 3000 | X63: =V63*40 -> 80
U64: QECL | V64: 4 | W64: =V64*1500 -> 6000 | X64: =V64*40 -> 160
U65: Total Credits | W65: =W55+W56+W57+W62+W63+W58+W54+W59+W60+W64 -> 188500 | X65: =X55+X56+X57+X62+X63+X58+X54+X59+X60+X64 -> 2350
T66: 6. Umar Abbas | U66: ODI Tournament | V66: 11 | W66: =V66*10000 -> 110000 | X66: =V66*100 -> 1100
U67: Franchise League
A68: All Franchise League Credits Updates : | U68: QECL | V68: 1 | W68: =V68*1500 -> 1500 | X68: =V68*40 -> 40
A69: =A72+A84+A117+A152+A179+A200+A240+A260+A300 -> 3761000 | U69: Total Credits | W69: =W66+W68 -> 111500 | X69: =X66+X68 -> 1140
T70: 6. Aaiz Khan | U70: ODI Tournament | V70: 0.5 | W70: =V70*10000 -> 5000 | X70: =V70*100 -> 50
A71: THE HUNDRED : | U71: Total Credits | W71: =W70 -> 5000 | X71: =X70 -> 50
A72: 22300
A73: 2026
A74: London Spirit | B74: Southern Brave | C74: Welsh Fire | D74: MI London | E74: Sunrisers Leeds
A75: Team Profit: 5000 | D75: Team Profit: 1000 | E75: Team Profit: 11000
A76: 1. Zarnish Saira | D76: 1. Ans Sheikh | E76: 1. Shamroz
A77: Salary: 2300 | D77: Salary(Replacement Player): 1000 | E77: Salary: 3000
A78: 2. Bhavin Kumar | D78: Champions: 5300 | E78: Runners Up: 2850
A79: Salary: 2000 | E79: 2. Nasrullah
A80: Man of the match: 1 ( 500 ) | E80: Salary: 2300
A81: Best Batsman: 1 ( 200 ) | E81: Runners Up: 2850
A83: Pakistan Super League ( Own League )
A84: 137880
A85: 2026
A86: Hosting Rights : 50000
A87: All Team Profit: 142880
A88: LAHORE QALANDARS | B88: PINDIZ | C88: MULTAN SULTANS | D88: KARACHI KINGS | E88: QUETTA GLADIATORS | F88: HYDERABAD KINGSMEN
A89: Team Profit: 61340 | B89: Team Profit: 14100 | C89: Team Profit: 14400 | D89: Team Profit: 13900 | E89: Team Profit: 21080 | F89: Team Profit: 24160
A90: 1. Muhammad Usman | B90: 1. Muhammad Ahmad | C90: 1. Engr Ans Sheikh | D90: 1. Nasrullah Kapri | E90: 1. Zarnish Saira | F90: 1. Bhavin Kumar
A91: Captain Salary: 7000 | B91: Captain Salary: 7000 | C91: Captain Salary: 7000 | D91: Captain Salary: 7000 | E91: Captain Salary: 7000 | F91: Captain Salary: 7000
A92: Man of the match: 2 (1000) | B92: Best Bowler: 1 ( 200 ) | C92: Man of the match: 2 ( 1000 ) | D92: Best Bowler: 1 ( 200 ) | E92: Best Bowler: 1 ( 200 ) | F92: Man of the Match: 3 ( 1500 )
A93: Best Batsman: 1 ( 200 ) | B93: 2. Aaiz Khan | C93: Best Bowler: 2 ( 400 ) | D93: 2. Hizbullah Sahito | E93: Fair Play(Captain): 1540 | F93: Best Batsman: 1 ( 200 )
A94: Best Bowler: 1 ( 200 ) | B94: Icon Salary: 4000 | C94: 2. Arslan Ali Shani | D94: Icon Salary: 4000 | E94: 2. Shamroz | F94: Best Bowler: 2 ( 400 )
A95: Most Sixes: 5000 | B95: Man of the match: 1 (500) | C95: Icon Salary: 4000 | D95: Man of the match: 1 ( 500 ) | E95: Icon Salary: 4000 | F95: Runners up ( Captain ): 2880
A96: Champions ( Captain ) : 5190 | B96: Best Bowler: 2 (400) | C96: 3. M Huzaifa | D96: Best Batsman: 1 ( 200 ) | E96: Fair Play: 1380 | F96: 2. Ganesh Chunduru
A97: 2. Ayaan Sheikh | B97: 3. Moiz Mohsin | C97: Salary: 2000 | D97: 3. Ghamshad Baloch | E97: 3. Talha | F97: Icon Salary: 4000
A98: Icon Salary: 4000 | B98: Salary: 2000 | D98: Salary: 3000 | E98: Salary: 3000 | F98: Runners up: 2480
A99: Champions: 4990 | D99: 4. Khan Mahar | E99: Fair Play: 1380 | F99: 3. Masrifa Munni
A100: 3. Wafa Baloch | D100: Salary: 2000 | E100: 4. Suranja | F100: Salary: 3500
A101: Salary: 3000 | D101: 4. Ayat | E101: Salary: 500 | F101: Runners up: 2480
...

Sheet PNG
A1: Board: PAPUA NEW GUINEA
A2: Chairman: Aman Raj Singh | CEO: Sayed Babu
A3: Credits left:
A4: =100000+D6+B6+F6+A29+C6 -> 253225
A5: Players | B5: Player trade: | C5: Stadium: | D5: International Series: | E5: Trophy Cabinet ( International Series) | F5: Umpires Credits :
A6: 1. Abhishek Rana | B6: 13000 | C6: -60000 | D6: 19500 | E6: 1. Green Flag Trophy (Away) | F6: =I9 -> 3000
A7: 2. Aman Saini | B7: 1. Yohaan: Chairman of Kenya(10k) | C7: Level 3 Stadiums | D7: 1. Away(West Indies): 5000 (Won) | E7: 2. United Nations Cricket Summit (Away) | F7: Umpire | G7: Details | H7: Total Matches | I7: Credits | J7: Points
A8: 3. Anandhu Nandhu | B8: 2. Kuldeep to Argentina: 10k | C8: Royal PNG signature stadium | D8: 2. Away(Nepal): 3000 (Lost) | E8: 3. UAE PNG Friendship Series (Away) | F8: 1. Aman Raj Singh | G8: T20 Series | H8: 1 | I8: =H8*3000 -> 3000 | J8: =H8*40 -> 40
A9: 4. Ansh Akki | B9: 3. Furqan from Spain: 5k | C9: Young Monk | D9: 3. Away(Netherlands, Canada, West Indies): 7500 (Won) | E9: 4. Golden Raggiana Trophy (Home) | G9: Total Credits | I9: =I8 -> 3000 | J9: =J8 -> 40
A10: 5. Viraj Sharma | B10: 4. Dileep to England: 19000 | D10: 4. Home(USA): 5000 (Lost)
A11: 6. Grishav | B11: 5. Naveen from Canada: Free | D11: 5. Away(UAE): 5000 (Won)
A12: 7. Harry Gujjar | B12: 6. Ishaq to Spain: 5000 | D12: 6. Away(UAE): 5000 (Lost)
A13: 8. Naveen Gupta | B13: 7. Naveen from NZ: 5000 | D13: 7. Home(Ireland): 5000 (Won)
A14: 9. Josiya | B14: 8. Jabir from NZ: 30000
A15: 10. Kalash
A16: 11. Mehul
A17: 12. Mumtaz Khan
A18: 13. Pawan
A19: 14. Prakash Singh Negi
A20: 15. Pranjal Kundaliya
A21: 16. Salik Hassan
A22: 17. Shivi
A23: 18. Suhail PS
A24: 19. Urmila
A25: 20. Draco
A26: 21. Naveen
... A28: All Franchise League Credits Updates :
A29: =A31 -> 177725
A30: Qatar Elite Crown League :
A31: =A34 -> 177725
A32: 2026
A33: All Team Profit:
A34: =A37+B37+C37+D37+E37+F37+G37+H37 -> 177725
A35: AL KHOR PREDATORS | B35: AL RAYYAN RAIDERS | C35: AL WAKRAH DUKES | D35: DOHA STALLIONS | E35: LUSAIL KNIGHTS | F35: MESAEID BLAZE | G35: QATAR VENOMS | H35: UMM SALAL SPARTANS
A36: Team Profit: | B36: Team Profit: | C36: Team Profit: | D36: Team Profit: | E36: Team Profit: | F36: Team Profit: | G36: Team Profit: | H36: Team Profit:
A37: 0 | B37: 33725 | C37: 0 | D37: 10000 | E37: 132000 | F37: 0 | G37: 0 | H37: 2000
B38: 1. Naveen Gupta | D38: 1. Furqan | E38: 1. Sayed Babu | H38: 1. Kalash
B39: No Salary(Traded) | D39: Salary: 2000 | E39: Salary: 7000 | H39: Salary: 2000
B40: Fair Play: 33725 | D40: 2. Ishaq Ahmed | E40: 2. Aman Raj Singh
D41: Salary: 8000 | E41: Salary: 125000

Sheet Portugal
A1: Board: Portugal
A2: Chairman: Kailas MS | CEO: -
A3: Credits left:
A4: =100000+C6+B6+D6 -> 72000
A5: Players | B5: Player trade: | C5: Stadium: | D5: International Series: | E5: Trophy Cabinet ( International Series)
A6: 1. Akhil | B6: -7000 | C6: -30000 | D6: 9000 | E6: 1. The Goat Cup (Away)
A7: 2. Akshay Vernam | B7: 1. Akshay from Scot: 5k | C7: Level 3 Stadiums | D7: 1. Away(Argentina): 3000 bet (Lost) | E7: 2. Himalayan Dreams (Away)
A8: 3. Anand | B8: 2. Sujith from Eng: 2k | C8: Lisbon Cricket Ground | D8: 2. Away(Nepal & England): 3000 bet (Won)
A9: 4. Ashiq
A10: 5. Irshad
A11: 6. Irshad
A12: 7. Jijith
A13: 8. Lalu
A14: 9. Mubashir
A15: 10. Mushfik
A16: 11. Pranav
A17: 12. Rashid M
A18: 13. Sandra
A19: 14. Zachu
A20: 15. Sujith Kumar
... A24: 19. Hannimon

Sheet Qatar
A1: Board: Qatar
A2: Chairman: Ans Sheikh | CEO: Ebad Malik
A3: Media Sponsors: Techysphere.com
A4: Credits left:
A5: =100000+B7+C7+D7+F7+G7+H7+I7+A59+L7+R7+O7+D19 -> 5621460
A6: Players | B6: Stadium: | C6: International Series: | D6: Whitewash lose: | E6: Trophy Cabinet ( International Series) | F6: IOCF T20 WORLD CUP 🏆 : | G6: Player trade: | H6: Player limit Increased: | I6: IOCF WORLD TEST CHAMPIONSHIP 🏆: | L6: CONTINENTAL CUP 2026 🏆: ( ASIA ) | O6: ODI WORLD CUP 2026 🏆: | R6: Umpires Credits :
A7: 1. Abdul Haseeb | B7: -90000 | C7: 19000 | D7: -500 | E7: 1. Freedom Trophy ( Home ) | F7: 36100 | G7: =35000+45000-25000 -> 55000 | H7: 0 | I7: =I9+J9+K9 -> 13500 | L7: =L9 -> 453200 | O7: =O9 -> 333000 | R7: =U12+U14+U19+U21+U27+U37 -> 110500
A8: 2. Abdullah Ishtiaq | B8: Level 3 Stadiums | C8: Away( Newzealand ): 3000 bet ( Lost ) | D8: 1. Against Australia: 1 | E8: 2. Van Ghani ( Away ) | F8: Entry: -5000 | G8: 1. Jishnu to Scotland - 1000 | I8: Player Awards | J8: Match Bet Credits | K8: Entry Credits | L8: Players & Match Awards | O8: Players & Match Awards | R8: Umpire | S8: Details | T8: Total Matches | U8: Credits | V8: Points
A9: 3. Adnan Khalid | B9: West End Park | C9: Home( Srilanka) : 5000 bet ( Lost ) | E9: 3. Afghan Pak ( Home ) | F9: Players Awards: 1100 | G9: 2. Ahmed from Qatar - 2000 | I9: =K24+K27+K30+K33+K36+K39+K42+K45 -> 11500 | J9: 7000 | K9: -5000 | L9: =N11+N14+N19+N23+N27+N26 -> 453200 | O9: =Q11+Q13+Q15+Q18+Q19+Q21+Q22+Q23 -> 333000 | R9: 1. Malik Zubair | S9: T20 Tournament | T9: 2.5 | U9: =T9*6000 -> 15000 | V9: =T9*40 -> 100
A10: 4. Aman Raj Singh | B10: Lusail International Stadium | C10: Home ( England): 3000 bet ( Won ) | E10: 4. Khyber Dutch (Home) | F10: 1. Farhan Mallick | G10: 3. Ebad from Qatar - 2000 | J10: Home (India): 7000 bet (Won) | K10: Trophy Cabinet (Test) | L10: Player | M10: Award | N10: Credits | O10: Player | P10: Award | Q10: Credits | S10: Franchise League
A11: 5. Zohaib Khan Tareen | B11: Doha International Stadium | C11: Away ( South Africa): 6000 bet ( Lost ) | E11: 5. Clash of the Neighbours (Away) | F11: Economical Bowler: 1 | G11: 4. Abdul from Qatar - 2000 | J11: Away (Srilanka): 10000 bet (Won) | K11: 1. Valley Trophy A (Away) | L11: 1. Umar Shahzad | M11: Man of the match(2000): 1 | N11: 4000 | O11: 1. Suleman Haider | P11: Best Batsman(3000): 2 | Q11: 7000 | S11: KCL | T11: 1 | U11: =T11*1500 -> 1500 | V11: =T11*40 -> 40
A12: 6. Huzaifa Imran | B12: Level 2 Stadiums | C12: Away ( Australia): 7000 bet ( Lost ) | E12: 6. Freedom Jalebi Trophy (Away) | F12: • vs England: 300 | G12: 5. Abul from BD - 15000 | J12: Home (Srilanka): 10000 bet (Won) | K12: 2. Valley Trophy B (Home) | M12: Best Batsman(1000): 1 | P12: Most Sixes(1000): 1 | S12: Total Credits | U12: =U9+U11 -> 16500 | V12: =V9+V11 -> 140
A13: 7. Mudasir Ali | B13: None | C13: Away ( Netherlands): 5000 bet ( Won ) | E13: 7. Desert Derby (Away) | F13: Man of the match: 1 | G13: 6. Harsh from BD - 15000 | J13: Home (Italy): 5000 bet (Won) | K13: 3. Kabul Trophy | M13: Best Bowler(1000): 1 | O13: 2. Muhammad Touqeer | P13: Best Batsman(3000): 1 | Q13: 5000 | R13: 2. Adithya Mahajan | S13: T20 Series | T13: 0.5 | U13: =T13*3000 -> 1500 | V13: =T13*40 -> 20
A14: 8. Muhammad Ahmed Mughal | B14: Level 1 Stadiums | C14: Away ( West Indies): 3000 bet ( Lost ) | E14: 8. The Gulf Cup (Home) | F14: • vs Australia: 500 | G14: 7. Harsh to Aus - 60000 | J14: Home (West Indies): 5000 bet (Lost) | K14: 4. Desert Tulip | L14: 2. Syed Raza | M14: Man of the match(2000): 2 | N14: =7000+25000+50000+5400 -> 87400 | P14: Most Dot Balls(1000): 2 | S14: Total Credits | U14: =U13 -> 1500 | V14: =V13 -> 20
A15: 9. Umar Shahzad | B15: None | C15: Away ( Bangladesh ): 5000 bet ( Lost ) | E15: 9. ODI WC Warmup 8 (Won) | F15: 2. Malik Zubair | G15: 8. Veer from ND: 10000 | J15: Home (Netherlands): 5000 bet (Won) | K15: 5. Dunes Cup | M15: Best Batsman(1000): 4 | O15: 3. Ahmed Mughal | P15: Man of the match(5000): 1 | Q15: 9000 | R15: 3. Saad Rizwan | S15: Club Series | T15: 2 | U15: =T15*1000 -> 2000 | V15: =T15*20 -> 40
A16: 10. Syed Raza | C16: Home ( Pakistan ): 5000 bet ( Won ) | F16: • Most Sixes: 300 | G16: 9. Abul (10k) - USA CEO | J16: Home(England): 5000 bet (Won) | M16: Golden Bat Award(25000) | P16: Best Bowler(3000): 1 | S16: T20 Series | T16: 1 | U16: =T16*3000 -> 3000 | V16: =T16*40 -> 40
A17: 11. Saad Rizwan | C17: Away ( Newzealand ): 5000 bet ( Lost ) | F17: Eliminated in group stage: 10k | G17: 10. Suleman to USA - 45000 | J17: Home(Newzealand): 5000 bet (Lost) | M17: Player of the Tournament(50000) | P17: Most Dot Balls(1000): 1 | S17: Franchise League
A18: 12. Suhyl Muhammad | C18: Home (Pakistan): 5000 bet (Lost) | D18: Sponsors | G18: 11. Waleed (Chairman Afghanistan): 10k | J18: Home(Bangladesh): 5000 bet (Lost) | M18: Team of the tournament - 5400 | O18: 4. Abdul Muqeeth | P18: Man of the match(5000): 1 | Q18: 5000 | S18: QECL | T18: 2 | U18: =T18*1500 -> 3000 | V18: =T18*40 -> 80
A19: 13. Sufyan Gujjar | C19: Home (Netherlands): 4000 bet (Won) | D19: 100000 | F19: Fantasy League Winner | G19: 12. Anas to Spain: free | J19: Home(Scotland): 10000 (Lost) | L19: 3. Ahmed Mughal | M19: Man of the match(2000): 1 | N19: =3000+25000+5400 -> 33400 | O19: 5. Umar Shahzad | P19: Best Batsman(3000): 1 | Q19: 4000 | S19: Total Credits | U19: =U16+U15+U18 -> 8000 | V19: =V16+V15+V18 -> 160
A20: 14. Suman Pradhan | C20: Away (Pakistan): 5000 bet (Won) | D20: 1. Techysphere.com (Media Sponsors) | F20: Malik Zubair: 30000 | G20: 13. Touqeer to Spain: Free | J20: Away(Newzealand): 10000 (Lost) | M20: Best Bowler(1000): 1 | P20: Most Sixes(1000): 1 | R20: 4. Ebad Malik | S20: Test Tournament | T20: 1 | U20: =T20*8000 -> 8000 | V20: =T20*80 -> 80
A21: 15. SV | C21: Away(South Africa): 5000 bet (Won) | G21: 14. Muzamil to Spain: Free | M21: Golden Ball Award(25000) | O21: 6. Sufyan Gujjar | P21: Best Batsman(3000): 1 | Q21: 3000 | S21: Total Credits | U21: =U20 -> 8000 | V21: =V20 -> 80
A22: 16. Tushar Kumar | C22: Away(UAE): 3000 bet (Won) | G22: 15. Tushar from Qatar: 25000 | I22: Players Awards & Credits | M22: Team of the tournament - 5400 | O22: Group Stage Exit | Q22: 200000 | R22: 5. Ahmed Mughal | S22: T10 Series | T22: 2 | U22: =T22*2000 -> 4000 | V22: =T22*40 -> 80
C23: Away(Pakistan): 5000 bet (Lost) | I23: Player | J23: Award | K23: Credits | L23: 4. Ans Sheikh | M23: Man of the match(2000): 1 | N23: =17000+6000 -> 23000 | O23: Prediction Contest: 3rd Place | Q23: 100000 | S23: Test Tournament | T23: 1 | U23: =T23*8000 -> 8000 | V23: =T23*80 -> 80
C24: Away(West Indies): 5000 bet (Lost) | I24: 1. Malik Zubair | J24: Man of the Match: 1 (1000) | K24: 1000 | M24: Best Captain Award(15000) | S24: Franchise League
C25: Home(Ireland): 5000 bet (Won) | J25: Best Batsman: 0 (500) | M25: Team of the tournament(Captain) - 6000 | S25: IPL | T25: 1 | U25: =T25*1500 -> 1500 | V25: =T25*40 -> 40
C26: Home(Newzealand): 5000 bet (Won) | J26: Best Bowler: 0 (500) | L26: 5. Huzaifa Imran | M26: Team of the tournament - 5400 | N26: 5400 | S26: QECL | T26: 6 | U26: =T26*1500 -> 9000 | V26: =T26*40 -> 240
C27: Home(Scotland): 5000 bet (Lost) | I27: 2. Anas Asim | J27: Man of the Match: 0 (1000) | K27: 500 | L27: Champions | N27: 300000 | S27: Total Credits | U27: =U22+U23+U25+U26 -> 22500 | V27: =V22+V23+V25+V26 -> 440
J28: Best Batsman: 1 (500) | R28: 5. Mudasir Ali | S28: Club Series | T28: 2 | U28: =T28*1000 -> 2000 | V28: =T28*20 -> 40
J29: Best Bowler: 0 (500) | S29: Club Tournament | T29: 2 | U29: =T29*2000 -> 4000 | V29: =T29*20 -> 40
I30: 3. Huzaifa Imran | J30: Man of the Match: 1 (1000) | K30: 1500 | S30: ODI Tournament | T30: 1 | U30: =T30*10000 -> 10000 | V30: =T30*100 -> 100
J31: Best Batsman: 0 (500) | S31: L4i Series | T31: 2 | U31: =T31*3500 -> 7000 | V31: =T31*60 -> 120
J32: Best Bowler: 1 (500) | S32: T10 Series | T32: 1 | U32: =T32*2000 -> 2000 | V32: =T32*40 -> 40
I33: 4. Adithya Mahajan | J33: Man of the Match: 1 (1000) | K33: 2500 | S33: T20 Series | T33: 4 | U33: =T33*3000 -> 12000 | V33: =T33*40 -> 160
J34: Best Batsman: 2 (500) | S34: Test Tournament | T34: 1 | U34: =T34*8000 -> 8000 | V34: =T34*80 -> 80
J35: Best Bowler: 1 (500) | S35: Franchise League
I36: 5. Farhan Mallick | J36: Man of the Match: 1 (1000) | K36: 1500 | S36: QECL | T36: 6 | U36: =T36*1500 -> 9000 | V36: =T36*40 -> 240
J37: Best Batsman: 1 (500) | S37: Total Credits | U37: =U28+U29+U30+U36+U31+U32+U33+U34 -> 54000 | V37: =V28+V29+V30+V36+V31+V32+V33+V34 -> 820
J38: Best Bowler: 0 (500)
I39: 6. Mudasir Ali | J39: Man of the Match: 1 (1000) | K39: 1500
J40: Best Batsman: 0 (500)
J41: Best Bowler: 1 (500)
I42: 7. Ahmed Mughal | J42: Man of the Match: 1 (1000) | K42: 2000
J43: Best Batsman: 0 (500)
J44: Best Bowler: 2 (500)
I45: 8. Ans Sheikh | J45: Man of the Match: 0 (1000) | K45: 1000
J46: Best Batsman: 0 (500)
J47: Best Bowler: 2 (500)
A58: All Franchise League Credits Updates :
A59: =A61+A73+A95+A108+A133+A157+A177+A191+A220 -> 4491660
A60: THE HUNDRED :
A61: 17300
A62: 2026
A63: London Spirit | B63: Southern Brave | C63: Welsh Fire | D63: MI London | E63: Sunrisers Leeds
A64: 1. Anas Asim | B64: Team Profit: 9000 | D64: 1. Malik Zubair
A65: Salary: 1000 | B65: 1. Dr Waleed Khan | D65: Salary: 2000
B66: Salary: 2300 | D66: Champions: 5300
B67: Best Bowler: 1 ( 200 )
B68: Economical Bowler Award: 5000
B69: 2. Farhan Mallick
B70: Salary: 1500
A72: Pakistan Super League :
A73: 67270
A74: 2026
A75: LAHORE QALANDARS | B75: PINDIZ | C75: MULTAN SULTANS | D75: KARACHI KINGS | E75: QUETTA GLADIATORS | F75: HYDERABAD KINGSMEN
A76: Team Profit: 52270 | B76: Team Profit: 7700 | C76: Team Profit: 7300
A77: 1. Anas Asim | B77: 1. Waleed Khan | C77: 1. M Touqeer
A78: Direct Signing: 4000 | B78: Salary: 5000 | C78: Salary: 6000
A79: Man of the match: 1 (500) | B79: 2. Farhan Mallick | C79: 2. Huzaifa Imran
A80: Best Batsman: 2 (400) | B80: Salary: 1500 | C80: Salary: 800
A81: Champions: 4990 | B81: 3. Umar Khan | C81: 3. Sufyan
A82: 2. Saad Rizwan | B82: Salary: 1000 | C82: Salary: 500
A83: Salary: 600 | B83: Best Batsman: 1 (200)
A84: Champions: 4990
A85: 3. Adithya Mahajan
A86: Salary: 500
A87: Man of the match: 1 (500)
A88: Best Bowler: 3 (600)
A89: Best Batsman: 1 (200)
A90: Best Bowler of the Tournament: 10000
A91: Player of the Tournament: 20000
A92: Champions: 4990
A94: Big Bash League
A95: 55400
A96: 2026
A97: Adelaide Strikers | B97: Brisbane Heat | C97: Hobart Hurricanes | D97: Melbourne Renegades | E97: Melbourne Stars | F97: Perth Scorchers | G97: Sydney Sixers | H97: Sydney Thunders
A98: Team Profit: | B98: Team Profit: 18300 | C98: Team Profit: | D98: Team Profit: | E98: Team Profit: 18400 | F98: Team Profit: 3700 | G98: Team Profit: 15000 | H98: Team Profit:
B99: 1. Adithya | E99: 1. Waleed | F99: 1. Anas | G99: 1. Touqeer
B100: Salary: 10000 | E100: Salary: 2500 | F100: Salary: 3000 | G100: Salary: 3000
B101: Fair Play Award: 3100 | E101: Runners up: 6200 | F101: 2. Mudasir | G101: Man of the match: 1 (1000)
B102: 2. Adnan Abbas | E102: 2. Saad | F102: Salary: 700 | G102: Champions: 11000
B103: Salary: 1600 | E103: Salary: 3000
B104: Best Batsman: 1 (500) | E104: Best Batsman: 1 (500)
B105: Fair Play Award: 3100 | E105: Runners up: 6200
A107: Kiwi Crown League : 000
A108: =A111 -> 232365
A109: 2026
A110: All Team Profit: 0000
A111: =A114+B114+C114+D114+E114+F114+G114+H114 -> 232365
A112: Wellington Warriors | B112: Auckland Aces | C112: Canterbury Kings | D112: Otago Volts | E112: Northern Knights | F112: Central Stags | G112: Queenstown Royals | H112: Tauranga Titans
A113: Team Profit: | B113: Team Profit: | C113: Team Profit: | D113: Team Profit: | E113: Team Profit: | F113: Team Profit: | G113: Team Profit: | H113: Team Profit:
...

Sheet Scotland
A1: Board: Scotland
A2: Chairman: Ajaykumar Sajeev | CEO: Jishnu
A3: Credits left:
A4: =100000+B6+B13+C6+D6+F6+F10+G6+I6+A64+E16+L6+N6+T6+Q6 -> 17724615
A5: Players | B5: Player trade: | C5: Stadium: | D5: International Series: | E5: Trophy Cabinet ( International Series) | F5: Whitewash win: | G5: IOCF T20 WORLD CUP 🏆: | I5: IOCF WORLD TEST CHAMPIONSHIP 🏆: | L5: EMERGING TALENTS LEAGUE: | N5: CONTINENTAL CUP 2026 🏆: ( EURO ) | Q5: ODI WORLD CUP 2026 🏆: | T5: Umpires Credits :
A6: 1. Abhinand | B6: =14000-100000 -> -86000 | C6: -110000 | D6: 43000 | E6: 1. Mccullum Graveney ( Away ) | F6: 2000 | G6: 117200 | I6: =I8+J8+K8 -> 57500 | L6: 145000 | N6: =P9-101000+P12+P14+P16+P17+P18 -> 53400 | Q6: =Q8 -> 6172000 | T6: =W11+W19+W21+W25+W27+W30+W35+W38+W44 -> 180250
A7: 2. Adarsh | B7: Jishnu from Afghanistan: 1k | C7: Level 3 Stadiums | D7: Away( Westindies/Scotland): 5000 ( Lost ) | E7: 2. Macleod Bardman ( Home ) | F7: 1. Mcculim Graveney ( Away ) | G7: Entry: -5000 | H7: Players Awards: 35000 | I7: Player Awards | J7: Match Bet Credits | K7: Entry Credits | L7: Tournament Awards: | M7: Award Winners | N7: Hosting Amount: 101k | Q7: Players & Match Awards | T7: Umpire | U7: Details | V7: Total Matches | W7: Credits | X7: Points
A8: 3. Afsal OCA | B8: Kailas (Portugal Chairman): 10k | C8: Grange Cricket Stadium | D8: Away( England ): 5000 ( Lost ) | E8: 3. Coca Cola Series ( Away ) | F8: 2. Macleod Bardman ( Home ) | G8: Players Awards: 6700 | H8: 1. Hashir | I8: =K28+K31+K34+K37+K40+K43+K46+K49+K52+K55+K58+K61 -> 19500 | J8: 43000 | K8: -5000 | L8: Best Talent Discovery Board: | M8: Scotland (10000) | N8: Player | O8: Award | P8: Credits | Q8: =S10+S16+S19+S23+S26+S27+S30+S31 -> 6172000 | T8: 1. Jishnu | U8: Franchise League
A9: 4. Ajoy | B9: Arjun from West Indies: 100000 | C9: Seven Oaks Stadium | D9: Home ( pakistan): 5000 ( Lost ) | E9: 4. Euro Cup ( Away ) | F9: Whitewash lose: | G9: 1. Jishnu | H9: Most Sixes(18): 5000 | J9: Home (West Indies): 5000 bet ( Lost ) | K9: Trophy Cabinet (Test) | L9: Fair Play: | M9: Scotland(15000) | N9: 1. Jishnu | O9: Man of the match(2000): 1 | P9: 4000 | Q9: Player | R9: Award | S9: Credits | U9: 100 | V9: 1 | W9: =V9*1500 -> 1500 | X9: =V9*40 -> 40
A10: 5. Amal | B10: Akshay to Portugal: 5k | C10: Scotba Cricket Stadium | L1 FL | UP | D10: Away( Newzealand): 5000 ( Won ) | E10: 5. ODI WC Warmup 9 (Home) | F10: -1000 | G10: Man of the match : 1 | H10: 2. Shafi | J10: Away ( West Indies ): 5000 bet ( Won ) | K10: 1. Palmyra Trophy | L10: Best Captain: | M10: Amjith (20000) | O10: Best Batsman(1000): 1 | Q10: 1. Hari M | R10: Man of the match(5000): 2 | S10: =26000+500000+800000+1000000 -> 2326000 | U10: SPL | V10: 6 | W10: =V10*1500 -> 9000 | X10: =V10*40 -> 240
A11: 6. Amjith | C11: K.M Cricket Arena | D11: Home ( Australia): 5000 ( Won ) | E11: 6. Friends Cup (Away) | F11: 1. Thistle shaheen ( Home ) | G11: • vs South Africa: 500 | H11: Best Bowler: 10000 | J11: Away (Italy): 5000 bet (Won) | K11: 2. Mediterranean Saltire | L11: Champions: | M11: 100000 | O11: Best Bowler(1000): 1 | R11: Best Batsman(3000): 4 | U11: Total Credits | W11: =W9+W10 -> 10500 | X11: =X9+X10 -> 280
A12: 7. Anandhu | B12: Player limit increased: | C12: Level 2 Stadiums | D12: Away ( SL, Pak, WI): 6000 ( Won ) | E12: World T20 Champions 2026 | F12: 2. Crescent Carnage ( Home ) | G12: Economical bowler: 2 | H12: Man of the Tournament: 20000 | J12: Away (Newzealand): 5000 bet ( Won ) | K12: 3. Kiwi Thistle | N12: 2. Shukoor | O12: Man of the match(2000): 1 | P12: 3000 | R12: Most Sixes(1000): 4 | T12: 2. Kebin | U12: T10 Series | V12: 3 | W12: =V12*2000 -> 6000 | X12: =V12*40 -> 120
A13: 8. Ansar | B13: -30000 | C13: None | D13: Home ( Pakistan ): 10000 ( Lost ) | G13: • vs Scotland: 300 | J13: Home (Newzealand): 5000 bet (Won) | K13: 4. Celtic Kiwi | O13: Best Batsman(1000): 1 | R13: Most Sixes in the tournament: 500000 | U13: T20 Series | V13: 1 | W13: =V13*3000 -> 3000 | X13: =V13*40 -> 40
A14: 9. Anoop MK | B14: 1. 20 to 25: 10000 | C14: Level 1 Stadiums | D14: Away ( Srilanka ): 5000 ( Lost ) | G14: • vs Afghanistan: 300 | H14: Champions: 80000 | J14: Away (Bangladesh): 5000 bet (Lost) | K14: 5. Highland Tigers | N14: 3. Kebin | O14: Man of the match(2000): 1 | P14: =1000+5400 -> 6400 | R14: Best Batsman of the tournament: 800000 | U14: Test Tournament | V14: 2 | W14: =V14*8000 -> 16000 | X14: =V14*80 -> 160
A15: 10. Arjun Raj R | B15: 2. 25 to 30: 10000 | C15: None | D15: Away ( Netherlands ): 5000 ( Won ) | E15: IOCF LONE WARRIOR | G15: • vs South Africa: 300 | J15: Home (Bangladesh): 5000 bet (Won) | K15: 6. Madsen Berrington | O15: Team of the tournament - 5400 | R15: Man of the tournament: 1000000 | U15: ODI Tournament | V15: 7 | W15: =V15*10000 -> 70000 | X15: =V15*100 -> 700
A16: 11. Arshad | B16: 3. 30 to 35: 10000 | D16: Home(South Africa): 5000 (Won) | E16: 10000 | G16: 2. Shafi | H16: Prediction 4th Place: 5000 | J16: Away(Scotland): 3000 bet (Lost) | K16: 7. The Ravana Cup | N16: 4. Ashiqui Ashi | O16: Best Bowler(1000): 1 | P16: 1000 | Q16: 2. Arjun Raj | R16: Man of the match(5000): 1 | S16: 10000 | U16: Franchise League
A17: 12. Arshad N | D17: Away(Qatar): 5000 (Won) | E17: Semifinalit: Abhinand | G17: Man of the match : 4 | J17: Home (Italy): 5000 bet (Won) | K17: 8. Latitude Clash | N17: Official Host | P17: 100000 | R17: Best Bowler(3000): 1 | U17: QECL | V17: 1 | W17: =V17*1500 -> 1500 | X17: =V17*40 -> 40
A18: 13. Ashiqui Ashi | G18: • vs Afghanistan: 500 | J18: Home(Australia): 5000 bet (Lost) | K18: 9. Highland Falcons | N18: Fair Play Award | P18: 40000 | R18: Most Dot Balls(1000): 2 | U18: SPL | V18: 14 | W18: =V18*1500 -> 21000 | X18: =V18*40 -> 560
A19: 14. Ashith S | G19: • vs India: 500 | J19: Away(Australia): 5000 bet (Lost) | K19: 10. Falcons–Thistles Test | Q19: 3. Ajay Kumar Sajeev | R19: Best Bowler(3000): 2 | S19: 707000 | U19: Total Credits | W19: =W12+W13+W14+W15+W18+W17 -> 117500 | X19: =X12+X13+X14+X15+X18+X17 -> 1620
A20: 15. Asthu Mohammad | G20: • vs Newzealand: 500 | J20: Away(Srilanka): 6000 bet (Won) | K20: 11. Lions–Thistles Test | R20: Most Dot Balls(1000): 1 | T20: 3. Resham Das | U20: T20 Series | V20: 1 | W20: =V20*3000 -> 3000 | X20: =V20*40 -> 40
A21: 16. Athul | G21: • vs India(Semis): 500 | J21: Away(UAE): 5000 bet (Won) | R21: Best Bowling Economy: 200000 | U21: Total Credits | W21: =W20 -> 3000 | X21: =X20 -> 40
A22: 17. Bijoy | G22: Economical bowler: 1 | J22: Home(UAE): 5000 bet (Won) | R22: Most Maidens: 500000 | T22: 4. Akshay | U22: Franchise League
A23: 18. Blesson Devassi | G23: • vs India: 300 | J23: Away(Qatar): 10000 (Won) | Q23: 4. Shukoor | R23: Man of the match(5000): 1 | S23: 12000 | U23: SPL | V23: 1.5 | W23: =V23*1500 -> 2250 | X23: =V23*40 -> 60
A24: 19. Chappy MK | G24: Most sixes: 1 | J24: Away(England): 10000 (Won) | R24: Best Batsman(3000): 3 | U24: T20 Series | V24: 1 | W24: =V24*3000 -> 3000 | X24: =V24*40 -> 40
A25: 20. Dingan | G25: • vs India(Semis): 300 | R25: Most Sixes(1000): 2 | U25: Total Credits | W25: =W24+W23 -> 5250 | X25: =X24+X23 -> 100
A26: 21. Ershad | G26: 3. Hashir | I26: Players Awards & Credits | Q26: 5. Amal | R26: Best Bowler(3000): 1 | S26: 3000 | T26: 5. Kailas | U26: ODI Tournament | V26: 0.5 | W26: =V26*10000 -> 5000 | X26: =V26*100 -> 50
A27: 22. Hari M | G27: Most sixes: 3 | I27: Player | J27: Award | K27: Credits | Q27: 6. Hashir | R27: Man of the match(5000): 2 | S27: 14000 | U27: Total Credits | W27: =W26 -> 5000 | X27: =X26 -> 50
A28: 23. Harishankar | G28: • vs Afghanistan: 300 | I28: 1. Irshad Bekal | J28: Man of the Match: 4 (1000) | K28: 5000 | R28: Best Bowler(3000): 1 | T28: 6. Ajay | U28: Franchise League
A29: 24. Hashir | G29: • vs India: 300 | J29: Best Batsman: 1 (500) | R29: Most Dot Balls(1000): 1 | U29: SPL | V29: 1.5 | W29: =V29*1500 -> 2250 | X29: =V29*40 -> 60
A30: 25. Huzain Muhammad | G30: • vs South Africa: 300 | J30: Best Bowler: 1 (500) | Q30: Champions | S30: 3000000 | U30: Total Credits | W30: =W29 -> 2250 | X30: =X29 -> 60
A31: 26. Irshad Bekal | G31: 4. Shukoor | I31: 2. Thesbeer | J31: Man of the Match: 0 (1000) | K31: 500 | Q31: Prediction Contest: 4th Place | S31: 100000 | T31: 7. Hashir | U31: T10 Series | V31: 1 | W31: =V31*2000 -> 2000 | X31: =V31*40 -> 40
A32: 27. Jasheer V | G32: Most sixes: 1 | J32: Best Batsman: 0 (500) | U32: ODI Series | V32: 1 | W32: =V32*5000 -> 5000 | X32: =V32*100 -> 100
A33: 28. Kebin | G33: • vs India(Semis): 300 | J33: Best Bowler: 1 (500) | U33: Franchise League
A34: 29. Libin Thomas | G34: 5. Irshad Bekal | I34: 3. Hashir | J34: Man of the Match: 1 (1000) | K34: 1500 | U34: SPL | V34: 8 | W34: =V34*1500 -> 12000 | X34: =V34*40 -> 320
A35: 30. MS | G35: Most sixes: 1 | J35: Best Batsman: 0 (500) | U35: Total Credits | W35: =W34+W31+W32 -> 19000 | X35: =X34+X31+X32 -> 460
A36: 31. Rojo | G36: • vs England(Final): 500 | J36: Best Bowler: 1 (500) | T36: 8. Sufaid | U36: Franchise League
A37: 32. Sajith | G37: 6. Kebin | I37: 4. Ershad | J37: Man of the Match: 0 (1000) | K37: 500 | U37: SPL | V37: 0.5 | W37: =V37*1500 -> 750 | X37: =V37*40 -> 20
A38: 33. Salimax | G38: Man of the match : 1 | J38: Best Batsman: 1 (500) | U38: Total Credits | W38: =W37 -> 750 | X38: =X37 -> 20
A39: 34. Shaheen | G39: • vs England(Final): 1000 | J39: Best Bowler: 0 (500) | T39: 9. Irshad | U39: T20 Series | V39: 0.5 | W39: =V39*3000 -> 1500 | X39: =V39*40 -> 20
A40: 35. Shehinsha | I40: 5. Ashith | J40: Man of the Match: 0 (1000) | K40: 1000 | U40: Club Series | V40: 2 | W40: =V40*1000 -> 2000 | X40: =V40*20 -> 40
A41: 36. Shinu | J41: Best Batsman: 2 (500) | U41: Franchise League
A42: 37. Shukoor | J42: Best Bowler: 0 (500) | U42: SPL | V42: 6 | W42: =V42*1500 -> 9000 | X42: =V42*40 -> 240
A43: 38. Sufaid | I43: 6. Asthu | J43: Man of the Match: 1 (1000) | K43: 2000 | U43: QECL | V43: 3 | W43: =V43*1500 -> 4500 | X43: =V43*40 -> 120
A44: 39. Thanvin | J44: Best Batsman: 2 (500) | U44: Total Credits | W44: =W42+W39+W40+W43 -> 17000 | X44: =X42+X39+X40+X43 -> 420
A45: 40. Thebseer | J45: Best Bowler: 0 (500)
A46: 41. Vivek | I46: 7. Salimax | J46: Man of the Match: 0 (1000) | K46: 1000
A47: 42. Yadhu | J47: Best Batsman: 2 (500)
A48: 43. Zuhaid Mohd | J48: Best Bowler: 0 (500)
I49: 8. AjayKumar Sajeev | J49: Man of the Match: 2 (1000) | K49: 3500
J50: Best Batsman: 0 (500)
J51: Best Bowler: 3 (500)
I52: 9. Jishnu | J52: Man of the Match: 1 (1000) | K52: 1500
J53: Best Batsman: 0 (500)
J54: Best Bowler: 1 (500)
I55: 10. Hari | J55: Man of the Match: 0 (1000) | K55: 500
J56: Best Batsman: 1 (500)
J57: Best Bowler: 0 (500)
I58: 11. Sufaid | J58: Man of the Match: 1 (1000) | K58: 1000
J59: Best Batsman: 0 (500)
J60: Best Bowler: 0 (500)
I61: 12. Arjun Raj | J61: Man of the Match: 1 (1000) | K61: 1500
J62: Best Batsman: 0 (500)
A63: All Franchise League Credits Updates : | J63: Best Bowler: 1 (500)
A64: =A71+A86+A110+A126+A144+A226+A194+A256 -> 11071265
A65: THE HUNDRED : 000
A66: 2026
A67: London Spirit | B67: Southern Brave | C67: Welsh Fire | D67: MI London | E67: Sunrisers Leeds
A68: No one is playing: They will concetrate on series
A70: Pakistan Super League :
A71: 16940
A72: 2026
A73: LAHORE QALANDARS | B73: PINDIZ | C73: MULTAN SULTANS | D73: KARACHI KINGS | E73: QUETTA GLADIATORS | F73: HYDERABAD KINGSMEN
B74: Team Profit: 3800 | C74: Team Profit: 4000 | E74: Team Profit: 9140
B75: 1. Jishnu | C75: 1. Ashique Ashi | E75: 1. Shafi
B76: Salary: 3800 | C76: Salary: 4000 | E76: Salary: 3000
E77: Fair Play: 1380
E78: 2. Shukoor
E79: Salary: 500
E80: Fair Play: 1380
E81: 3. Huzain
E82: Salary: 1500
E83: Fair Play: 1380
A85: Big Bash League :
A86: 95600
A87: 2026
A88: All Team Profit: 95600
A89: Adelaide Strikers | B89: Brisbane Heat | C89: Hobart Hurricanes | D89: Melbourne Renegades | E89: Melbourne Stars | F89: Perth Scorchers | G89: Sydney Sixers | H89: Sydney Thunders
A90: Team Profit: 10000 | B90: Team Profit: 3600 | C90: Team Profit: 500 | D90: Team Profit: 4500 | E90: Team Profit: 2200 | F90: Team Profit: | G90: Team Profit: 68100 | H90: Team Profit: 500
A91: 1. Hashir | B91: 1. Kebin | C91: 1. Ashith | D91: 1. AjayKumar | E91: 1. Irshad | G91: 1. Ashiqui | H91: 1. Rojo
A92: Salary: 5000 | B92: Salary: 500 | C92: Salary: 500 | D92: Salary: 4000 | E92: Salary: 1200 | G92: Salary: 6000 | H92: Salary: 500
A93: Best Batsman: 1 (500) | B93: Fair Play Award: 3100 | D93: Best Batsman: 1 (500) | E93: Man of the Match: 1 (1000) | G93: Champions: 11000
A94: 2. Jishnu | E94: Runners up: 6200 | G94: 2. Thebseer
A95: Salary: 4000 | G95: Salary: 2500
A96: Best Bowler: 1 (500) | G96: Champions: 11000
G97: 3. Shaheen
G98: Salary: 2000
G99: Champions: 11000
G100: 4. Salimax
G101: Salary: 1600
G102: Best Batsman: 1 (500)
...

Sheet SA
A1: Board: South Africa
A2: Chairman: Srinidhi & Donald Baghwar
A3: Credits left:
A4: JERSEY SPONSORS: Cricket Bhu
A5: MEDIA SPONSORS: Cricket with Mit
A6: =100000+C8+B8+A46+D8+F8+I8+O8+L8+B21 -> 5181100
A7: Players: | B7: Stadium: | C7: Traded Players: | D7: International Series: | E7: Trophy Cabinet ( International series) | F7: IOCF WORLD TEST CHAMPIONSHIP 🏆: | I7: CONTINENTAL CUP 2026 🏆: ( OCEANIA ) | L7: ODI WORLD CUP 2026 🏆: | O7: Umpires Credits :
A8: 1. Aditya Mahajan | B8: -60000 | C8: =200000-55000-100000 -> 45000 | D8: -5000 | E8: 1. UAE - SA Elite Series (Away) | F8: =F10+G10+H10 -> 57500 | I8: =I10 -> 27300 | L8: =L10 -> 2272000 | O8: =R14+R16+R20 -> 21500
A9: 2. Anshuman Mishra | B9: Level 3 Stadiums | C9: 1. Bhavin from BD - 2500 | D9: Home(Afghanistan): 5000 bet (Lost) | E9: 2. Rhino - Bear Cup (Home) | F9: Player Awards | G9: Match Bet Credits | H9: Entry Credits | I9: Players & Match Awards | L9: Players & Match Awards | O9: Umpire | P9: Details | Q9: Total Matches | R9: Credits | S9: Points
A10: 3. Bhavesh B | B10: Newlands Cricket Stadium | C10: 2. Raksh from BD - 2500 | D10: Away(Bangladesh): 5000 bet (Lost) | F10: =H26+H29+H32+H35+H38+H41 -> 12500 | G10: 50000 | H10: -5000 | I10: =K12+K15+K17 -> 27300 | L10: =N12+N14+N17+N18+N21+N23+N25+N28+N30+N31+N32 -> 2272000 | O10: 1. K Srinidhi | P10: Club Series | Q10: 1 | R10: =Q10*1000 -> 1000 | S10: =Q10*20 -> 20
A11: 4. Bhavin Kumar | B11: Wanderers International Stadium | C11: 3. Saketh from BD - 2500 | D11: Away(UAE): 5000 Bet (Won) | G11: Home(Italy): 5000 bet (Lost) | H11: Trophy Cabinet (Test) | I11: Player | J11: Award | K11: Credits | L11: Player | M11: Award | N11: Credits | P11: T10 Series | Q11: 1 | R11: =Q11*2000 -> 2000 | S11: =Q11*40 -> 40
A12: 5. Dheeraj Shastri | B12: Level 2 Stadiums | C12: 4. Bhavesh from BD - 2500 | D12: Away(England): 5000 (Lost) | G12: Home(West Indies): 5000 bet (Won) | H12: 1. Sky Bound | I12: 1. Kaushik Kalita | J12: Best Batsman(1000): 2 | K12: =9500+5400 -> 14900 | L12: 1. Siddharth V Jain | M12: Man of the match(5000): 1 | N12: 8000 | P12: ODI Tournament | Q12: 0.5 | R12: =Q12*10000 -> 5000 | S12: =Q12*100 -> 50
A13: 6. Girish Ranjan | B13: None | C13: 5. Mahi from Aus - 2500 | D13: Home(Canada): 5000 (Lost) | G13: Away(West Indies): 5000 bet (Won) | H13: 2. Earth Bound | J13: Emerging Player Award | M13: Best Batsman(3000): 1 | P13: Test Series | Q13: 0.5 | R13: =Q13*4000 -> 2000 | S13: =Q13*80 -> 40
A14: 7. Jibin Althaf | B14: Level 1 Stadiums | C14: 6. K Rakesh from Aus - 2500 | D14: Home(Srilanka): 5000 (Won) | G14: Home(India): 5000 bet (Won) | H14: 3. Heritage Trophy | J14: Team of the tournament - 5400 | L14: 2. Shajahan | M14: Man of the match(5000): 2 | N14: 24000 | P14: Total Credits | R14: =R10+R11+R12+R13 -> 10000 | S14: =S10+S11+S12+S13 -> 150
A15: 8. Kamlesh Choudhary | B15: None | C15: 7. Shibasis from NZ - 5000 | D15: Away(Scotland): 5000 (Lost) | G15: Away(India): 5000 bet (Won) | H15: 4. Bungle in The Jungle | I15: 2. Siddharth V Jain | J15: Man of the match(2000): 1 | K15: 3000 | M15: Best Batsman(3000): 4 | O15: 2. Rahul Mohapatra | P15: ODI Series | Q15: 0.5 | R15: =Q15*5000 -> 2500 | S15: =Q15*100 -> 50
A16: 9. Kaushik Jagadeesan | C16: 8. Adithya from BD - 15000 | G16: Away(Srilanka): 5000 bet (Won) | H16: 5. Legends of the Lion Test | J16: Best Bowler(1000): 1 | M16: Most Sixes(1000): 2 | P16: Total Credits | R16: =R15 -> 2500 | S16: =S15 -> 50
A17: 10. K Rakesh | C17: 9. Saubhagya (Trade Issue) - 20000 | G17: Home(Srilanka): 10000 (Won) | H17: 6. Proteas–Lions Test | I17: 3. Shibasis | J17: Man of the match(2000): 1 | K17: =4000+5400 -> 9400 | L17: 3. Saubhagya Gupta | M17: Best Bowler(3000): 1 | N17: 3000 | O17: 3. Rakshith Shetty | P17: Club Series | Q17: 1 | R17: =Q17*1000 -> 1000 | S17: =Q17*20 -> 20
A18: 11. Mahi Mahendra | C18: 10. Sid to BD: 100000 | G18: Home(UAE): 10000 (Won) | H18: 7. Proteas–Desert Test | J18: Best Batsman(1000): 1 | L18: 4. K Rakesh | M18: Man of the match(5000): 1 | N18: 10000 | P18: ODI Tournament | Q18: 0.5 | R18: =Q18*10000 -> 5000 | S18: =Q18*100 -> 50
A19: 12. Manish Kumar | C19: 11. Kaushik to BD: 100000 | G19: Away(Bangladesh): 10000 (Won) | H19: 8. The Rainbow Bengal | J19: Best Bowler(1000): 1 | M19: Best Bowler(3000): 1 | P19: T20 Series | Q19: 1 | R19: =Q19*3000 -> 3000 | S19: =Q19*40 -> 40
A20: 13. Naman Mahajan | B20: Sponsors | C20: 12. Zamam from USA: 100000 | J20: Team of the tournament - 5400 | M20: Most Dot Balls(1000): 2 | P20: Total Credits | R20: =R18+R17+R19 -> 9000 | S20: =S18+S17+S19 -> 110
A21: 14. Parth Inamdar | B21: 200000 | L21: 5. Bhavin Kumar | M21: Best Bowler(3000): 1 | N21: 4000
A22: 15. Rahul Mohapatra | B22: 1. Cricket Bhu (Jersey Sponsors) | M22: Most Dot Balls(1000): 1
A23: 16. Rakshith Raksh | B23: 2. Cricket with Mit (Media Sponsors) | L23: 6. Donald Baghwar | M23: Man of the match(5000): 1 | N23: 8000
A24: 17. Rakshith Shetty | F24: Players Awards & Credits | M24: Best Bowler(3000): 1
A25: 18. Saketh B | F25: Player | G25: Award | H25: Credits | L25: 7. Adithya Mahajan | M25: Man of the match(5000): 1 | N25: 11000
A26: 19. Saubhagya Gupta | F26: 1. K Rakesh | G26: Man of the Match: 5 (1000) | H26: 7000 | M26: Best Batsman(3000): 1
A27: 20. Shahjahan | G27: Best Batsman: 2 (500) | M27: Best Bowler(3000): 1
A28: 21. Shiva Teja | G28: Best Bowler: 2 (500) | L28: 8. Kaushik Kalita | M28: Best Batsman(3000): 1 | N28: 4000
A29: 22. Susheel Teja | F29: 2. Kaushik | G29: Man of the Match: 0 (1000) | H29: 500 | M29: Most Sixes(1000): 1
A30: 23. Zamam Usmani | G30: Best Batsman: 1 (500) | L30: 9. Bhavesh B | M30: Highest Strike Rate: 200000 | N30: 200000
G31: Best Bowler: 0 (500) | L31: Runners Up | N31: 1500000
F32: 3. Bhavin Kumar | G32: Man of the Match: 1 (1000) | H32: 1500 | L32: Prediction Contest: 1st Place | N32: 500000
G33: Best Batsman: 1 (500)
G34: Best Bowler: 0 (500)
F35: 4. Saketh balne | G35: Man of the Match: 1 (1000) | H35: 1500
G36: Best Batsman: 0 (500)
G37: Best Bowler: 1 (500)
F38: 5. Naman Mahajan | G38: Man of the Match: 0 (1000) | H38: 500
G39: Best Batsman: 1 (500)
G40: Best Bowler: 0 (500)
F41: 6. Bhavesh B | G41: Man of the Match: 1 (1000) | H41: 1500
G42: Best Batsman: 1 (500)
G43: Best Bowler: 0 (500)
A45: All leagues Profit
A46: =A48+A70+A98+A120+A138+A159 -> 2522800
A47: Kiwi Crown League :
A48: =A51 -> 25150
A49: 2026
A50: All Team Profit: 40000
A51: =A54+B54+C54+D54+E54+F54+G54+H54 -> 25150
A52: Wellington Warriors | B52: Auckland Aces | C52: Canterbury Kings | D52: Otago Volts | E52: Northern Knights | F52: Central Stags | G52: Queenstown Royals | H52: Tauranga Titans
A53: Team Profit: | B53: Team Profit: | C53: Team Profit: | D53: Team Profit: | E53: Team Profit: | F53: Team Profit: | G53: Team Profit: | H53: Team Profit:
A54: 0 | B54: 0 | C54: 0 | D54: 0 | E54: 24400 | F54: 750 | G54: 0 | H54: 0
E55: 1. Bhavin Kumar | F55: 1. Donald | G55: 1. Srinidhi
E56: No Salary(Traded) | F56: No Salary(Traded) | G56: No Salary(Traded)
E57: Man of the match: 2 (3000) | F57: 2. Saketh Balne
E58: Best Batsman: 1 (750) | F58: No Salary(Traded)
E59: Best Bowler: 1 (750) | F59: 3. Bhavesh B
E60: Champions: 19900 | F60: No Salary(Traded)
F61: Best Batsman: 1 (750)
F62: 4. Rakshith Raksh
F63: No Salary(Traded)
A69: Bangladesh Premier League :
A70: =A73 -> 74200
A71: 2026
A72: All Team Profit:
A73: =A76+B76+C76+D76+E76+F76+G76+H76+I76+J76 -> 74200
A74: BARISAL RIVER RIDERS | B74: CHANDPUR ILLISH TITANS | C74: SYLHET EMERALD BLADES | D74: RAJSHAHI MANGO LEGION | E74: DHAKA BURIGANGA BLAZERS | F74: CHITTAGONG MARINERS | G74: MAINAMATI TITANS | H74: SONARGAON ROYALS | I74: MYMENSINGH MAVERICKS | J74: CUMILA FALCONS
A75: Team Profit: | B75: Team Profit: | C75: Team Profit: | D75: Team Profit: | E75: Team Profit: | F75: Team Profit: | G75: Team Profit: | H75: Team Profit: | I75: Team Profit: | J75: Team Profit:
A76: 18000 | B76: 47200 | C76: 0 | D76: 3000 | E76: 0 | F76: 0 | G76: 6000 | H76: 0 | I76: 0 | J76: 0
A77: 1. Rahul Mahapatra | B77: 1. Donald Baghwar Dkhar | D77: 1. Bhavesh | G77: 1. Kaushik Kalita
A78: Salary: 3000 | B78: No Salary ( Traded ) | D78: No Salary ( Traded ) | G78: Salary: 6000
A79: 2. Shiva Teja | B79: 2. Rakshith Raksh | D79: Man of the match: 1 (2000)
A80: Salary: 4000 | B80: No Salary ( Traded ) | D80: Best Batsman: 1 (1000)
A81: 3. Saketh | B81: 3. Mahi Mahendra
A82: Salary: 10000 | B82: Salary: 4500
A83: Best Bowler: 1 (1000) | B83: 4. K Rakesh
B84: Salary: 12000
B85: 5. Parth Inamdar
B86: Salary: 8500
B87: 6. Manish Kumar
B88: Salary: 3500
B89: 7. Susheel
B90: Salary: 500
B91: 8. K Srinidhi
B92: Salary: 5000
B93: 9. Shibasis
B94: Salary: 12200
B95: Best Batsman: 1 (1000)
A96: Tournament Cancelled
A97: Indian Premier League
A98: =A101 -> 212000
A99: 2026
A100: All Team Profit:
A101: =A104+B104+C104+D104+E104+F104+G104+H104+I104+J104 -> 212000
A102: CHENNAI SUPER KINGS | B102: DELHI CAPITALS | C102: GUJRAT TITANS | D102: KOLKATA KNIGHT RIDERS | E102: LUCKNOW SUPER GAINTS | F102: MUMBAI INDIANS | G102: PUNJAB KINGS | H102: RAJASTHAN ROYALS | I102: ROYAL CHALLENGERS BENGALURU | J102: SUNRISERS HYDERABAD
A103: Team Profit: | B103: Team Profit: | C103: Team Profit: | D103: Team Profit: | E103: Team Profit: | F103: Team Profit: | G103: Team Profit: | H103: Team Profit: | I103: Team Profit: | J103: Team Profit:
C104: 22000 | E104: 19500 | F104: 24500 | G104: 30500 | I104: 115500
C105: 1. Kaushik | E105: 1. Adithya Mahajan | F105: 1. Bhavesh | G105: 1. Raksh | I105: 1. Sidharth V Jain
C106: Salary: 10000 | E106: No Salary(Traded) | F106: Salary: 20000 | G106: Salary: 5000 | I106: Direct Signing: 35000
...

Sheet Spain
A1: Board: Spain
A2: Chairman: Muhammad Talha | CEO: ---
A3: Credits left:
A4: =100000+B6+A25+G6+D6+C6+F6+F11 -> 134000
A5: Players | B5: Player trade | C5: Stadium: | D5: International Series: | E5: Trophy Cabinet ( International series) | F5: Whitewash Win: | G5: Umpires Credits :
A6: 1. Muhammad Shahzad | B6: 15000 | C6: -30000 | D6: 0 | E6: 1. Emerald - Spanish Debut Cup (Away) | F6: 1000 | G6: =J11 -> 18000
A7: 2. Jalal Jalu | B7: 1. Shahzad from Aus: 5k | C7: Level 3 Stadiums | D7: 1. Away(Ireland): 5000 bet (Lost) | E7: 2. Crimson Samurai Clash | F7: 1. Crimson Samurai Clash (Home) | G7: Umpire | H7: Details | I7: Total Matches | J7: Credits | K7: Points
A8: 3. Nouraiz Abbas | B8: 2. Jalal from Pak: Free | C8: Estadi de Cricket | D8: 2. Away(Canada & Kenya): 5000 bet (Lost) | G8: 1. Furqan Rasheed | H8: Club Series | I8: 1 | J8: =I8*1000 -> 1000 | K8: =I8*20 -> 20
A9: 4. Irfan Ali | B9: 3. Nouraiz from Pak: Free | C9: Level 2 Stadiums | D9: 3. Home(USA): 7000 bet (Lost) | H9: T20 Series | I9: 5 | J9: =I9*3000 -> 15000 | K9: =I9*40 -> 200
A10: 5. SK Haseeb Ali | B10: 4. Haseeb from Pak: Free | C10: None | D10: 4. Away(Italy): 3000 (Lost) | F10: Whitewash loss: | H10: T10 Series | I10: 1 | J10: =I10*2000 -> 2000 | K10: =I10*40 -> 40
A11: 6. Furqan Rasheed | B11: 5. Furqan from PNG: 5k | C11: Level 1 Stadiums | D11: 5. Home(Japan): 5000 (Won) | F11: 0 | H11: Total Credits | J11: =J9+J8+J10 -> 18000 | K11: =K9+K8+K10 -> 260
A12: 7. Ghamshad Kapri | B12: 6. Gamshad from BD: Free | C12: None
A13: 8. Abdul Rehman Yaseen | B13: 7. Fraz from Kenya: 5000
A14: 9. Ejas Ahammed | B14: 8. Anas from Qatar: Free
A15: 10. Safeer Chepzy | B15: 9. Touqeer from Qatar: Free
A16: 11. Najam | B16: 10. Muzammil from Qatar: Free
A17: 12. Fraz Ali | B17: 11. Tushar to Qatar: 25000
A18: 13. Anas Asim | B18: 12. Ishaq from PNG: 5000
A19: 14. Muhammad Touqeer
A20: 15. Muzammil Zafar
A21: 16. Ishaq Ahmed
A24: All Franchise League Credits Updates :
A25: =A27 -> 30000
A26: Qatar Elite Crown League :
A27: =A30 -> 30000
A28: 2026
A29: All Team Profit:
A30: =A33+B33+C33+D33+E33+F33+G33+H33 -> 30000
A31: AL KHOR PREDATORS | B31: AL RAYYAN RAIDERS | C31: AL WAKRAH DUKES | D31: DOHA STALLIONS | E31: LUSAIL KNIGHTS | F31: MESAEID BLAZE | G31: QATAR VENOMS | H31: UMM SALAL SPARTANS
A32: Team Profit: | B32: Team Profit: | C32: Team Profit: | D32: Team Profit: | E32: Team Profit: | F32: Team Profit: | G32: Team Profit: | H32: Team Profit:
A33: 0 | B33: 0 | C33: 0 | D33: 25000 | E33: 5000 | F33: 0 | G33: 0 | H33: 0
D34: 1. Muhammad Shahzad | E34: 1. Muhammad Talha
D35: No salary(Traded) | E35: No salary(Traded)
D36: Man of the match: 1 (10000) | E36: Best Bowler: 1 (5000)
D37: 2. Jalal Jalu
D38: No salary(Traded)
D39: Best Bowler: 2 (5000)
D40: 3. Ghamshad Kapri
D41: No salary(Traded)
D42: Best Batsman: 1 (5000)

Sheet Srilanka
A1: Board: SRILANKA
A2: Chairman: Damitha Naranpanawa | CEO: Thilanga Dumindu
A3: Credits left:
A4: =100000+B6+C6+E6+F6+G6+A34+J6+M6 -> 1654300
A5: Players | B5: Stadium: | C5: International Series: | D5: Trophy Cabinet ( International series) | E5: IOCF T20 WORLD CUP 🏆 : | F5: Whitewash win: | G5: IOCF WORLD TEST CHAMPIONSHIP 🏆: | J5: CONTINENTAL CUP 🏆: ( ASIA ) | M5: ODI WORLD CUP 2026 🏆: ( ASIA ) | P5: Umpires Credits :
A6: 1. Asiri | B6: -60000 | C6: 88000 | D6: 1. Colombo Cup ( Home ) | E6: 16400 | F6: 1000 | G6: =G8+H8+I8 -> -7500 | J6: =J8 -> 8000 | M6: =M8 -> 532000 | P6: =S12+S14+S16 -> 30500
A7: 2. Binara | B7: Level 3 Stadiums | C7: Home( Pakistan ): 6000 bet ( Won ) | D7: 2. Revival Cup ( Away ) | E7: Entry: -5000 | F7: 1. Eagles Trophy ( Home ) | G7: Player Awards | H7: Match Bet Credits | I7: Entry Credits | J7: Players & Match Awards | M7: Players & Match Awards | P7: Umpire | Q7: Details | R7: Total Matches | S7: Credits | T7: Points
A8: 3. Chalana Rukshan | B8: Colombo International Stadium | C8: Away( Afghanistan): 5000 bet ( Won ) | D8: 3. Blue Rivalry cup ( Home ) | E8: Players Awards: 1400 | G8: =I24+I27+I30+I33+I36+I39+I42+I45 -> 9500 | H8: -12000 | I8: -5000 | J8: =L10+L12+L13+L14+L15 -> 8000 | M8: =O10+O13+O17+O18+O20+O22+O23+O24 -> 532000 | P8: 1. Damitha N | Q8: Club Series | R8: 18 | S8: =R8*1000 -> 18000 | T8: =R8*20 -> 360
A9: 4. Damith Nandana | B9: Kandy International Stadium | C9: Home( India ): 6000 bet ( Won ) | D9: 4. Emerald Isle ( Away ) | E9: 1. Virendra | H9: Home (Afghanistan ): 10000 bet (Lost) | I9: Trophy Cabinet (Test) | J9: Player | K9: Award | L9: Credits | M9: Player | N9: Award | O9: Credits | Q9: Test Tournament | R9: 1 | S9: =R9*8000 -> 8000 | T9: =R9*80 -> 80
A10: 5. Hansana De Silva | B10: Level 2 Stadiums | C10: Away( England): 5000 bet ( won ) | D10: 5. Eagles Trophy ( Home ) | E10: Most Sixes: 1 | H10: Away (Afghanistan): 10000 bet (Lost) | I10: 1. Hague Colombo | J10: 1. Miraj Cool | K10: Man of the match(2000): 1 | L10: 3000 | M10: 1. Sasith Jayawardane | N10: Man of the match(5000): 1 | O10: 10000 | Q10: Franchise League
A11: 6. Hasindu Rashminda | B11: None | C11: Home( Scot,Pak,WI): 6000 bet ( Lost ) | D11: 6. Highland Lions ( Away ) | E11: • vs India: 300 | H11: Away (Netherlands): 5000 bet (Won) | I11: 2. Island Trophy | K11: Best Bowler(1000): 1 | N11: Best Bowler(3000): 1 | Q11: KCL | R11: 1 | S11: =R11*1500 -> 1500 | T11: =R11*40 -> 40
A12: 7. Kavinda Gihan | B12: Level 1 Stadiums | C12: Home ( USA ): 5000 bet ( Won ) | D12: 7. The London Cup (Away) | E12: 2. Kavinda | H12: Home (Srilanka): 10000 bet (Won) | I12: 3. Srilanka in England | J12: 2. Hasindu Rashminda | K12: Best Batsman(1000): 2 | L12: 2000 | N12: Most Dot Balls(1000): 2 | Q12: Total Credits | S12: =S8+S9+S11 -> 27500 | T12: =T8+T9+T11 -> 480
A13: 8. Kithmewan Gimantha | B13: None | C13: Away ( Newzealand): 5000 bet ( Lost ) | D13: 8. Kingdom Trophy ( Home) | E13: Man of the match: 1 | H13: Away(England): 5000 bet (Won) | I13: 4. Lions–Shaheens Test | J13: 3. Ruwanga | K13: Best Batsman(1000): 1 | L13: 1000 | M13: 2. Rasith Wijethunga | N13: Best Batsman(3000): 1 | O13: 8000 | P13: 2. Thilanga D | Q13: Club Series | R13: 2 | S13: =R13*1000 -> 2000 | T13: =R13*20 -> 40
A14: 9. Kosala Jayasinghe | C14: Away ( Scotland ): 5000 bet ( Won ) | D14: 9. Breaking Boundaries Cup (Away) | E14: • vs Newzealand: 500 | H14: Home(Scotland): 6000 bet (Lost) | J14: 4. Damitha Naranpanawa | K14: Best Bowler(1000): 1 | L14: 1000 | N14: Best Bowler(3000): 1 | Q14: Total Credits | S14: =S13 -> 2000 | T14: =T13 -> 40
A15: 10. Miraj Cool | C15: Home (Italy): 6000 bet (Lost) | D15: 10. Austral-Asia Tri Series (Away) | E15: 3. Damitha N | H15: Away(West Indies): 6000 bet (Lost) | J15: 5. Thilanga Dumindu | K15: Best Batsman(1000): 1 | L15: 1000 | N15: Most Dot Balls(1000): 1 | P15: 3. Hasindu R | Q15: Club Series | R15: 1 | S15: =R15*1000 -> 1000 | T15: =R15*20 -> 20
A16: 11. Poorna K De Silva | C16: Away(Australia): 5000 bet (Lost) | D16: 11. ODI WC Warmup 3 (Home) | E16: Most Sixes: 1 | H16: Away(Australia): 5000 bet (Lost) | N16: Most Sixes(1000): 1 | Q16: Total Credits | S16: =S15 -> 1000 | T16: =T15 -> 20
A17: 12. Rasith Wijethunga | C17: Away(England): 5000 bet (Won) | E17: • vs Newzealand: 300 | H17: Home(South Africa): 5000 bet (Lost) | M17: 3. Ruwanga B | N17: Best Batsman(3000): 1 | O17: 3000
A18: 13. Rubesh Jude Daniel | C18: Home(West Indies): 5000 bet (Won) | E18: 4. Sasith | H18: Home(Australia): 10000 bet (Won) | M18: 4. Damitha Naranpanawa | N18: Man of the match(5000): 1 | O18: 6000
A19: 14. Ruwanga Bandarawaththa | C19: Away(West Indies): 5000 bet (Lost) | E19: Most Sixes: 1 | H19: Away(South Africa): 10000 (Lost) | N19: Most Dot Balls(1000): 1
A20: 15. Sasith Jayawardena | C20: Away(West Indies): 10000 bet (Won) | E20: • vs Pakistan: 300 | H20: Home(Pakistan): 10000 (Won) | M20: 5. Damith Nandana | N20: Best Batsman(3000): 1 | O20: 4000
A21: 16. Thilina Jayarathna | C21: Away(Australia & UAE): 15000 (Won) | E21: Eliminated in Group Stage: 10k | N21: Most Sixes(1000): 1
A22: 17. Uresh Gnananga | C22: Home(USA): 5000 (Won) | G22: Players Awards & Credits | M22: 6. Kosala | N22: Most Sixes(1000): 1 | O22: 1000
A23: 18. Virendra | C23: Away(South Africa): 5000 (Lost) | E23: Players Awards: 5000 | G23: Player | H23: Award | I23: Credits | M23: Group Stage Exit | O23: 200000
E24: 1. Virendra | G24: 1. Damitha Naranpanawa | H24: Man of the Match: 0 (1000) | I24: 1000 | M24: Fantasy League: 1st Place | O24: 300000
E25: Best Economy(2.0): 5000 | H25: Best Batsman: 0 (500)
E26: Fantasy League 4th Place | H26: Best Bowler: 2 (500)
E27: Sasith: 5000 | G27: 2. Rasith W | H27: Man of the Match: 1 (1000) | I27: 2000
H28: Best Batsman: 1 (500)
H29: Best Bowler: 1 (500)
G30: 3. Sasith J | H30: Man of the Match: 1 (1000) | I30: 1500
H31: Best Batsman: 1 (500)
H32: Best Bowler: 0 (500)
A33: All Franchise League Credits Updates : | G33: 4. Ruwanga | H33: Man of the Match: 2 (1000) | I33: 3000
A34: =A36+A52+A75+A97+A117+A138+A159+A186 -> 976400 | H34: Best Batsman: 0 (500)
A35: THE HUNDRED : | H35: Best Bowler: 2 (500)
A36: 29550 | G36: 5. Damith Nandana | H36: Man of the Match: 0 (1000) | I36: 500
A37: 2026 | H37: Best Batsman: 1 (500)
A38: London Spirit | B38: Southern Brave | C38: Welsh Fire | D38: MI London | E38: Sunrisers Leeds | H38: Best Bowler: 0 (500)
A39: 1. Thilanga Dumindu | C39: 1. Hasindu Rashminda | D39: 1. Rasith Wijethunga ( Replacement ) | E39: Team Profit: 13550 | G39: 6. Uresh G | H39: Man of the Match: 0 (1000) | I39: 500
A40: Salary: 2800 | C40: Salary: 1700 | D40: Salary: 4000 | E40: 1. Damitha Naranpanawa | H40: Best Batsman: 0 (500)
A41: 2. Sasith | D41: Champions: 5300 | E41: Salary: 2800 | H41: Best Bowler: 1 (500)
A42: Salary: 1200 | E42: Runners Up: 2850 | G42: 7. Chalana | H42: Man of the Match: 0 (1000) | I42: 500
A43: 3. Miraj Cool | E43: 2. Virendra | H43: Best Batsman: 0 (500)
A44: Salary: 1000 | E44: Salary: 1200 | H44: Best Bowler: 1 (500)
A45: 4. Damith Nandana ( Replacement ) | E45: Runners Up: 2850 | G45: 8. Thilanga | H45: Man of the Match: 0 (1000) | I45: 500
A46: Salary: 1000 | E46: 3. Kosala Jayasinghe | H46: Best Batsman: 1 (500)
E47: Salary: 1000 | H47: Best Bowler: 0 (500)
E48: Runners Up: 2850
A51: Pakistan Super League : 37140
A52: 37140
A53: 2026
A54: LAHORE QALANDARS | B54: PINDIZ | C54: MULTAN SULTANS | D54: KARACHI KINGS | E54: QUETTA GLADIATORS | F54: HYDERABAD KINGSMEN
A55: Team Profit: 11980 | B55: Team Profit: 1100 | E55: Team Profit: 18100 | F55: Team Profit: 5960
A56: 1. Miraj Cool | B56: 1. Rasith Wijetthunga | E56: 1. Thilanga Dumindu | F56: 1. Rubesh
A57: Salary: 1000 | B57: Salary: 1100 | E57: Salary: 3600 | F57: Salary: 500
A58: Champions: 4990 | E58: Fair Play: 1380 | F58: Runners up: 2480
A59: 2. Damith Nandana | E59: 2. Damitha Naranpanwa | F59: 2. Kosala
A60: Salary: 1000 | E60: Salary: 5500 | F60: Salary: 500
A61: Champions: 4990 | E61: Best Batsman: 2 ( 400 ) | F61: Runners up: 2480
E62: Fair Play: 1380
E63: 3. Virendra
E64: Salary: 500
E65: Fair Play: 1380
E66: 4. Hasindu Rashminda
E67: Salary: 500
E68: Best Bowler: 1 ( 200 )
E69: Fair Play: 1380
E70: 5. Sasith
E71: Salary: 500
E72: Fair Play: 1380
A74: Big Bash League : 25900
A75: 44500
A76: 2026
A77: All Team Profit: 44500
A78: Adelaide Strikers | B78: Brisbane Heat | C78: Hobart Hurricanes | D78: Melbourne Renegades | E78: Melbourne Stars | F78: Perth Scorchers | G78: Sydney Sixers | H78: Sydney Thunders
A79: Team Profit: 7500 | B79: Team Profit: | C79: Team Profit: | D79: Team Profit: 4500 | E79: Team Profit: 21600 | F79: Team Profit: 23400 | G79: Team Profit: | H79: Team Profit:
A80: 1. Miraj | D80: 1. Ruwanga | E80: 1. Hasana | F80: 1. Damitha Naranpanawa
A81: Salary: 1000 | D81: Salary: 3000 | E81: Salary: 2000 | F81: Direct Signing: 5000
A82: 2. Hasindu | D82: Man of the match: 1 (1000) | E82: Runners up: 6200 | F82: 2. Thilanga
A83: Salary: 3500 | D83: Best Bowler: 1 (500) | E83: 2. Thilina | F83: Salary: 14000
A84: 3. Rasith | E84: Salary: 500 | F84: 3. Virendra
A85: Salary: 2500 | E85: Runners up: 6200 | F85: Salary: 1200
A86: 4. Uresh GN | E86: 3. Rubesh | F86: 4. Damith N
A87: Salary: 500 | E87: Salary: 300 | F87: Salary: 1000
E88: Best Bowler: 1 (500) | F88: 5. Sasith
E89: Runners up: 6200 | F89: Salary: 2200
A96: Kiwi Crown League :
A97: =A100 -> 145710
A98: 2026
A99: All Team Profit:
A100: =A103+B103+C103+D103+E103+F103+G103+H103 -> 145710
A101: Wellington Warriors | B101: Auckland Aces | C101: Canterbury Kings | D101: Otago Volts | E101: Northern Knights | F101: Central Stags | G101: Queenstown Royals | H101: Tauranga Titans
A102: Team Profit: | B102: Team Profit: | C102: Team Profit: | D102: Team Profit: | E102: Team Profit: | F102: Team Profit: | G102: Team Profit: | H102: Team Profit:
A103: 8750 | B103: 20000 | C103: 14110 | D103: 0 | E103: 86600 | F103: 10250 | G103: 6000 | H103: 0
A104: 1. Hasindu Rashminda | B104: 1. Damitha N | C104: 1. Kavinda Gihan | E104: 1. Ruwanga | F104: 1. Rasith | G104: 1. Thilanga Dumindu
A105: Salary: 5000 | B105: Direct Signing: 20000 | C105: Salary: 1000 | E105: Salary: 5500 | F105: Salary: 5500 | G105: Salary: 6000
A106: Best Batsman: 1 (750) | C106: Fair Play: 5555 | E106: Champions: 19900 | F106: Best Bowler: 1 (750)
A107: 2. Sasith | C107: 2. Rubesh Jude | E107: 2. Kosala | F107: 2. Virendra
A108: Salary: 1000 | C108: Salary: 2000 | E108: Salary: 500 | F108: Salary: 3000
A109: 3. Miraj Cool | C109: Fair Play: 5555 | E109: Champions: 19900 | F109: 3. Damith Nandana
...

Sheet UAE
A1: Board: UAE
A2: Chairman: Antony John CTR | CEO: Hanish
A3: Credits left:
A4: =100000+B6+C6+E6+H6+K6+N6+Q18+A33 -> 468725
A5: Players: | B5: Stadium: | C5: International Series: | D5: Trophy Cabinet ( International series) | E5: IOCF WORLD TEST CHAMPIONSHIP 🏆: | H5: CONTINENTAL CUP 2026 🏆: ( ASIA ) | K5: ODI WORLD CUP 2026 🏆: | N5: Umpires Credits :
A6: 1. Abhijith | B6: -30000 | C6: 10000 | D6: 1. Crescent Cup (Away) | E6: =E8+F8+G8 -> -36500 | H6: =H8 -> 28400 | K6: =K8 -> 233000 | N6: =Q12+Q15+Q18 -> 39000
A7: 2. Akhil | B7: Level 3 Stadiums | C7: Away(West Indies): 5000 bet (Lost) | D7: 2. Highland Trophy (Away) | E7: Player Awards | F7: Match Bet Credits | G7: Entry Credits | H7: Players & Match Awards | K7: Players & Match Awards | N7: Umpire | O7: Details | P7: Total Matches | Q7: Credits | R7: Points
A8: 3. Alan | B8: Dubai International Stadium | C8: Home(Qatar): 3000 bet (Lost) | D8: 3. Sir Gary Sobers Remembrance Trophy (Away) | E8: =G17+G20+G23+G26+G29 -> 3500 | F8: -35000 | G8: -5000 | H8: =J10+J12+J13+J16+J17 -> 28400 | K8: =M10+M11+M12+M15+M16+M17+M18 -> 233000 | N8: 1. Jafnis | O8: Club Tournament | P8: 2 | Q8: =P8*2000 -> 4000 | R8: =P8*20 -> 40
A9: 4. Arjun | B9: Level 2 Stadiums | C9: Away(England): 5000 bet (Lost) | D9: 4. Falcon Cup (Away) | F9: Home(Scotland): 5000 bet (Lost) | G9: Trophy Cabinet (Test) | H9: Player | I9: Award | J9: Credits | K9: Player | L9: Award | M9: Credits | O9: Club Series | P9: 0.5 | Q9: =P9*1000 -> 500 | R9: =P9*20 -> 10
A10: 5. Athul | B10: None | C10: Away(Bangladesh): 5000 bet (Won) | D10: 5. Falcon Eagle Clash (Home) | F10: Away(Scotland): 5000 bet (Lost) | G10: 1. Arabian Crown Trophy | H10: 1. Tom | I10: Man of the match(2000): 1 | J10: 4000 | K10: 1. Antony John Ctr | L10: Best Batsman(3000): 2 | M10: 6000 | O10: Test Tournament | P10: 1 | Q10: =P10*8000 -> 8000 | R10: =P10*80 -> 80
A11: 6. Ayas | B11: Level 1 Stadiums | C11: Away(England): 5000 bet (Won) | D11: 6. The Falcon Eagle Clash 2.0 (Home) | F11: Home(England): 5000 bet (Won) | I11: Best Bowler(1000): 2 | K11: 2. Rahul Raj | L11: Best Batsman(3000): 1 | M11: 3000 | O11: T20 Series | P11: 1 | Q11: =P11*3000 -> 3000 | R11: =P11*40 -> 40
A12: 7. Jabir | B12: None | C12: Home(West Indies): 10000 bet (Lost) | D12: 7. The Emirates royal Cup (Home) | F12: Home(Australia): 10000 (Lost) | H12: 2. Vishnu | I12: Best Batsman(1000): 1 | J12: 1000 | K12: 3. Jafnis | L12: Man of the match(5000): 1 | M12: 10000 | O12: Total Credits | Q12: =Q8+Q9+Q10+Q11 -> 15500 | R12: =R8+R9+R10+R11 -> 170
A13: 8. Jafnis | C13: Away(West Indies): 10000 bet (Won) | D13: 8. The Indo-Emirates Cup (Away) | F13: Home(West Indies): 10000 (Lost) | H13: 3. Sebin | I13: Best Bowler(100): 1 | J13: =16000+5400 -> 21400 | L13: Best Bowler(3000): 1 | N13: 2. Thrived | O13: ODI Tournament | P13: 0.5 | Q13: =P13*10000 -> 5000 | R13: =P13*100 -> 50
A14: 9. Jin | C14: Away(Australia): 3000 bet (Won) | D14: 9. ODI WC Warmup 6 (Home) | F14: Away(South Africa): 10000 (Lost) | I14: Emerging Player Award | L14: Most Dot Balls(1000): 2 | O14: Club Series | P14: 0.5 | Q14: =P14*1000 -> 500 | R14: =P14*20 -> 10
A15: 10. Justin | C15: Home(South Africa): 5000 bet (Lost) | D15: 10. Japan UAE Friendship Series (Away) | E15: Players Awards & Credits | I15: Team of the tournament - 5400 | K15: 4. Sebin | L15: Man of the match(5000): 2 | M15: 10000 | O15: Total Credits | Q15: =Q14+Q13 -> 5500 | R15: =R14+R13 -> 60
A16: 11. Monai | C16: Away(Australia & Srilanka): 15000 (Lost) | D16: 11. BATTLE OF STORMS (Home) | E16: Player | F16: Award | G16: Credits | H16: 4. Jafnis | I16: Man of the match(2000): 1 | J16: 1000 | K16: 5. Arjun | L16: Most Sixes(1000): 1 | M16: 1000 | N16: 3. Sebin | O16: ODI Tournament | P16: 1 | Q16: =P16*10000 -> 10000 | R16: =P16*100 -> 100
A17: 12. Nikhil | C17: Home(USA): 5000 (Won) | E17: 1. Akhil | F17: Man of the Match: 0 (1000) | G17: 500 | H17: 5. Rahul Raj | I17: Best Bowler(100): 1 | J17: 1000 | K17: 6. Thrived | L17: Best Bowler(3000): 1 | M17: 3000 | O17: Test Tournament | P17: 1 | Q17: =P17*8000 -> 8000 | R17: =P17*80 -> 80
A18: 13. Rahul Raj | C18: Home(USA): 5000 (Won) | F18: Best Batsman: 1 (500) | H18: 6. Antony John CTR | I18: Best Batsman(1000): 1 | J18: =1000+5400 -> 6400 | K18: Group Stage Exit | M18: 200000 | O18: Total Credits | Q18: =Q16+Q17 -> 18000 | R18: =R16+R17 -> 180
A19: 14. Suhas | C19: Home(India): 5000 (Won) | F19: Best Bowler: 0 (500) | I19: Team of the tournament - 5400
A20: 15. Thrived | C20: Away(India): 5000 (Won) | E20: 2. Vishnu | F20: Man of the Match: 0 (1000) | G20: 500
A21: 16. Tom | C21: Home(Uganda): 5000 (Won) | F21: Best Batsman: 1 (500)
A22: 17. Vaishak | C22: Home(Zimbabwe): 5000 (Lost) | F22: Best Bowler: 0 (500)
A23: 18. Vaishnav | C23: Home(Japan): 5000 (Lost) | E23: 3. Abhijith | F23: Man of the Match: 0 (1000) | G23: 500
A24: 19. Varun | C24: Away(Japan): 5000 (Won) | F24: Best Batsman: 0 (500)
A25: 20. Vishnu | C25: Home(India): 10000 (Won) | F25: Best Bowler: 1 (500)
A26: 21. Zaheen | C26: Home(PNG): 5000 (Lost) | E26: 4. Sebin | F26: Man of the Match: 1 (1000) | G26: 1500
A27: 22. Rakesh | C27: Home(PNG): 5000 (Won) | F27: Best Batsman: 0 (500)
A28: 23. Abdu | F28: Best Bowler: 1 (500)
E29: 5. Jafnis | F29: Man of the Match: 0 (1000) | G29: 500
F30: Best Batsman: 1 (500)
F31: Best Bowler: 0 (500)
A32: All Franchise League Credits Updates :
A33: =A35 -> 106825
A34: Qatar Elite Crown League :
A35: =A38 -> 106825
A36: 2026
A37: All Team Profit:
A38: =A41+B41+C41+D41+E41+F41+G41+H41 -> 106825
A39: AL KHOR PREDATORS | B39: AL RAYYAN RAIDERS | C39: AL WAKRAH DUKES | D39: DOHA STALLIONS | E39: LUSAIL KNIGHTS | F39: MESAEID BLAZE | G39: QATAR VENOMS | H39: UMM SALAL SPARTANS
A40: Team Profit: | B40: Team Profit: | C40: Team Profit: | D40: Team Profit: | E40: Team Profit: | F40: Team Profit: | G40: Team Profit: | H40: Team Profit:
A41: =27000+59825 -> 86825 | B41: 0 | C41: 0 | D41: 0 | E41: 0 | F41: 0 | G41: 0 | H41: 20000
A42: 1. Sebin | H42: 1. Jafnis
A43: Salary: 27000 | H43: Salary: 20000
A44: Runners Up: 59825

Sheet Uganda
A1: Board: Uganda
A2: Chairman: Akhil Vijayan | CEO: Haseeb
A3: Credits left:
A4: =100000+B6+C6+D6+E6+A34+J6 -> 174825
A5: Players | B5: Stadium: | C5: International Series: | D5: Player trade: | E5: Umpires Credits : | J5: Associate Nations CUP 2026 🏆:
A6: 1. Abhimanue | B6: -30000 | C6: -20000 | D6: -5000 | E6: =H9 -> 1000 | J6: =J8 -> 5000
A7: 2. Ajwad | B7: Level 3 Stadiums | C7: Away( Canada & USA ): 5000 bet ( Lost ) | D7: 1. Midlaj from Zim: 5000 | E7: Umpire | F7: Details | G7: Total Matches | H7: Credits | I7: Points | J7: Players & Match Awards
A8: 3. Akash | B8: Mandela National Stadium | C8: Away(West Indies): 5000 bet (Lost) | E8: 2. Thrived | F8: Club Series | G8: 1 | H8: =G8*1000 -> 1000 | I8: =G8*20 -> 20 | J8: =L10+L12+L13 -> 5000
A9: 4. Akshay | B9: Level 2 Stadiums | C9: Home(Uganda): 5000 bet (Lost) | F9: Total Credits | H9: =H8 -> 1000 | I9: =I8 -> 20 | J9: Player | K9: Award | L9: Credits
A10: 5. Alen | B10: None | C10: Away(UAE): 5000 bet (Lost) | J10: 1. Noufal | K10: Man of the match (2000): 1 | L10: 3000
A11: 6. Althwaf | B11: Level 1 Stadiums | K11: Best Bowler (1000): 1
A12: 7. Anoop | B12: None | J12: 2. Vineeth Chandhu | K12: Best Batsman(1000): 1 | L12: 1000
A13: 8. Anu | J13: 3. Ayaz | K13: Best Batsman(1000): 1 | L13: 1000
A14: 9. Anumod
A15: 10. Aravind
A16: 11. Asaf
A17: 12. Ayaz
A18: 13. Hubalnas
A19: 14. Joyal
A20: 15. Jubi
A21: 16. Mallaya
A22: 17. Midlaj
A23: 18. Noufal
A24: 19. Rijoyes
A25: 20. Sahad
... A33: All Franchise League Credits Updates :
A34: =A36+A48 -> 123825
A35: Scottish Premier League
A36: =A39 -> 62000
A37: 2026
A38: All Team Profit:
A39: =A42+B42+C42+D42+E42+F42+G42+H42+I42+J42 -> 62000
A40: ABERDEEN TITANS | B40: DUNDEE WARRIORS | C40: EDINBURGH ROYALS | D40: GLASGOW GIANTS | E40: HIGHLAND HAWKS | F40: INVERNESS EAGLES | G40: LOTHIAN LIONS | H40: PERTH PANTHERS | I40: STIRLING KNIGHTS | J40: TARTAN STRIKERS
A41: Team Profit: | B41: Team Profit: | C41: Team Profit: | D41: Team Profit: | E41: Team Profit: | F41: Team Profit: | G41: Team Profit: | H41: Team Profit: | I41: Team Profit: | J41: Team Profit:
A42: 0 | B42: 0 | C42: 0 | D42: 0 | E42: 0 | F42: 0 | G42: 0 | H42: 0 | I42: 0 | J42: =5000+57000 -> 62000
J43: 1. Akhil Vijayan
J44: No Salary(Traded)
J45: Best Batsman: 1 (5000)
J46: Runners Up: 57000
A47: Qatar Elite Crown League :
A48: =A51 -> 61825
A49: 2026
A50: All Team Profit:
A51: =A54+B54+C54+D54+E54+F54+G54+H54 -> 61825
